Workbook
Name TASK: #REF!

Sheet KH Solar Plan
A2: FY 2024-25 | Khavda Solar Projects Monthly Commissioning Plan (MWac) | AH2: For Internal Purpose | AP2: 45747
A3: Priority | B3: Project | C3: SPV | D3: Plot No | E3: Plot No GP | F3: Category | G3: Category | H3: MMS Type | I3: Module Source | J3: Module Wp | K3: Capacity (MWac) | L3: OL | M3: Capacity (MWdc) | O3: PSS No. | P3: PSS Charging Date | Q3: SCOD | R3: Commissioning as per Growth Plan | S3: Plot Head | T3: Commissioning as per Growth Plan (R5 - 08-Feb-25) | U3: Capex BOQ Release Date | V3: LTA Phase | W3: Expected LTA Operationalization | X3: Plant Code | Y3: SUPPLY Plant Code | Z3: SERVICE Plant Code | AA3: Commissioning as per Growth Plan | AB3: Charging Start | AC3: Charging Finish | AE3: Capex NFA Status | AF3: 45748 | AG3: 45778 | AH3: 45809 | AI3: 45839 | AJ3: 45870 | AK3: 45901 | AL3: 45931 | AM3: 45962 | AN3: 45992 | AO3: 46023 | AP3: 46054 | AQ3: 46082 | AR3: Total (MW)
A4: 10 | B4: AGEL Merchant | C4: ARE56L | D4: S-08 | F4: Merchant | G4: Merchant | H4: HSAT | K4: 400 | L4: 1.37 | M4: 548 | O4: PSS-09 | P4: Charged | S4: Arvind Kulshrestha | T4: 45717 | AF4: 150 | AG4: 100 | AR4: =SUM(AF4:AQ4) -> 250
A5: 13 | B5: AGEL Merchant | C5: ARE56L | D5: A-02 | F5: Merchant | G5: Merchant | H5: HSAT | K5: 225 | L5: 1.37 | M5: 308.25 | O5: PSS-04 | P5: Charged | S5: Akhil Agarwal | T5: 45717 | AF5: 50 | AR5: =SUM(AF5:AQ5) -> 50
A6: 11 | B6: MLP AP New | C6: ARE57L | D6: A-11 | F6: PPA | G6: PPA | H6: HSAT | K6: 500 | L6: 1.36 | M6: 680 | O6: PSS-13 | P6: Charged | S6: Salim Beg | T6: 45717 | AF6: 187.5 | AR6: =SUM(AF6:AQ6) -> 187.5
A7: 12 | B7: MLP AP New | C7: ARE57L | D7: A-12 | F7: PPA | G7: PPA | H7: HSAT | K7: 350 | L7: 1.35 | M7: =L7*K7 -> 472.5 | O7: PSS-13 | P7: Charged | S7: Bikash Kumar | T7: 45717 | AH7: 100 | AI7: 250 | AR7: =SUM(AF7:AQ7) -> 350
A8: 14 | B8: SECI H-3 | C8: AHEJ5L | D8: A-13 | F8: PPA | G8: PPA | H8: FT | K8: 570 | L8: 1.4 | M8: 798 | O8: PSS-05 | P8: Charged | S8: Syed Ali | T8: 45717 | AF8: 295 | AH8: 275 | AR8: =SUM(AF8:AQ8) -> 570
A9: 15 | B9: AGEL Merchant | C9: ARE45L | D9: A-14 | F9: Merchant | G9: Merchant | H9: HSAT | K9: 250 | L9: 1.37 | M9: 342.5 | O9: PSS-05 | P9: Charged | S9: Syed Ali | T9: 45717 | AF9: 150 | AG9: 100 | AR9: =SUM(AF9:AQ9) -> 250
A10: 16 | B10: MLP T3 AP | C10: ARE56L | D10: S-06 | F10: PPA | G10: PPA | H10: HSAT | K10: 500 | L10: 1.37 | M10: 685 | O10: PSS-10 | P10: Charged | S10: Ramesh Suthar | T10: 45717 | AF10: 100 | AH10: 100 | AI10: 300 | AR10: =SUM(AF10:AQ10) -> 500
A11: Monthwise FY 24-25 Projects (A) | K11: 4045 | M11: =SUM(M4:M10) -> 3834.25 | AF11: =SUM(AF4:AF10) -> 932.5 | AG11: =SUM(AG4:AG10) -> 200 | AH11: =SUM(AH4:AH10) -> 475 | AI11: =SUM(AI4:AI10) -> 550 | AR11: =SUM(AF11:AQ11) -> 2157.5
AF12: 600 | AG12: 200 | AH12: 325 | AI12: 550
P13: Category | R13: Category | T13: =U13 -> Capacity (MWac) | U13: Capacity (MWac) | AF13: 45748 | AG13: 45778 | AH13: 45809 | AI13: 45839 | AJ13: 45870 | AK13: 45901 | AL13: 45931 | AM13: 45962 | AN13: 45992 | AO13: 46023 | AP13: 46054 | AQ13: 46082
P14: Merchant | R14: Merchant | T14: =SUM(AF14:AQ14) -> 550 | U14: =SUMIF($G$23:$G$43,$R14,K$23:K$43) -> 1227 | AF14: =SUMIF($G$4:$G$10,$R14,AF$4:AF$10) -> 350 | AG14: =SUMIF($G$4:$G$10,$R14,AG$4:AG$10) -> 200 | AH14: =SUMIF($G$4:$G$10,$R14,AH$4:AH$10) -> 0 | AI14: =SUMIF($G$4:$G$10,$R14,AI$4:AI$10) -> 0 | AJ14: =SUMIF($G$4:$G$10,$R14,AJ$4:AJ$10) -> 0 | AK14: =SUMIF($G$4:$G$10,$R14,AK$4:AK$10) -> 0 | AL14: =SUMIF($G$4:$G$10,$R14,AL$4:AL$10) -> 0 | AM14: =SUMIF($G$4:$G$10,$R14,AM$4:AM$10) -> 0 | ... AQ14: =SUMIF($G$4:$G$10,$R14,AQ$4:AQ$10) -> 0
P15: PPA | R15: PPA | T15: =SUM(AF15:AQ15) -> 1607.5 | U15: =SUMIF($G$23:$G$43,$R15,K$23:K$43) -> 1650 | AF15: =SUMIF($G$4:$G$10,$R15,AF$4:AF$10) -> 582.5 | AG15: =SUMIF($G$4:$G$10,$R15,AG$4:AG$10) -> 0 | AH15: =SUMIF($G$4:$G$10,$R15,AH$4:AH$10) -> 475 | AI15: =SUMIF($G$4:$G$10,$R15,AI$4:AI$10) -> 550 | AJ15: =SUMIF($G$4:$G$10,$R15,AJ$4:AJ$10) -> 0 | AK15: =SUMIF($G$4:$G$10,$R15,AK$4:AK$10) -> 0 | AL15: =SUMIF($G$4:$G$10,$R15,AL$4:AL$10) -> 0 | AM15: =SUMIF($G$4:$G$10,$R15,AM$4:AM$10) -> 0 | ... AQ15: =SUMIF($G$4:$G$10,$R15,AQ$4:AQ$10) -> 0
P16: Group | R16: Group | T16: =SUM(AF16:AQ16) -> 0 | U16: =SUMIF($G$23:$G$43,$R16,K$23:K$43) -> 150 | AF16: =SUMIF($G$4:$G$10,$R16,AF$4:AF$10) -> 0 | AG16: =SUMIF($G$4:$G$10,$R16,AG$4:AG$10) -> 0 | AH16: =SUMIF($G$4:$G$10,$R16,AH$4:AH$10) -> 0 | AI16: =SUMIF($G$4:$G$10,$R16,AI$4:AI$10) -> 0 | AJ16: =SUMIF($G$4:$G$10,$R16,AJ$4:AJ$10) -> 0 | AK16: =SUMIF($G$4:$G$10,$R16,AK$4:AK$10) -> 0 | AL16: =SUMIF($G$4:$G$10,$R16,AL$4:AL$10) -> 0 | AM16: =SUMIF($G$4:$G$10,$R16,AM$4:AM$10) -> 0 | ... AQ16: =SUMIF($G$4:$G$10,$R16,AQ$4:AQ$10) -> 0
P17: EPC | R17: EPC | T17: =SUM(AF17:AQ17) -> 0 | U17: =SUMIF($G$23:$G$43,$R17,K$23:K$43) -> 0 | AF17: =SUMIF($G$4:$G$10,$R17,AF$4:AF$10) -> 0 | AG17: =SUMIF($G$4:$G$10,$R17,AG$4:AG$10) -> 0 | AH17: =SUMIF($G$4:$G$10,$R17,AH$4:AH$10) -> 0 | AI17: =SUMIF($G$4:$G$10,$R17,AI$4:AI$10) -> 0 | AJ17: =SUMIF($G$4:$G$10,$R17,AJ$4:AJ$10) -> 0 | AK17: =SUMIF($G$4:$G$10,$R17,AK$4:AK$10) -> 0 | AL17: =SUMIF($G$4:$G$10,$R17,AL$4:AL$10) -> 0 | AM17: =SUMIF($G$4:$G$10,$R17,AM$4:AM$10) -> 0 | ... AQ17: =SUMIF($G$4:$G$10,$R17,AQ$4:AQ$10) -> 0
P18: Total | R18: Total | T18: =SUM(AF18:AQ18) -> 2157.5 | U18: =SUM(U14:U17) -> 3027 | V18: =SUM(V14:V17) -> 0 | W18: =SUM(W14:W17) -> 0 | X18: =SUM(X14:X17) -> 0 | Y18: =SUM(Y14:Y17) -> 0 | Z18: =SUM(Z14:Z17) -> 0 | AA18: =SUM(AA14:AA17) -> 0 | AB18: =SUM(AB14:AB17) -> 0 | ... AQ18: =SUM(AQ14:AQ17) -> 0
AF20: 1145 | AG20: 550 | AH20: 375
A21: FY 2025-26 | Khavda Solar Projects Monthly Commissioning Plan (MWac) | AH21: In May-25 & Jun-25 @1.15 OL & balance 1.37 OL by Jul to Sep-25
A22: Priority | B22: Project | C22: SPV | D22: Plot No | E22: Plot No GP | F22: Category | G22: Category | H22: MMS Type | I22: Module Source | J22: Module Wp | K22: Capacity (MWac) | L22: OL | M22: Capacity (MWdc) | N22: IDT (No.s) | O22: PSS No. | P22: PSS Charging Date | Q22: SCOD | R22: Commissioning as per Growth Plan | S22: Plot Head | T22: Commissioning as per Growth Plan (R5 - 08-Feb-25) | U22: Capex BOQ Release Date | V22: LTA Phase | W22: Expected LTA Operationalization | X22: Plant Code | Y22: SUPPLY Plant Code | Z22: SERVICE Plant Code | AA22: Commissioning as per Growth Plan | AB22: Charging Start | AC22: Charging Finish | AE22: Capex NFA Status | AF22: 45748 | AG22: 45778 | AH22: 45809 | AI22: 45839 | AJ22: 45870 | AK22: 45901 | AL22: 45931 | AM22: 45962 | AN22: 45992 | AO22: 46023 | AP22: 46054 | AQ22: 46082
A23: P-01 | B23: Google Hybrid | C23: ARE3L | D23: A-6 | E23: A18 | F23: Merchant-Google | G23: Merchant | H23: HSAT | I23: ALMM | J23: 580 | K23: =SUM(AF23:AQ23) -> 25 | L23: 1.35 | M23: =L23*K23 -> 33.75 | N23: 2 | O23: PSS-08 | P23: 45851 | Q23: - | R23: 45838 | S23: Trilochan Saggu | T23: 45838 | U23: 45615 | V23: Phase - II | W23: 45747 | AH23: 25 | AR23: =SUM(AF23:AQ23) -> 25
A24: P-02 | B24: AGEL Merchant | C24: ASEJ6PL | D24: A-6 | E24: A18, S9 | F24: Merchant-Hybrid | G24: Merchant | H24: HSAT | I24: ALMM | J24: 580 | K24: =SUM(AF24:AQ24) -> 35 | L24: 1.35 | M24: =L24*K24 -> 47.25 | N24: 3 | O24: PSS-08 | P24: =P23 -> 45851 | Q24: - | R24: 45838 | S24: Trilochan Saggu | T24: 45838 | U24: 45615 | V24: Phase - II | W24: 45747 | AH24: 35 | AR24: =SUM(AF24:AQ24) -> 35
A25: P-03 | B25: AGEL Hybrid Merchant | C25: ARE48L | D25: S-8 | E25: S7, S8 | F25: Merchant-Hybrid | G25: Merchant | H25: HSAT | I25: ALMM | J25: 580 | K25: =SUM(AF25:AQ25) -> 100 | L25: 1.35 | M25: =L25*K25 -> 135 | N25: 8 | O25: PSS-09 | P25: Charged | Q25: - | R25: 45838 | S25: Arvind / Dhritiman | T25: 45838 | U25: 45615 | V25: Phase - III | W25: 46022 | AO25: 100 | AR25: =SUM(AF25:AQ25) -> 100
A26: P-04 | B26: AGEL Merchant | C26: AHEJ5L | D26: A-15a | E26: A15 | F26: Merchant | G26: Merchant | H26: HSAT | I26: ALMM | J26: 580 | K26: =SUM(AF26:AQ26) -> 150 | L26: 1.35 | M26: =L26*K26 -> 202.5 | N26: 12 | O26: PSS-08 | P26: =P24 -> 45851 | Q26: - | R26: 45838 | S26: Atul Kumar Kothari | T26: 45838 | U26: 45615 | V26: Phase - II | W26: 45747 | AM26: 50 | AO26: 100 | AR26: =SUM(AF26:AQ26) -> 150
A27: P-05a | B27: AGEL Hybrid Merchant | C27: AGE26BL | D27: S-5 | E27: S5, S6 | F27: Merchant-Hybrid | G27: Merchant | H27: HSAT | I27: ALMM | J27: 580 | K27: =SUM(AF27:AQ27) -> 142 | L27: 1.35 | M27: =L27*K27 -> 191.7 | N27: 24 | O27: PSS-10 | P27: =P10 -> Charged | Q27: - | R27: 46022 | S27: P. Raja | T27: 45838 | U27: 45622 | V27: Phase - III | W27: 46022 | AG27: 100 | AH27: 42 | AR27: =SUM(AF27:AQ27) -> 142
A28: P-05b | B28: AGEL Merchant | C28: AGE26BL | D28: S-5 | E28: S5, S6 | F28: Merchant-Hybrid | G28: Merchant | H28: HSAT | I28: ALMM | J28: 580 | K28: =SUM(AF28:AQ28) -> 150 | L28: 1.35 | M28: =L28*K28 -> 202.5 | N28: 24 | O28: PSS-10 | P28: =+P27 -> Charged | Q28: - | R28: 46022 | S28: P. Raja | T28: 45838 | U28: 45622 | V28: Phase - III | W28: 46022 | AH28: 150 | AR28: =SUM(AF28:AQ28) -> 150
A29: P-06 | B29: AGEL Merchant | C29: AGE24L | D29: S-5 | E29: S5, S6 | F29: Merchant | G29: Merchant | H29: HSAT | I29: ALMM | J29: 580 | K29: =SUM(AF29:AQ29) -> 150 | L29: 1.35 | M29: =L29*K29 -> 202.5 | N29: 12 | O29: PSS-10 | P29: =P27 -> Charged | Q29: - | R29: 46022 | S29: P. Raja | T29: 45838 | U29: 45622 | V29: Phase - III | W29: 46022 | AG29: 50 | AH29: 100 | AR29: =SUM(AF29:AQ29) -> 150
A30: P-07 | B30: AGEL Merchant | C30: AGE24L | D30: A-14 | E30: A13, A14, A17 | F30: Merchant | G30: Merchant | H30: HSAT | I30: ALMM | J30: 580 | K30: =SUM(AF30:AQ30) -> 150 | L30: 1.35 | M30: =L30*K30 -> 202.5 | N30: 12 | O30: PSS-05 | P30: =P9 -> Charged | Q30: - | S30: Syed Ali | T30: 45838 | AM30: 150 | AR30: =SUM(AF30:AQ30) -> 150
A31: P-08 | B31: Cement - Hybrid | C31: ACL | D31: A-1 | E31: A1, A2 | F31: Cement - Hybrid | G31: Group | H31: FT | I31: ALMM | J31: 580 | K31: =SUM(AF31:AQ31) -> 125 | L31: 1.36 | M31: =L31*K31 -> 170 | N31: 10 | O31: PSS-04 | P31: =P5 -> Charged | Q31: - | R31: 45838 | S31: Rupesh Kumar | T31: 45838 | U31: 45615 | V31: Phase - II | W31: 45747 | AH31: 125 | AR31: =SUM(AF31:AQ31) -> 125
A32: P-14 | B32: MLP T3 AP | C32: AGE25CL | D32: A-6 | E32: A6 | F32: PPA | G32: PPA | H32: HSAT | I32: China | K32: =SUM(AF32:AQ32) -> 75 | L32: 1.35 | M32: =L32*K32 -> 101.25 | N32: 6 | O32: PSS-08 | P32: =P24 -> 45851 | Q32: 45966 | T32: 45931 | AM32: 75 | AR32: =SUM(AF32:AQ32) -> 75
A33: P-09 | B33: MLP T1 J&K | C33: AGE26AL | D33: A-16 | E33: A16 | F33: PPA | G33: PPA | H33: FT | I33: SEA | K33: =SUM(AF33:AQ33) -> 50 | L33: 1.36 | M33: =L33*K33 -> 68 | N33: 4 | O33: PSS-06 | P33: 45976 | Q33: 45734 | R33: 45930 | T33: 45930 | U33: 45608 | V33: Phase - I | W33: 45309 | AK33: 50 | AR33: =SUM(AF33:AQ33) -> 50
A34: P-10 | B34: MLP T1 CG | C34: AGE26AL | D34: A-16 | E34: A16 | F34: PPA | G34: PPA | H34: FT | I34: SEA | K34: =SUM(AF34:AQ34) -> 200 | L34: 1.36 | M34: =L34*K34 -> 272 | N34: 16 | O34: PSS-06 | P34: =P33 -> 45976 | Q34: 45734 | R34: 45930 | T34: 45930 | U34: 45608 | V34: Phase - I | W34: 45309 | AL34: 200 | AR34: =SUM(AF34:AQ34) -> 200
A35: P-11 | B35: MLP T1 TN | C35: AGE26AL | D35: A-16 | E35: A16 | F35: PPA | G35: PPA | H35: FT | I35: SEA | K35: =SUM(AF35:AQ35) -> 167 | L35: 1.36 | M35: =L35*K35 -> 227.12 | N35: 14 | O35: PSS-06 | P35: =P34 -> 45976 | Q35: 45734 | R35: 45930 | T35: 45930 | U35: 45608 | V35: Phase - I | W35: 45309 | AL35: 167 | AR35: =SUM(AF35:AQ35) -> 167
A36: P-12 | B36: MLP T1 OR | C36: AGE26AL | D36: A-16 | E36: A16 | F36: PPA | G36: PPA | H36: FT | I36: SEA | K36: =SUM(AF36:AQ36) -> 333 | L36: 1.36 | M36: =L36*K36 -> 452.88 | N36: 27 | O36: PSS-06 | P36: 46014 | Q36: 45734 | R36: 45930 | T36: 45930 | U36: 45608 | V36: Phase - I | W36: 45309 | AK36: 333 | AR36: =SUM(AF36:AQ36) -> 333
A37: P-13 | B37: MLP T1 TR | C37: AGE26AL | D37: A10a | E37: A9, A10 | F37: PPA | G37: PPA | H37: FT | I37: SEA | K37: =SUM(AF37:AQ37) -> 50 | L37: 1.36 | M37: =L37*K37 -> 68 | N37: 4 | O37: PSS-03 | P37: Charged | Q37: 45561 | R37: 45838 | T37: 45930 | U37: 45608 | V37: Phase - II | W37: 45747 | AK37: 50 | AR37: =SUM(AF37:AQ37) -> 50
A38: P-15 | B38: MLP T3 AP | C38: AGE25CL | D38: A-6 | E38: A6 | F38: PPA | G38: PPA | H38: FT | I38: China | K38: =SUM(AF38:AQ38) -> 425 | L38: 1.36 | M38: =L38*K38 -> 578 | N38: 34 | O38: PSS-08 | P38: =P19 -> 0 | AN38: 425 | AR38: =SUM(AF38:AQ38) -> 425
A39: P-16 | B39: AGEL Hybrid Merchant | C39: AHEJ5L | D39: S-4 | E39: Merchant | F39: Merchant | G39: Merchant | H39: HSAT | K39: 300 | L39: 1.35 | M39: =L39*K39 -> 405 | N39: PSS-11 | AN39: 100 | AO39: 100 | AP39: 100 | AR39: =SUM(AF39:AQ39) -> 300
A40: P-17 | B40: =B14 -> 0 | C40: =C14 -> 0 | D40: =D14 -> 0 | E40: PPA | F40: PPA | G40: PPA | H40: HSAT | K40: 350 | L40: 1.35 | M40: =L40*K40 -> 472.5 | N40: =N14 -> 0 | AO40: 150 | AP40: 200 | AR40: =SUM(AF40:AQ40) -> 350
A41: P-18a | B41: KCTL | C41: KCTL | D41: A-15a | E41: Group | F41: Copper | G41: Group | H41: HSAT | K41: 12.5 | L41: 1.35 | M41: =L41*K41 -> 16.875 | N41: PSS-08 | AR41: =SUM(AF41:AQ41) -> 0
A42: P-18b | B42: MCIPL | C42: MCIPL | D42: A-15a | E42: Group | F42: Copper | G42: Group | H42: HSAT | K42: 12.5 | L42: 1.35 | M42: =L42*K42 -> 16.875 | N42: PSS-08 | AR42: =SUM(AF42:AQ42) -> 0
A43: P-19 | B43: AGEL Merchant | C43: ASEJo6PL | D43: A-15a | E43: Merchant | F43: Merchant | G43: Merchant | H43: HSAT | K43: 25 | L43: 1.35 | M43: =L43*K43 -> 33.75 | N43: PSS-08 | Q43: 45966 | T43: 45931 | AR43: =SUM(AF43:AQ43) -> 0
A44: Monthwise FY 25-26 Projects (B) | K44: =SUM(K23:K43) -> 3027 | M44: =SUM(M23:M43) -> 4099.95 | AF44: =SUM(AF23:AF43) -> 0 | AG44: =SUM(AG23:AG43) -> 150 | AH44: =SUM(AH23:AH43) -> 477 | AI44: =SUM(AI23:AI43) -> 0 | AJ44: =SUM(AJ23:AJ43) -> 0 | AK44: =SUM(AK23:AK43) -> 433 | AL44: =SUM(AL23:AL43) -> 367 | AM44: =SUM(AM23:AM43) -> 275 | ... AQ44: =SUM(AQ23:AQ43) -> 0 | AR44: =SUM(AF44:AQ44) -> 2977
A46: Monthwise FY 24-26 Projects (A) + (B) | K46: =K44+K11 -> 7072 | M46: =M44+M11 -> 7934.2 | AF46: =AF44+AF11 -> 932.5 | AG46: =AG44+AG11 -> 350 | AH46: =AH44+AH11 -> 952 | AI46: =AI44+AI11 -> 550 | AJ46: =AJ44+AJ11 -> 0 | AK46: =AK44+AK11 -> 433 | AL46: =AL44+AL11 -> 367 | AM46: =AM44+AM11 -> 275 | ... AR46: =AR44+AR11 -> 5134.5
A47: FY Wise & Quaterly Breakup | K47: =K46 -> 7072 | M47: =M46 -> 7934.2 | AF47: =SUM(AF46:AH46) -> 2234.5 | AI47: =SUM(AI46:AK46) -> 983 | AL47: =SUM(AL46:AN46) -> 1167 | AO47: =SUM(AO46:AQ46) -> 750
AF48: =AF47+AI47+AL47+AO47 -> 5134.5
A49: b. For 25-26 Merchant Projects 627 MW commissioning planned in May-25 & Jun-25 to be commissioned at 1.15 DC overloading, and full capacity DC overloading shall be achieved during July-25 to Sep-25 (need to be considered during revenue projections)
P50: Category | R50: Category | T50: =U50 -> Capacity (MWac) | U50: Capacity (MWac) | AF50: 45748 | AG50: 45778 | AH50: 45809 | AI50: 45839 | AJ50: 45870 | AK50: 45901 | AL50: 45931 | AM50: 45962 | AN50: 45992 | AO50: 46023 | AP50: 46054 | AQ50: 46082
P51: Merchant | R51: Merchant | T51: =U51 -> 1227 | U51: =SUMIF($G$23:$G$43,$R51,K$23:K$43) -> 1227 | AF51: =SUMIF($G$23:$G$43,$R51,AF$23:AF$43) -> 0 | AG51: =SUMIF($G$23:$G$43,$R51,AG$23:AG$43) -> 150 | AH51: =SUMIF($G$23:$G$43,$R51,AH$23:AH$43) -> 352 | AI51: =SUMIF($G$23:$G$43,$R51,AI$23:AI$43) -> 0 | AJ51: =SUMIF($G$23:$G$43,$R51,AJ$23:AJ$43) -> 0 | AK51: =SUMIF($G$23:$G$43,$R51,AK$23:AK$43) -> 0 | AL51: =SUMIF($G$23:$G$43,$R51,AL$23:AL$43) -> 0 | AM51: =SUMIF($G$23:$G$43,$R51,AM$23:AM$43) -> 200 | ... AR51: =SUMIF($G$23:$G$43,$R51,AR$23:AR$43) -> 1202
P52: PPA | R52: PPA | T52: =U52 -> 1650 | U52: =SUMIF($G$23:$G$43,$R52,K$23:K$43) -> 1650 | AF52: =SUMIF($G$23:$G$43,$R52,AF$23:AF$43) -> 0 | AG52: =SUMIF($G$23:$G$43,$R52,AG$23:AG$43) -> 0 | AH52: =SUMIF($G$23:$G$43,$R52,AH$23:AH$43) -> 0 | AI52: =SUMIF($G$23:$G$43,$R52,AI$23:AI$43) -> 0 | AJ52: =SUMIF($G$23:$G$43,$R52,AJ$23:AJ$43) -> 0 | AK52: =SUMIF($G$23:$G$43,$R52,AK$23:AK$43) -> 433 | AL52: =SUMIF($G$23:$G$43,$R52,AL$23:AL$43) -> 367 | AM52: =SUMIF($G$23:$G$43,$R52,AM$23:AM$43) -> 75 | ... AR52: =SUMIF($G$23:$G$43,$R52,AR$23:AR$43) -> 1650
P53: Group | R53: Group | T53: =U53 -> 150 | U53: =SUMIF($G$23:$G$43,$R53,K$23:K$43) -> 150 | AF53: =SUMIF($G$23:$G$43,$R53,AF$23:AF$43) -> 0 | AG53: =SUMIF($G$23:$G$43,$R53,AG$23:AG$43) -> 0 | AH53: =SUMIF($G$23:$G$43,$R53,AH$23:AH$43) -> 125 | AI53: =SUMIF($G$23:$G$43,$R53,AI$23:AI$43) -> 0 | AJ53: =SUMIF($G$23:$G$43,$R53,AJ$23:AJ$43) -> 0 | AK53: =SUMIF($G$23:$G$43,$R53,AK$23:AK$43) -> 0 | AL53: =SUMIF($G$23:$G$43,$R53,AL$23:AL$43) -> 0 | AM53: =SUMIF($G$23:$G$43,$R53,AM$23:AM$43) -> 0 | ... AR53: =SUMIF($G$23:$G$43,$R53,AR$23:AR$43) -> 125
P54: EPC | R54: EPC | T54: =U54 -> 0 | U54: =SUMIF($G$23:$G$43,$R54,K$23:K$43) -> 0 | AF54: =SUMIF($G$23:$G$43,$R54,AF$23:AF$43) -> 0 | AG54: =SUMIF($G$23:$G$43,$R54,AG$23:AG$43) -> 0 | AH54: =SUMIF($G$23:$G$43,$R54,AH$23:AH$43) -> 0 | AI54: =SUMIF($G$23:$G$43,$R54,AI$23:AI$43) -> 0 | AJ54: =SUMIF($G$23:$G$43,$R54,AJ$23:AJ$43) -> 0 | AK54: =SUMIF($G$23:$G$43,$R54,AK$23:AK$43) -> 0 | AL54: =SUMIF($G$23:$G$43,$R54,AL$23:AL$43) -> 0 | AM54: =SUMIF($G$23:$G$43,$R54,AM$23:AM$43) -> 0 | ... AR54: =SUMIF($G$23:$G$43,$R54,AR$23:AR$43) -> 0
P55: Total | R55: Total | T55: =U55 -> 3027 | U55: =SUM(U51:U54) -> 3027 | V55: =SUM(V51:V54) -> 0 | W55: =SUM(W51:W54) -> 0 | X55: =SUM(X51:X54) -> 0 | Y55: =SUM(Y51:Y54) -> 0 | Z55: =SUM(Z51:Z54) -> 0 | AA55: =SUM(AA51:AA54) -> 0 | AB55: =SUM(AB51:AB54) -> 0 | ... AQ55: =SUM(AQ51:AQ54) -> 0
AF56: =AF51+AF53 -> 0 | AG56: =AG51+AG53 -> 150 | AH56: =AH51+AH53 -> 477 | AI56: =AI51+AI53 -> 0 | AJ56: =AJ51+AJ53 -> 0 | AK56: =AK51+AK53 -> 0 | AL56: =AL51+AL53 -> 0 | AM56: =AM51+AM53 -> 200 | ... AQ56: =AQ51+AQ53 -> 0
P57: FY 2024-26 | Khavda Solar Projects Monthly Commissioning Plan (MWac)
P58: Category | R58: Category | T58: =U58 -> Capacity (MWac) | U58: Capacity (MWac) | AF58: 45748 | AG58: 45778 | AH58: 45809 | AI58: 45839 | AJ58: 45870 | AK58: 45901 | AL58: 45931 | AM58: 45962 | AN58: 45992 | AO58: 46023 | AP58: 46054 | AQ58: 46082
P59: Merchant | R59: Merchant | T59: =SUM(AF59:AQ59) -> 1752 | U59: =SUMIF($G$23:$G$43,$R59,K$23:K$43) -> 1227 | AF59: =AF14+AF51 -> 350 | AG59: =AG14+AG51 -> 350 | AH59: =AH14+AH51 -> 352 | AI59: =AI14+AI51 -> 0 | AJ59: =AJ14+AJ51 -> 0 | AK59: =AK14+AK51 -> 0 | AL59: =AL14+AL51 -> 0 | AM59: =AM14+AM51 -> 200 | ... AQ59: =AQ14+AQ51 -> 0
P60: PPA | R60: PPA | T60: =SUM(AF60:AQ60) -> 3257.5 | U60: =SUMIF($G$23:$G$43,$R60,K$23:K$43) -> 1650 | AF60: =AF15+AF52 -> 582.5 | AG60: =AG15+AG52 -> 0 | AH60: =AH15+AH52 -> 475 | AI60: =AI15+AI52 -> 550 | AJ60: =AJ15+AJ52 -> 0 | AK60: =AK15+AK52 -> 433 | AL60: =AL15+AL52 -> 367 | AM60: =AM15+AM52 -> 75 | ... AQ60: =AQ15+AQ52 -> 0
P61: Group | R61: Group | T61: =SUM(AF61:AQ61) -> 125 | U61: =SUMIF($G$23:$G$43,$R61,K$23:K$43) -> 150 | AF61: =AF16+AF53 -> 0 | AG61: =AG16+AG53 -> 0 | AH61: =AH16+AH53 -> 125 | AI61: =AI16+AI53 -> 0 | AJ61: =AJ16+AJ53 -> 0 | AK61: =AK16+AK53 -> 0 | AL61: =AL16+AL53 -> 0 | AM61: =AM16+AM53 -> 0 | ... AQ61: =AQ16+AQ53 -> 0
P62: EPC | R62: EPC | T62: =SUM(AF62:AQ62) -> 0 | U62: =SUMIF($G$23:$G$43,$R62,K$23:K$43) -> 0 | AF62: =AF17+AF54 -> 0 | AG62: =AG17+AG54 -> 0 | AH62: =AH17+AH54 -> 0 | AI62: =AI17+AI54 -> 0 | AJ62: =AJ17+AJ54 -> 0 | AK62: =AK17+AK54 -> 0 | AL62: =AL17+AL54 -> 0 | AM62: =AM17+AM54 -> 0 | ... AQ62: =AQ17+AQ54 -> 0
P63: Total | R63: Total | T63: =SUM(AF63:AQ63) -> 5134.5 | U63: =SUM(U59:U62) -> 3027 | V63: =SUM(V59:V62) -> 0 | W63: =SUM(W59:W62) -> 0 | X63: =SUM(X59:X62) -> 0 | Y63: =SUM(Y59:Y62) -> 0 | Z63: =SUM(Z59:Z62) -> 0 | AA63: =SUM(AA59:AA62) -> 0 | AB63: =SUM(AB59:AB62) -> 0 | ... AQ63: =SUM(AQ59:AQ62) -> 0
O64: FY 24-25 Projects | AF64: =AF11 -> 932.5 | AG64: =AG11 -> 200 | AH64: =AH11 -> 475 | AI64: =AI11 -> 550 | AJ64: =AJ11 -> 0 | AK64: =AK11 -> 0 | AL64: =AL11 -> 0 | AM64: =AM11 -> 0 | ... AQ64: =AQ11 -> 0
O65: Total FY 24-26 | AF65: =AF64+AF44 -> 932.5 | AG65: =AG64+AG44 -> 350 | AH65: =AH64+AH44 -> 952 | AI65: =AI64+AI44 -> 550 | AJ65: =AJ64+AJ44 -> 0 | AK65: =AK64+AK44 -> 433 | AL65: =AL64+AL44 -> 367 | AM65: =AM64+AM44 -> 275 | ... AQ65: =AQ64+AQ44 -> 0
AF66: =SUM(AF65:AF65) -> 932.5 | AH66: =SUM(AG65:AH65) -> 1302 | AK66: =SUM(AI65:AK65) -> 983
O69: 2775 | AF69: 1820.3843 | AG69: 3879.1327 | AH69: 5479.9409 | AI69: 6247.1308 | AJ69: 5643.9145 | AK69: 6566.6761 | AL69: 3374.6377 | AM69: 2741.8741 | AN69: 1475.6137 | AO69: 452.88508 | AP69: 165.27669 | AQ69: 176.53846
O70: 1027 | AF70: 4035 | AG70: 1992 | AH70: 1437
O71: 3995
AF72: =AF71+AF70+AF69 -> 5855.3843 | AG72: =AG71+AG70+AG69 -> 5871.1327 | AH72: =AH71+AH70+AH69 -> 6916.9409 | AI72: =AI71+AI70+AI69 -> 6247.1308 | AJ72: =AJ71+AJ70+AJ69 -> 5643.9145 | AK72: =AK71+AK70+AK69 -> 6566.6761 | AL72: =AL71+AL70+AL69 -> 3374.6377 | AM72: =AM71+AM70+AM69 -> 2741.8741 | ... AQ72: =AQ71+AQ70+AQ69 -> 176.53846
AF73: 30 | AG73: 30 | AH73: 30 | AI73: 30 | AJ73: 30 | AK73: 30 | AL73: 30 | AM73: 30 | AN73: 30 | AO73: 30
O74: =SUM(AF74:AO74) -> 1354385.7 | AF74: =AF73*AF72 -> 175661.53 | AG74: =AG73*AG72 -> 176133.98 | AH74: =AH73*AH72 -> 207508.23 | AI74: =AI73*AI72 -> 187413.92 | AJ74: =AJ73*AJ72 -> 169317.43 | AK74: =AK73*AK72 -> 197000.28 | AL74: =AL73*AL72 -> 101239.13 | AM74: =AM73*AM72 -> 82256.223 | ... AO74: =AO73*AO72 -> 13586.552
O75: =O74/360 -> 3762.1825
H76: FT | K76: =SUMIF(H23:H43,H76,K23:K43) -> 1350 | L76: 325 | M76: =K76+L76 -> 1675
H77: HSAT | K77: =SUMIF(H23:H43,H77,K23:K43) -> 1677 | L77: 575 | M77: =K77+L77 -> 2252
K78: =SUM(K76:K77) -> 3027 | L78: =SUM(L76:L77) -> 900 | M78: =K78+L78 -> 3927
D79: Plot No | F79: Capacity (MWac)
A80: A-1 | D80: A-1 | F80: =SUMIF($D$23:$E$43,D80,$K$23:$K$43) -> 125 | O80: PSS-01 | P80: =SUMIF($O$23:$O$43,$O80,$K$23:$K$43) -> 0 | AF80: =SUMIF($O$23:$O$43,$O80,AF$23:AF$43) -> 0 | AG80: =SUMIF($O$23:$O$43,$O80,AG$23:AG$43) -> 0 | AH80: =SUMIF($O$23:$O$43,$O80,AH$23:AH$43) -> 0 | AI80: =SUMIF($O$23:$O$43,$O80,AI$23:AI$43) -> 0 | AJ80: =SUMIF($O$23:$O$43,$O80,AJ$23:AJ$43) -> 0 | AK80: =SUMIF($O$23:$O$43,$O80,AK$23:AK$43) -> 0 | AL80: =SUMIF($O$23:$O$43,$O80,AL$23:AL$43) -> 0 | AM80: =SUMIF($O$23:$O$43,$O80,AM$23:AM$43) -> 0 | ... AQ80: =SUMIF($O$23:$O$43,$O80,AQ$23:AQ$43) -> 0
A81: A-2 | D81: A-2 | F81: =SUMIF($D$23:$E$43,D81,$K$23:$K$43) -> 0 | O81: PSS-02 | P81: =SUMIF($O$23:$O$43,$O81,$K$23:$K$43) -> 0 | AF81: =SUMIF($O$23:$O$43,$O81,AF$23:AF$43) -> 0 | AG81: =SUMIF($O$23:$O$43,$O81,AG$23:AG$43) -> 0 | AH81: =SUMIF($O$23:$O$43,$O81,AH$23:AH$43) -> 0 | AI81: =SUMIF($O$23:$O$43,$O81,AI$23:AI$43) -> 0 | AJ81: =SUMIF($O$23:$O$43,$O81,AJ$23:AJ$43) -> 0 | AK81: =SUMIF($O$23:$O$43,$O81,AK$23:AK$43) -> 0 | AL81: =SUMIF($O$23:$O$43,$O81,AL$23:AL$43) -> 0 | AM81: =SUMIF($O$23:$O$43,$O81,AM$23:AM$43) -> 0 | ... AQ81: =SUMIF($O$23:$O$43,$O81,AQ$23:AQ$43) -> 0
A82: A-6 | D82: A-6 | F82: =SUMIF($D$23:$E$43,D82,$K$23:$K$43) -> 560 | O82: PSS-03 | P82: =SUMIF($O$23:$O$43,$O82,$K$23:$K$43) -> 50 | AF82: =SUMIF($O$23:$O$43,$O82,AF$23:AF$43) -> 0 | AG82: =SUMIF($O$23:$O$43,$O82,AG$23:AG$43) -> 0 | AH82: =SUMIF($O$23:$O$43,$O82,AH$23:AH$43) -> 0 | AI82: =SUMIF($O$23:$O$43,$O82,AI$23:AI$43) -> 0 | AJ82: =SUMIF($O$23:$O$43,$O82,AJ$23:AJ$43) -> 0 | AK82: =SUMIF($O$23:$O$43,$O82,AK$23:AK$43) -> 50 | AL82: =SUMIF($O$23:$O$43,$O82,AL$23:AL$43) -> 0 | AM82: =SUMIF($O$23:$O$43,$O82,AM$23:AM$43) -> 0 | ... AQ82: =SUMIF($O$23:$O$43,$O82,AQ$23:AQ$43) -> 0
A83: A10a | D83: A10a | F83: =SUMIF($D$23:$E$43,D83,$K$23:$K$43) -> 50 | O83: PSS-04 | P83: =SUMIF($O$23:$O$43,$O83,$K$23:$K$43) -> 125 | AF83: =SUMIF($O$23:$O$43,$O83,AF$23:AF$43) -> 0 | AG83: =SUMIF($O$23:$O$43,$O83,AG$23:AG$43) -> 0 | AH83: =SUMIF($O$23:$O$43,$O83,AH$23:AH$43) -> 125 | AI83: =SUMIF($O$23:$O$43,$O83,AI$23:AI$43) -> 0 | AJ83: =SUMIF($O$23:$O$43,$O83,AJ$23:AJ$43) -> 0 | AK83: =SUMIF($O$23:$O$43,$O83,AK$23:AK$43) -> 0 | AL83: =SUMIF($O$23:$O$43,$O83,AL$23:AL$43) -> 0 | AM83: =SUMIF($O$23:$O$43,$O83,AM$23:AM$43) -> 0 | ... AQ83: =SUMIF($O$23:$O$43,$O83,AQ$23:AQ$43) -> 0
A84: A-12 | D84: A-12 | F84: =SUMIF($D$23:$E$43,D84,$K$23:$K$43) -> 0 | O84: PSS-05 | P84: =SUMIF($O$23:$O$43,$O84,$K$23:$K$43) -> 150 | AF84: =SUMIF($O$23:$O$43,$O84,AF$23:AF$43) -> 0 | AG84: =SUMIF($O$23:$O$43,$O84,AG$23:AG$43) -> 0 | AH84: =SUMIF($O$23:$O$43,$O84,AH$23:AH$43) -> 0 | AI84: =SUMIF($O$23:$O$43,$O84,AI$23:AI$43) -> 0 | AJ84: =SUMIF($O$23:$O$43,$O84,AJ$23:AJ$43) -> 0 | AK84: =SUMIF($O$23:$O$43,$O84,AK$23:AK$43) -> 0 | AL84: =SUMIF($O$23:$O$43,$O84,AL$23:AL$43) -> 0 | AM84: =SUMIF($O$23:$O$43,$O84,AM$23:AM$43) -> 150 | ... AQ84: =SUMIF($O$23:$O$43,$O84,AQ$23:AQ$43) -> 0
A85: A-13 | D85: A-13 | F85: =SUMIF($D$23:$E$43,D85,$K$23:$K$43) -> 0 | O85: PSS-06 | P85: =SUMIF($O$23:$O$43,$O85,$K$23:$K$43) -> 750 | AF85: =SUMIF($O$23:$O$43,$O85,AF$23:AF$43) -> 0 | AG85: =SUMIF($O$23:$O$43,$O85,AG$23:AG$43) -> 0 | AH85: =SUMIF($O$23:$O$43,$O85,AH$23:AH$43) -> 0 | AI85: =SUMIF($O$23:$O$43,$O85,AI$23:AI$43) -> 0 | AJ85: =SUMIF($O$23:$O$43,$O85,AJ$23:AJ$43) -> 0 | AK85: =SUMIF($O$23:$O$43,$O85,AK$23:AK$43) -> 383 | AL85: =SUMIF($O$23:$O$43,$O85,AL$23:AL$43) -> 367 | AM85: =SUMIF($O$23:$O$43,$O85,AM$23:AM$43) -> 0 | ... AQ85: =SUMIF($O$23:$O$43,$O85,AQ$23:AQ$43) -> 0
A86: A-14 | D86: A-14 | F86: =SUMIF($D$23:$E$43,D86,$K$23:$K$43) -> 150 | O86: PSS-07 | P86: =SUMIF($O$23:$O$43,$O86,$K$23:$K$43) -> 0 | AF86: =SUMIF($O$23:$O$43,$O86,AF$23:AF$43) -> 0 | AG86: =SUMIF($O$23:$O$43,$O86,AG$23:AG$43) -> 0 | AH86: =SUMIF($O$23:$O$43,$O86,AH$23:AH$43) -> 0 | AI86: =SUMIF($O$23:$O$43,$O86,AI$23:AI$43) -> 0 | AJ86: =SUMIF($O$23:$O$43,$O86,AJ$23:AJ$43) -> 0 | AK86: =SUMIF($O$23:$O$43,$O86,AK$23:AK$43) -> 0 | AL86: =SUMIF($O$23:$O$43,$O86,AL$23:AL$43) -> 0 | AM86: =SUMIF($O$23:$O$43,$O86,AM$23:AM$43) -> 0 | ... AQ86: =SUMIF($O$23:$O$43,$O86,AQ$23:AQ$43) -> 0
A87: A-15a | D87: A-15a | F87: =SUMIF($D$23:$E$43,D87,$K$23:$K$43) -> 200 | O87: PSS-08 | P87: =SUMIF($O$23:$O$43,$O87,$K$23:$K$43) -> 710 | AF87: =SUMIF($O$23:$O$43,$O87,AF$23:AF$43) -> 0 | AG87: =SUMIF($O$23:$O$43,$O87,AG$23:AG$43) -> 0 | AH87: =SUMIF($O$23:$O$43,$O87,AH$23:AH$43) -> 60 | AI87: =SUMIF($O$23:$O$43,$O87,AI$23:AI$43) -> 0 | AJ87: =SUMIF($O$23:$O$43,$O87,AJ$23:AJ$43) -> 0 | AK87: =SUMIF($O$23:$O$43,$O87,AK$23:AK$43) -> 0 | AL87: =SUMIF($O$23:$O$43,$O87,AL$23:AL$43) -> 0 | AM87: =SUMIF($O$23:$O$43,$O87,AM$23:AM$43) -> 125 | ... AQ87: =SUMIF($O$23:$O$43,$O87,AQ$23:AQ$43) -> 0
A88: A-16 | D88: A-16 | F88: =SUMIF($D$23:$E$43,D88,$K$23:$K$43) -> 750 | O88: PSS-09 | P88: =SUMIF($O$23:$O$43,$O88,$K$23:$K$43) -> 100 | AF88: =SUMIF($O$23:$O$43,$O88,AF$23:AF$43) -> 0 | AG88: =SUMIF($O$23:$O$43,$O88,AG$23:AG$43) -> 0 | AH88: =SUMIF($O$23:$O$43,$O88,AH$23:AH$43) -> 0 | AI88: =SUMIF($O$23:$O$43,$O88,AI$23:AI$43) -> 0 | AJ88: =SUMIF($O$23:$O$43,$O88,AJ$23:AJ$43) -> 0 | AK88: =SUMIF($O$23:$O$43,$O88,AK$23:AK$43) -> 0 | AL88: =SUMIF($O$23:$O$43,$O88,AL$23:AL$43) -> 0 | AM88: =SUMIF($O$23:$O$43,$O88,AM$23:AM$43) -> 0 | ... AQ88: =SUMIF($O$23:$O$43,$O88,AQ$23:AQ$43) -> 0
A89: S-2 | D89: S-2 | F89: =SUMIF($D$23:$E$43,D89,$K$23:$K$43) -> 0 | O89: PSS-10 | P89: =SUMIF($O$23:$O$43,$O89,$K$23:$K$43) -> 442 | AF89: =SUMIF($O$23:$O$43,$O89,AF$23:AF$43) -> 0 | AG89: =SUMIF($O$23:$O$43,$O89,AG$23:AG$43) -> 150 | AH89: =SUMIF($O$23:$O$43,$O89,AH$23:AH$43) -> 292 | AI89: =SUMIF($O$23:$O$43,$O89,AI$23:AI$43) -> 0 | AJ89: =SUMIF($O$23:$O$43,$O89,AJ$23:AJ$43) -> 0 | AK89: =SUMIF($O$23:$O$43,$O89,AK$23:AK$43) -> 0 | AL89: =SUMIF($O$23:$O$43,$O89,AL$23:AL$43) -> 0 | AM89: =SUMIF($O$23:$O$43,$O89,AM$23:AM$43) -> 0 | ... AQ89: =SUMIF($O$23:$O$43,$O89,AQ$23:AQ$43) -> 0
A90: S-4 | D90: S-4 | F90: =SUMIF($D$23:$E$43,D90,$K$23:$K$43) -> 300 | O90: PSS-11 | P90: =SUMIF($O$23:$O$43,$O90,$K$23:$K$43) -> 0 | AF90: =SUMIF($O$23:$O$43,$O90,AF$23:AF$43) -> 0 | AG90: =SUMIF($O$23:$O$43,$O90,AG$23:AG$43) -> 0 | AH90: =SUMIF($O$23:$O$43,$O90,AH$23:AH$43) -> 0 | AI90: =SUMIF($O$23:$O$43,$O90,AI$23:AI$43) -> 0 | AJ90: =SUMIF($O$23:$O$43,$O90,AJ$23:AJ$43) -> 0 | AK90: =SUMIF($O$23:$O$43,$O90,AK$23:AK$43) -> 0 | AL90: =SUMIF($O$23:$O$43,$O90,AL$23:AL$43) -> 0 | AM90: =SUMIF($O$23:$O$43,$O90,AM$23:AM$43) -> 0 | ... AQ90: =SUMIF($O$23:$O$43,$O90,AQ$23:AQ$43) -> 0
A91: S-5 | D91: S-5 | F91: =SUMIF($D$23:$E$43,D91,$K$23:$K$43) -> 442 | O91: PSS-12 | P91: =SUMIF($O$23:$O$43,$O91,$K$23:$K$43) -> 0 | AF91: =SUMIF($O$23:$O$43,$O91,AF$23:AF$43) -> 0 | AG91: =SUMIF($O$23:$O$43,$O91,AG$23:AG$43) -> 0 | AH91: =SUMIF($O$23:$O$43,$O91,AH$23:AH$43) -> 0 | AI91: =SUMIF($O$23:$O$43,$O91,AI$23:AI$43) -> 0 | AJ91: =SUMIF($O$23:$O$43,$O91,AJ$23:AJ$43) -> 0 | AK91: =SUMIF($O$23:$O$43,$O91,AK$23:AK$43) -> 0 | AL91: =SUMIF($O$23:$O$43,$O91,AL$23:AL$43) -> 0 | AM91: =SUMIF($O$23:$O$43,$O91,AM$23:AM$43) -> 0 | ... AQ91: =SUMIF($O$23:$O$43,$O91,AQ$23:AQ$43) -> 0
... A93: S-8 | D93: S-8 | F93: =SUMIF($D$23:$E$43,D93,$K$23:$K$43) -> 100 | O93: PSS-14 | P93: =SUMIF($O$23:$O$43,$O93,$K$23:$K$43) -> 0 | AF93: =SUMIF($O$23:$O$43,$O93,AF$23:AF$43) -> 0 | AG93: =SUMIF($O$23:$O$43,$O93,AG$23:AG$43) -> 0 | AH93: =SUMIF($O$23:$O$43,$O93,AH$23:AH$43) -> 0 | AI93: =SUMIF($O$23:$O$43,$O93,AI$23:AI$43) -> 0 | AJ93: =SUMIF($O$23:$O$43,$O93,AJ$23:AJ$43) -> 0 | AK93: =SUMIF($O$23:$O$43,$O93,AK$23:AK$43) -> 0 | AL93: =SUMIF($O$23:$O$43,$O93,AL$23:AL$43) -> 0 | AM93: =SUMIF($O$23:$O$43,$O93,AM$23:AM$43) -> 0 | ... AQ93: =SUMIF($O$23:$O$43,$O93,AQ$23:AQ$43) -> 0
A94: NHPC | D94: NHPC | F94: =SUMIF($D$23:$E$43,D94,$K$23:$K$43)-1.5 -> -1.5 | O94: NHPC | P94: =SUMIF($O$23:$O$43,$O94,$K$23:$K$43) -> 0 | AF94: =SUMIF($O$23:$O$43,$O94,AF$23:AF$43) -> 0 | AG94: =SUMIF($O$23:$O$43,$O94,AG$23:AG$43) -> 0 | AH94: =SUMIF($O$23:$O$43,$O94,AH$23:AH$43) -> 0 | AI94: =SUMIF($O$23:$O$43,$O94,AI$23:AI$43) -> 0 | AJ94: =SUMIF($O$23:$O$43,$O94,AJ$23:AJ$43) -> 0 | AK94: =SUMIF($O$23:$O$43,$O94,AK$23:AK$43) -> 0 | AL94: =SUMIF($O$23:$O$43,$O94,AL$23:AL$43) -> 0 | AM94: =SUMIF($O$23:$O$43,$O94,AM$23:AM$43) -> 0 | ... AQ94: =SUMIF($O$23:$O$43,$O94,AQ$23:AQ$43) -> 0
D95: Total | F95: =SUM(F80:F94) -> 2675.5 | O95: Total | P95: =SUM(P80:P94) -> 2327 | Q95: =SUM(Q80:Q94) -> 0
AF96: =#REF!+#REF!+#REF!+#REF!+#REF!+#REF!+#REF!+#REF!+#REF!+AF6+AF7+AF5+AF8+AF9+#REF!+#REF!+#REF!+AF23+AF24+AF26+AF30+AF31+AF33+AF34+AF35+AF36+AF37+AF32+AF43+#REF!+#REF!+#REF!+#REF!+#REF! -> #REF! | AG96: =#REF!+#REF!+#REF!+#REF!+#REF!+#REF!+#REF!+#REF!+#REF!+AG6+AG7+AG5+AG8+AG9+#REF!+#REF!+#REF!+AG23+AG24+AG26+AG30+AG31+AG33+AG34+AG35+AG36+AG37+AG32+AG43+#REF!+#REF!+#REF!+#REF!+#REF! -> #REF! | AH96: =#REF!+#REF!+#REF!+#REF!+#REF!+#REF!+#REF!+#REF!+#REF!+AH6+AH7+AH5+AH8+AH9+#REF!+#REF!+#REF!+AH23+AH24+AH26+AH30+AH31+AH33+AH34+AH35+AH36+AH37+AH32+AH43+#REF!+#REF!+#REF!+#REF!+#REF! -> #REF! | AI96: =#REF!+#REF!+#REF!+#REF!+#REF!+#REF!+#REF!+#REF!+#REF!+AI6+AI7+AI5+AI8+AI9+#REF!+#REF!+#REF!+AI23+AI24+AI26+AI30+AI31+AI33+AI34+AI35+AI36+AI37+AI32+AI43+#REF!+#REF!+#REF!+#REF!+#REF! -> #REF! | AJ96: =#REF!+#REF!+#REF!+#REF!+#REF!+#REF!+#REF!+#REF!+#REF!+AJ6+AJ7+AJ5+AJ8+AJ9+#REF!+#REF!+#REF!+AJ23+AJ24+AJ26+AJ30+AJ31+AJ33+AJ34+AJ35+AJ36+AJ37+AJ32+AJ43+#REF!+#REF!+#REF!+#REF!+#REF! -> #REF! | AK96: =#REF!+#REF!+#REF!+#REF!+#REF!+#REF!+#REF!+#REF!+#REF!+AK6+AK7+AK5+AK8+AK9+#REF!+#REF!+#REF!+AK23+AK24+AK26+AK30+AK31+AK33+AK34+AK35+AK36+AK37+AK32+AK43+#REF!+#REF!+#REF!+#REF!+#REF! -> #REF! | AL96: =#REF!+#REF!+#REF!+#REF!+#REF!+#REF!+#REF!+#REF!+#REF!+AL6+AL7+AL5+AL8+AL9+#REF!+#REF!+#REF!+AL23+AL24+AL26+AL30+AL31+AL33+AL34+AL35+AL36+AL37+AL32+AL43+#REF!+#REF!+#REF!+#REF!+#REF! -> #REF! | AM96: =#REF!+#REF!+#REF!+#REF!+#REF!+#REF!+#REF!+#REF!+#REF!+AM6+AM7+AM5+AM8+AM9+#REF!+#REF!+#REF!+AM23+AM24+AM26+AM30+AM31+AM33+AM34+AM35+AM36+AM37+AM32+AM43+#REF!+#REF!+#REF!+#REF!+#REF! -> #REF! | ... AQ96: =#REF!+#REF!+#REF!+#REF!+#REF!+#REF!+#REF!+#REF!+#REF!+AQ6+AQ7+AQ5+AQ8+AQ9+#REF!+#REF!+#REF!+AQ23+AQ24+AQ26+AQ30+AQ31+AQ33+AQ34+AQ35+AQ36+AQ37+AQ32+AQ43+#REF!+#REF!+#REF!+#REF!+#REF! -> #REF!
AF98: =AF11+AF44-AF96 -> #REF! | AG98: =AG11+AG44-AG96 -> #REF! | AH98: =AH11+AH44-AH96 -> #REF! | AI98: =AI11+AI44-AI96 -> #REF! | AJ98: =AJ11+AJ44-AJ96 -> #REF! | AK98: =AK11+AK44-AK96 -> #REF! | AL98: =AL11+AL44-AL96 -> #REF! | AM98: =AM11+AM44-AM96 -> #REF! | ... AQ98: =AQ11+AQ44-AQ96 -> #REF!
H105: FY 24-26
G106: Merchant | H106: Merchant | K106: =SUMIF($G$1:$G$43,$G106,K$1:K$43) -> 2102 | AF106: =SUMIF($G$1:$G$43,$G106,AF$1:AF$43) -> 350 | AG106: =SUMIF($G$1:$G$43,$G106,AG$1:AG$43) -> 350 | AH106: =SUMIF($G$1:$G$43,$G106,AH$1:AH$43) -> 352 | AI106: =SUMIF($G$1:$G$43,$G106,AI$1:AI$43) -> 0 | AJ106: =SUMIF($G$1:$G$43,$G106,AJ$1:AJ$43) -> 0 | AK106: =SUMIF($G$1:$G$43,$G106,AK$1:AK$43) -> 0 | AL106: =SUMIF($G$1:$G$43,$G106,AL$1:AL$43) -> 0 | AM106: =SUMIF($G$1:$G$43,$G106,AM$1:AM$43) -> 200 | ... AR106: =SUMIF($G$1:$G$43,$G106,AR$1:AR$43) -> 1752
G107: =#REF! -> #REF! | H107: PPA | K107: =SUMIF($G$1:$G$43,$G107,K$1:K$43) -> 0 | AF107: =SUMIF($G$1:$G$43,$G107,AF$1:AF$43) -> 0 | AG107: =SUMIF($G$1:$G$43,$G107,AG$1:AG$43) -> 0 | AH107: =SUMIF($G$1:$G$43,$G107,AH$1:AH$43) -> 0 | AI107: =SUMIF($G$1:$G$43,$G107,AI$1:AI$43) -> 0 | AJ107: =SUMIF($G$1:$G$43,$G107,AJ$1:AJ$43) -> 0 | AK107: =SUMIF($G$1:$G$43,$G107,AK$1:AK$43) -> 0 | AL107: =SUMIF($G$1:$G$43,$G107,AL$1:AL$43) -> 0 | AM107: =SUMIF($G$1:$G$43,$G107,AM$1:AM$43) -> 0 | ... AR107: =SUMIF($G$1:$G$43,$G107,AR$1:AR$43) -> 0
G108: Group | H108: Group | K108: =SUMIF($G$1:$G$43,$G108,K$1:K$43) -> 150 | AF108: =SUMIF($G$1:$G$43,$G108,AF$1:AF$43) -> 0 | AG108: =SUMIF($G$1:$G$43,$G108,AG$1:AG$43) -> 0 | AH108: =SUMIF($G$1:$G$43,$G108,AH$1:AH$43) -> 125 | AI108: =SUMIF($G$1:$G$43,$G108,AI$1:AI$43) -> 0 | AJ108: =SUMIF($G$1:$G$43,$G108,AJ$1:AJ$43) -> 0 | AK108: =SUMIF($G$1:$G$43,$G108,AK$1:AK$43) -> 0 | AL108: =SUMIF($G$1:$G$43,$G108,AL$1:AL$43) -> 0 | AM108: =SUMIF($G$1:$G$43,$G108,AM$1:AM$43) -> 0 | ... AR108: =SUMIF($G$1:$G$43,$G108,AR$1:AR$43) -> 125

Sheet KH Solar Rephase
A2: FY 2024-25 | Khavda Solar Projects Monthly Commissioning Plan (MWac) | AI2: For Internal Purpose | AO2: 45840
A3: Priority | B3: Project | C3: SPV | D3: Plot No | E3: Plot No GP | F3: Category | G3: Category | H3: MMS Type | I3: Module Source | J3: Module Wp | K3: Capacity (MWac) | L3: OL | M3: Capacity (MWdc) | N3: PSS No. | O3: PSS Charging Date | P3: SCOD | Q3: Commissioning as per Growth Plan | R3: Plot Head | S3: Commissioning as per Growth Plan (R5 - 08-Feb-25) | T3: Capex BOQ Release Date | U3: LTA Phase | V3: Expected LTA Operationalization | W3: Plant Code | X3: SUPPLY Plant Code | Y3: SERVICE Plant Code | Z3: Commissioning as per Growth Plan | AA3: Charging Start | AB3: Charging Finish | AD3: Capex NFA Status | AE3: 45748 | AF3: 45778 | AG3: 45809 | AH3: 45839 | AI3: 45870 | AJ3: 45901 | AK3: 45931 | AL3: 45962 | AM3: 45992 | AN3: 46023 | AO3: 46054 | AP3: 46082 | AQ3: Total (MW)
A4: 10 | B4: AGEL Merchant | C4: ARE56L | D4: S-08 | F4: Merchant | G4: Merchant | H4: HSAT | K4: 250 | L4: 1.37 | M4: 548 | N4: PSS-09 | O4: Charged | R4: Arvind Kulshrestha | S4: 45717 | AF4: 75 | AG4: 50 | AH4: 50 | AI4: 75 | AJ4: 0 | AK4: 0 | AQ4: =SUM(AE4:AP4) -> 250
A5: 11 | B5: MLP AP New | C5: ARE57L | D5: A-11 | F5: PPA | G5: PPA | H5: HSAT | K5: 50 | L5: 1.36 | M5: 680 | N5: PSS-13 | O5: Charged | R5: Salim Beg | S5: 45717 | AF5: 50 | AG5: 0 | AH5: 0 | AI5: 0 | AJ5: 0 | AK5: 0 | AQ5: =SUM(AE5:AP5) -> 50
A6: 12 | B6: MLP AP New | C6: ARE57L | D6: A-12 | F6: PPA | G6: PPA | H6: HSAT | K6: 187.5 | L6: 1.35 | M6: =L6*K6 -> 253.125 | N6: PSS-13 | O6: Charged | R6: Bikash Kumar | S6: 45717 | AE6: 75 | AF6: 112.5 | AG6: 0 | AK6: 0 | AQ6: =SUM(AE6:AP6) -> 187.5
A7: 13 | B7: AGEL Merchant | C7: ARE56L | D7: A-02 | F7: Merchant | G7: Merchant | H7: HSAT | K7: 350 | L7: 1.37 | M7: 308.25 | N7: PSS-04 | O7: Charged | R7: Akhil Agarwal | S7: 45717 | AF7: 50 | AG7: 175 | AH7: 0 | AI7: 75 | AJ7: 50 | AK7: 0 | AQ7: =SUM(AE7:AP7) -> 350
A8: 14 | B8: SECI H-3 | C8: AHEJ5L | D8: A-13 | F8: PPA | G8: PPA | H8: FT | K8: 570 | L8: 1.4 | M8: 798 | N8: PSS-05 | O8: Charged | R8: Syed Ali | S8: 45717 | AE8: 145 | AG8: 150 | AH8: 75 | AJ8: 50 | AK8: 50 | AL8: 100 | AQ8: =SUM(AE8:AP8) -> 570
A9: 15 | B9: AGEL Merchant | C9: ARE45L | D9: A-14 | F9: Merchant | G9: Merchant | H9: HSAT | K9: 250 | L9: 1.37 | M9: 342.5 | N9: PSS-05 | O9: Charged | R9: Syed Ali | S9: 45717 | AE9: 50 | AG9: 125 | AI9: 75 | AJ9: 0 | AK9: 0 | AQ9: =SUM(AE9:AP9) -> 250
A10: 16 | B10: MLP T3 AP | C10: ARE56L | D10: S-06 | F10: PPA | G10: PPA | H10: HSAT | K10: 500 | L10: 1.37 | M10: 685 | N10: PSS-10 | O10: Charged | R10: Ramesh Suthar | S10: 45717 | AE10: 100 | AG10: 137.5 | AH10: 112.5 | AJ10: 50 | AK10: 50 | AL10: 50 | AQ10: =SUM(AE10:AP10) -> 500
A11: Monthwise FY 24-25 Projects (A) | K11: 4045 | M11: =SUM(M4:M10) -> 3614.875 | AE11: =SUM(AE4:AE10) -> 370 | AF11: =SUM(AF4:AF10) -> 287.5 | AG11: =SUM(AG4:AG10) -> 637.5 | AH11: =SUM(AH4:AH10) -> 237.5 | AI11: =SUM(AI4:AI10) -> 225 | AJ11: =SUM(AJ4:AJ10) -> 150 | AK11: =SUM(AK4:AK10) -> 100 | AL11: =SUM(AL4:AL10) -> 150 | AQ11: =SUM(AE11:AP11) -> 2157.5
A12: FY 2025-26 | Khavda Solar Projects Monthly Commissioning Plan (MWac) | AG12: In May-25 & Jun-25 @1.15 OL & balance 1.37 OL by Jul to Sep-25
A13: Priority | B13: Project | C13: SPV | D13: Plot No | E13: Plot No GP | F13: Category | G13: Category | H13: MMS Type | I13: Module Source | J13: Module Wp | K13: Capacity (MWac) | L13: OL | M13: Capacity (MWdc) | N13: PSS No. | O13: PSS Charging Date | P13: SCOD | Q13: Commissioning as per Growth Plan | R13: Plot Head | S13: Commissioning as per Growth Plan (R5 - 08-Feb-25) | T13: Capex BOQ Release Date | U13: LTA Phase | V13: Expected LTA Operationalization | W13: Plant Code | X13: SUPPLY Plant Code | Y13: SERVICE Plant Code | Z13: Commissioning as per Growth Plan | AA13: Charging Start | AB13: Charging Finish | AD13: Capex NFA Status | AE13: 45748 | AF13: 45778 | AG13: 45809 | AH13: 45839 | AI13: 45870 | AJ13: 45901 | AK13: 45931 | AL13: 45962 | AM13: 45992 | AN13: 46023 | AO13: 46054 | AP13: 46082
A14: P-01 | B14: Google Hybrid | C14: ARE3L | D14: A-6 | E14: A18 | F14: Merchant-Google | G14: Merchant | H14: HSAT | I14: ALMM | J14: 580 | K14: =SUM(AE14:AP14) -> 25 | L14: 1.35 | M14: =L14*K14 -> 33.75 | N14: PSS-08 | O14: 45767 | P14: - | Q14: 45838 | R14: Trilochan Saggu | S14: 45838 | T14: 45615 | U14: Phase - II | V14: 45747 | AH14: 25 | AI14: 0 | AJ14: 0 | AK14: 0 | AL14: 0 | AM14: 0 | AQ14: =SUM(AE14:AP14) -> 25
A15: P-02 | B15: AGEL Merchant | C15: ASEJ6PL | D15: A-6 | E15: A18, S9 | F15: Merchant-Hybrid | G15: Merchant | H15: HSAT | I15: ALMM | J15: 580 | K15: =SUM(AE15:AP15) -> 35 | L15: 1.35 | M15: =L15*K15 -> 47.25 | N15: PSS-08 | O15: =O14 -> 45767 | P15: - | Q15: 45838 | R15: Trilochan Saggu | S15: 45838 | T15: 45615 | U15: Phase - II | V15: 45747 | AH15: 35 | AI15: 0 | AJ15: 0 | AK15: 0 | AL15: 0 | AM15: 0 | AQ15: =SUM(AE15:AP15) -> 35
A16: P-03 | B16: AGEL Hybrid Merchant | C16: ARE48L | D16: S-8 | E16: S7, S8 | F16: Merchant-Hybrid | G16: Merchant | H16: HSAT | I16: ALMM | J16: 580 | K16: =SUM(AE16:AP16) -> 100 | L16: 1.35 | M16: =L16*K16 -> 135 | N16: PSS-09 | O16: Charged | P16: - | Q16: 45838 | R16: Arvind / Dhritiman | S16: 45838 | T16: 45615 | U16: Phase - III | V16: 46022 | AG16: 0 | AH16: 0 | AI16: 50 | AJ16: 0 | AL16: 50 | AM16: 0 | AQ16: =SUM(AE16:AP16) -> 100
A17: P-04 | B17: AGEL Merchant | C17: AHEJ5L | D17: A-15a | E17: A15 | F17: Merchant | G17: Merchant | H17: HSAT | I17: ALMM | J17: 580 | K17: =SUM(AE17:AP17) -> 150 | L17: 1.35 | M17: =L17*K17 -> 202.5 | N17: PSS-08 | O17: =O15 -> 45767 | P17: - | Q17: 45838 | R17: Atul Kumar Kothari | S17: 45838 | T17: 45615 | U17: Phase - II | V17: 45747 | AG17: 0 | AH17: 0 | AI17: 0 | AJ17: 0 | AK17: 50 | AL17: 50 | AM17: 0 | AN17: 50 | AQ17: =SUM(AE17:AP17) -> 150
A18: P-05 | B18: AGEL Hybrid Merchant | C18: AGE26BL | D18: S-5 | E18: S5, S6 | F18: Merchant-Hybrid | G18: Merchant | H18: HSAT | I18: ALMM | J18: 580 | K18: =SUM(AE18:AP18) -> 142 | L18: 1.35 | M18: =L18*K18 -> 191.7 | N18: PSS-10 | O18: =O10 -> Charged | P18: - | Q18: 46022 | R18: P. Raja | S18: 45838 | T18: 45622 | U18: Phase - III | V18: 46022 | AH18: 50 | AI18: 0 | AJ18: 75 | AK18: 17 | AQ18: =SUM(AE18:AP18) -> 142
A19: P-05 | B19: AGEL Merchant | C19: AGE26BL | D19: S-5 | E19: S5, S6 | F19: Merchant | G19: Merchant | H19: HSAT | I19: ALMM | J19: 580 | K19: =SUM(AE19:AP19) -> 150 | L19: 1.35 | M19: =L19*K19 -> 202.5 | N19: PSS-10 | O19: =O11 -> 0 | P19: - | Q19: 46022 | R19: P. Raja | S19: 45838 | T19: 45622 | U19: Phase - III | V19: 46022 | AK19: 45 | AL19: 105 | AQ19: =SUM(AE19:AP19) -> 150
A20: P-06 | B20: AGEL Merchant | C20: AGE24L | D20: S-5 | E20: S5, S6 | F20: Merchant | G20: Merchant | H20: HSAT | I20: ALMM | J20: 580 | K20: =SUM(AE20:AP20) -> 150 | L20: 1.35 | M20: =L20*K20 -> 202.5 | N20: PSS-10 | O20: =O18 -> Charged | P20: - | Q20: 46022 | R20: P. Raja | S20: 45838 | T20: 45622 | U20: Phase - III | V20: 46022 | AG20: 0 | AH20: 0 | AI20: 0 | AJ20: 0 | AK20: 0 | AM20: 0 | AN20: 50 | AO20: 100 | AQ20: =SUM(AE20:AP20) -> 150
A21: P-07 | B21: AGEL Merchant | C21: AGE24L | D21: A-14 | E21: A13, A14, A17 | F21: Merchant | G21: Merchant | H21: HSAT | I21: ALMM | J21: 580 | K21: =SUM(AE21:AP21) -> 150 | L21: 1.35 | M21: =L21*K21 -> 202.5 | N21: PSS-05 | O21: =O9 -> Charged | P21: - | R21: Syed Ali | S21: 45838 | AG21: 0 | AH21: 0 | AI21: 0 | AJ21: 0 | AK21: 0 | AN21: 50 | AO21: 100 | AQ21: =SUM(AE21:AP21) -> 150
A22: P-08 | B22: Cement - Hybrid | C22: ACL | D22: A-1 | E22: A1, A2 | F22: Cement - Hybrid | G22: Group | H22: FT | I22: ALMM | J22: 580 | K22: =SUM(AE22:AP22) -> 125 | L22: 1.36 | M22: =L22*K22 -> 170 | N22: PSS-04 | O22: =O7 -> Charged | P22: - | Q22: 45838 | R22: Rupesh Kumar | S22: 45838 | T22: 45615 | U22: Phase - II | V22: 45747 | AG22: 0 | AH22: 0 | AI22: 75 | AK22: 50 | AL22: 0 | AM22: 0 | AQ22: =SUM(AE22:AP22) -> 125
A23: P-14 | B23: MLP T3 AP | C23: AGE25CL | D23: A-6 | E23: A6 | F23: PPA | G23: PPA | H23: HSAT | I23: China | K23: =SUM(AE23:AP23) -> 75 | L23: 1.35 | M23: =L23*K23 -> 101.25 | N23: PSS-08 | O23: =O15 -> 45767 | P23: 45966 | S23: 45931 | AI23: 75 | AQ23: =SUM(AE23:AP23) -> 75
A24: P-09 | B24: MLP T1 J&K | C24: AGE26AL | D24: A-16 | E24: A16 | F24: PPA | G24: PPA | H24: FT | I24: SEA | K24: =SUM(AE24:AP24) -> 50 | L24: 1.36 | M24: =L24*K24 -> 68 | N24: PSS-06 | O24: 45848 | P24: 45734 | Q24: 45930 | S24: 45930 | T24: 45608 | U24: Phase - I | V24: 45309 | AM24: 50 | AN24: 0 | AO24: 0 | AP24: 0 | AQ24: =SUM(AE24:AP24) -> 50
A25: P-10 | B25: MLP T1 CG | C25: AGE26AL | D25: A-16 | E25: A16 | F25: PPA | G25: PPA | H25: FT | I25: SEA | K25: =SUM(AE25:AP25) -> 200 | L25: 1.36 | M25: =L25*K25 -> 272 | N25: PSS-06 | O25: =O24 -> 45848 | P25: 45734 | Q25: 45930 | S25: 45930 | T25: 45608 | U25: Phase - I | V25: 45309 | AM25: 50 | AN25: 100 | AO25: 50 | AP25: 0 | AQ25: =SUM(AE25:AP25) -> 200
A26: P-11 | B26: MLP T1 TN | C26: AGE26AL | D26: A-16 | E26: A16 | F26: PPA | G26: PPA | H26: FT | I26: SEA | K26: =SUM(AE26:AP26) -> 167 | L26: 1.36 | M26: =L26*K26 -> 227.12 | N26: PSS-06 | O26: =O25 -> 45848 | P26: 45734 | Q26: 45930 | S26: 45930 | T26: 45608 | U26: Phase - I | V26: 45309 | AM26: 50 | AN26: 117 | AO26: 0 | AP26: 0 | AQ26: =SUM(AE26:AP26) -> 167
A27: P-12 | B27: MLP T1 OR | C27: AGE26AL | D27: A-16 | E27: A16 | F27: PPA | G27: PPA | H27: FT | I27: SEA | K27: =SUM(AE27:AP27) -> 333 | L27: 1.36 | M27: =L27*K27 -> 452.88 | N27: PSS-06 | O27: =O26 -> 45848 | P27: 45734 | Q27: 45930 | S27: 45930 | T27: 45608 | U27: Phase - I | V27: 45309 | AN27: 100 | AO27: 100 | AP27: 133 | AQ27: =SUM(AE27:AP27) -> 333
A28: P-13 | B28: MLP T1 TR | C28: AGE26AL | D28: A10a | E28: A9, A10 | F28: PPA | G28: PPA | H28: FT | I28: SEA | K28: =SUM(AE28:AP28) -> 50 | L28: 1.36 | M28: =L28*K28 -> 68 | N28: PSS-03 | O28: Charged | P28: 45561 | Q28: 45838 | S28: 45930 | T28: 45608 | U28: Phase - II | V28: 45747 | AJ28: 50 | AQ28: =SUM(AE28:AP28) -> 50
A29: P-15 | B29: MLP T3 AP | C29: AGE25CL | D29: A-6 | E29: A6 | F29: PPA | G29: PPA | H29: FT | I29: China | K29: =SUM(AE29:AP29) -> 425 | L29: 1.36 | M29: =L29*K29 -> 578 | N29: PSS-08 | O29: =O10 -> Charged | P29: 45966 | S29: 45931 | AN29: 150 | AO29: 150 | AP29: 125 | AQ29: =SUM(AE29:AP29) -> 425
A30: P-16 | B30: AGEL Hybrid Merchant | C30: AHEJ5L | D30: S-4 | E30: Merchant | F30: Merchant | G30: Merchant | H30: HSAT | K30: 300 | L30: 1.35 | M30: =L30*K30 -> 405 | N30: PSS-11 | AM30: 100 | AN30: 100 | AO30: 100 | AQ30: =SUM(AE30:AP30) -> 300
A31: P-17 | B31: =B5 -> MLP AP New | C31: =C5 -> ARE57L | D31: =D5 -> A-11 | E31: PPA | F31: PPA | G31: PPA | H31: HSAT | K31: 350 | L31: 1.35 | M31: =L31*K31 -> 472.5 | N31: =N5 -> PSS-13 | AM31: 150 | AN31: 200 | AQ31: =SUM(AE31:AP31) -> 350
A32: P-18a | B32: KCTL | C32: KCTL | D32: A-15a | E32: Group | F32: Copper | G32: Group | H32: HSAT | K32: 12.5 | L32: 1.35 | M32: =L32*K32 -> 16.875 | N32: PSS-08 | AO32: 12.5 | AQ32: =SUM(AE32:AP32) -> 12.5
A33: P-18b | B33: MCIPL | C33: MCIPL | D33: A-15a | E33: Group | F33: Copper | G33: Group | H33: HSAT | K33: 12.5 | L33: 1.35 | M33: =L33*K33 -> 16.875 | N33: PSS-08 | AO33: 12.5 | AQ33: =SUM(AE33:AP33) -> 12.5
A34: P-19 | B34: AGEL Merchant | C34: ASEJo6PL | D34: A-15a | E34: Merchant | F34: Merchant | G34: Merchant | H34: HSAT | K34: 25 | L34: 1.35 | M34: =L34*K34 -> 33.75 | N34: PSS-08 | AO34: 25 | AQ34: =SUM(AE34:AP34) -> 25
A35: Monthwise FY 25-26 Projects (B) | K35: =SUM(K14:K34) -> 3027 | L35: =SUM(L14:L34) -> 28.42 | M35: =SUM(M14:M34) -> 4099.95 | N35: =SUM(N14:N34) -> 0 | P35: =SUM(P14:P34) -> 320429 | Q35: =SUM(Q14:Q34) -> 596814 | R35: =SUM(R14:R34) -> 0 | S35: =SUM(S14:S34) -> 734054 | T35: =SUM(T14:T34) -> 592981 | U35: =SUM(U14:U34) -> 0 | V35: =SUM(V14:V34) -> 594059 | W35: =SUM(W14:W34) -> 0 | ... AQ35: =SUM(AQ14:AQ34) -> 3027
A37: Monthwise FY 24-26 Projects (A) + (B) | K37: =K35+K11 -> 7072 | M37: =M35+M11 -> 7714.825 | AE37: =AE35+AE11 -> 370 | AF37: =AF35+AF11 -> 287.5 | AG37: =AG35+AG11 -> 637.5 | AH37: =AH35+AH11 -> 347.5 | AI37: =AI35+AI11 -> 425 | AJ37: =AJ35+AJ11 -> 275 | AK37: =AK35+AK11 -> 262 | AL37: =AL35+AL11 -> 355 | ... AP37: =AP35+AP11 -> 258
A38: FY Wise & Quaterly Breakup | K38: =K37 -> 7072 | M38: =M37 -> 7714.825 | AE38: =SUM(AE37:AG37) -> 1295 | AH38: =SUM(AH37:AJ37) -> 1047.5 | AK38: =SUM(AK37:AM37) -> 1017 | AN38: =SUM(AN37:AP37) -> 1825
AE39: =AE38+AH38+AK38+AN38 -> 5184.5
A40: b. For 25-26 Merchant Projects 627 MW commissioning planned in May-25 & Jun-25 to be commissioned at 1.15 DC overloading, and full capacity DC overloading shall be achieved during July-25 to Sep-25 (need to be considered during revenue projections)

Sheet Summary Linked
A1: 8 | B1: AGEL FY 25-26 Commissioning Status Update | K1: For Chairman Budget Purpose @6.5GW +535 MW carryover | W1: 46022
A2: 3 | J2: Monthwise Distribution | Y2: Quarterly Distribution
I3: Plan / Actual | J3: 45748 | K3: 45778 | L3: 45809 | M3: 45839 | N3: 45870 | O3: 45901 | P3: 45931 | Q3: 45962 | R3: 45992 | S3: 46023 | T3: 46054 | U3: 46082 | V3: Total Capacity | W3: Cumm till 30-Nov-25 | Y3: Q1 | Z3: Q2 | AA3: Q3 | AB3: Q4
B4: AGEL Overall FY 2025-26 (1+2) | I4: Plan | J4: =SUM(J5:J7) -> 1114.5 | K4: =SUM(K5:K7) -> 532 | L4: =SUM(L5:L7) -> 1546.4 | M4: =SUM(M5:M7) -> 643.6 | N4: =SUM(N5:N7) -> 26 | O4: =SUM(O5:O7) -> 459 | P4: =SUM(P5:P7) -> 419 | Q4: =SUM(Q5:Q7) -> 655 | ... U4: =SUM(U5:U7) -> 75.9 | V4: =SUM(J4:U4) -> 7072.8 | W4: =SUM(OFFSET(J4,0,0,1,$A$1)) -> 5395.5 | Y4: =SUM(OFFSET($J4,0,0,1,$A$2)) -> 3192.9 | Z4: =SUM(OFFSET($M4,0,0,1,$A$2)) -> 1128.6 | AA4: =SUM(OFFSET($P4,0,0,1,$A$2)) -> 2113 | AB4: =SUM(OFFSET($S4,0,0,1,$A$2)) -> 638.3
I5: PPA | J5: =+J19+J212 -> 582.5 | K5: =+K19+K212 -> 0 | L5: =+L19+L212 -> 475 | M5: =+M19+M212 -> 622.8 | N5: =+N19+N212 -> 26 | O5: =+O19+O212 -> 459 | P5: =+P19+P212 -> 419 | Q5: =+Q19+Q212 -> 351 | ... U5: =+U19+U212 -> 0 | V5: =SUM(J5:U5) -> 4144.3 | W5: =SUM(OFFSET(J5,0,0,1,$A$1)) -> 2935.3 | Y5: =SUM(OFFSET($J5,0,0,1,$A$2)) -> 1057.5 | Z5: =SUM(OFFSET($M5,0,0,1,$A$2)) -> 1107.8 | AA5: =SUM(OFFSET($P5,0,0,1,$A$2)) -> 1679 | AB5: =SUM(OFFSET($S5,0,0,1,$A$2)) -> 300
I6: Merchant | J6: =+J20+J213 -> 506 | K6: =+K20+K213 -> 500.8 | L6: =+L20+L213 -> 646.4 | M6: =+M20+M213 -> 20.8 | N6: =+N20+N213 -> 0 | O6: =+O20+O213 -> 0 | P6: =+P20+P213 -> 0 | Q6: =+Q20+Q213 -> 304 | ... U6: =+U20+U213 -> 75.9 | V6: =SUM(J6:U6) -> 2446.3 | W6: =SUM(OFFSET(J6,0,0,1,$A$1)) -> 1978 | Y6: =SUM(OFFSET($J6,0,0,1,$A$2)) -> 1653.2 | Z6: =SUM(OFFSET($M6,0,0,1,$A$2)) -> 20.8 | AA6: =SUM(OFFSET($P6,0,0,1,$A$2)) -> 434 | AB6: =SUM(OFFSET($S6,0,0,1,$A$2)) -> 338.3
I7: Group | J7: =+J21+J214 -> 26 | K7: =+K21+K214 -> 31.2 | L7: =+L21+L214 -> 425 | M7: =+M21+M214 -> 0 | N7: =+N21+N214 -> 0 | O7: =+O21+O214 -> 0 | P7: =+P21+P214 -> 0 | Q7: =+Q21+Q214 -> 0 | ... U7: =+U21+U214 -> 0 | V7: =SUM(J7:U7) -> 482.2 | W7: =SUM(OFFSET(J7,0,0,1,$A$1)) -> 482.2 | Y7: =SUM(OFFSET($J7,0,0,1,$A$2)) -> 482.2 | Z7: =SUM(OFFSET($M7,0,0,1,$A$2)) -> 0 | AA7: =SUM(OFFSET($P7,0,0,1,$A$2)) -> 0 | AB7: =SUM(OFFSET($S7,0,0,1,$A$2)) -> 0
I8: Rephase | J8: =SUM(J9:J11) -> 474 | K8: =SUM(K9:K11) -> 313.5 | L8: =SUM(L9:L11) -> 848.7 | M8: =SUM(M9:M11) -> 575.5 | N8: =SUM(N9:N11) -> 653 | O8: =SUM(O9:O11) -> 353 | P8: =SUM(P9:P11) -> 366 | Q8: =SUM(Q9:Q11) -> 459 | ... U8: =SUM(U9:U11) -> 396.3 | V8: =SUM(J8:U8) -> 7072.8 | W8: =SUM(OFFSET(J8,0,0,1,$A$1)) -> 4042.7 | Y8: =SUM(OFFSET($J8,0,0,1,$A$2)) -> 1636.2 | Z8: =SUM(OFFSET($M8,0,0,1,$A$2)) -> 1581.5 | AA8: =SUM(OFFSET($P8,0,0,1,$A$2)) -> 1607.8 | AB8: =SUM(OFFSET($S8,0,0,1,$A$2)) -> 2247.3
I9: PPA | J9: =+J23+J216 -> 320 | K9: =+K23+K216 -> 162.5 | L9: =+L23+L216 -> 462.5 | M9: =+M23+M216 -> 187.5 | N9: =+N23+N216 -> 150 | O9: =+O23+O216 -> 200 | P9: =+P23+P216 -> 100 | Q9: =+Q23+Q216 -> 254 | ... U9: =+U23+U216 -> 258 | V9: =SUM(J9:U9) -> 4144.3 | W9: =SUM(OFFSET(J9,0,0,1,$A$1)) -> 1836.5 | Y9: =SUM(OFFSET($J9,0,0,1,$A$2)) -> 945 | Z9: =SUM(OFFSET($M9,0,0,1,$A$2)) -> 537.5 | AA9: =SUM(OFFSET($P9,0,0,1,$A$2)) -> 1136.8 | AB9: =SUM(OFFSET($S9,0,0,1,$A$2)) -> 1525
I10: Merchant | J10: =+J24+J217 -> 154 | K10: =+K24+K217 -> 125 | L10: =+L24+L217 -> 355 | M10: =+M24+M217 -> 238 | N10: =+N24+N217 -> 278 | O10: =+O24+O217 -> 153 | P10: =+P24+P217 -> 216 | Q10: =+Q24+Q217 -> 205 | ... U10: =+U24+U217 -> 138.3 | V10: =SUM(J10:U10) -> 2446.3 | W10: =SUM(OFFSET(J10,0,0,1,$A$1)) -> 1724 | Y10: =SUM(OFFSET($J10,0,0,1,$A$2)) -> 634 | Z10: =SUM(OFFSET($M10,0,0,1,$A$2)) -> 669 | AA10: =SUM(OFFSET($P10,0,0,1,$A$2)) -> 421 | AB10: =SUM(OFFSET($S10,0,0,1,$A$2)) -> 722.3
I11: Group | J11: =+J25+J218 -> 0 | K11: =+K25+K218 -> 26 | L11: =+L25+L218 -> 31.2 | M11: =+M25+M218 -> 150 | N11: =+N25+N218 -> 225 | O11: =+O25+O218 -> 0 | P11: =+P25+P218 -> 50 | Q11: =+Q25+Q218 -> 0 | ... U11: =+U25+U218 -> 0 | V11: =SUM(J11:U11) -> 482.2 | W11: =SUM(OFFSET(J11,0,0,1,$A$1)) -> 482.2 | Y11: =SUM(OFFSET($J11,0,0,1,$A$2)) -> 57.2 | Z11: =SUM(OFFSET($M11,0,0,1,$A$2)) -> 375 | AA11: =SUM(OFFSET($P11,0,0,1,$A$2)) -> 50 | AB11: =SUM(OFFSET($S11,0,0,1,$A$2)) -> 0
I12: Actual / Fcst | J12: =SUM(J13:J15) -> 474 | K12: =SUM(K13:K15) -> 313.5 | L12: =SUM(L13:L15) -> 848.7 | M12: =SUM(M13:M15) -> 127.6 | N12: =SUM(N13:N15) -> 537.3 | O12: =SUM(O13:O15) -> 531.2 | P12: =SUM(P13:P15) -> 203 | Q12: =SUM(Q13:Q15) -> 333.2 | ... U12: =SUM(U13:U15) -> 910.1 | V12: =SUM(J12:U12) -> 6588.8 | W12: =SUM(OFFSET(J12,0,0,1,$A$1)) -> 3368.5 | Y12: =SUM(OFFSET($J12,0,0,1,$A$2)) -> 1636.2 | Z12: =SUM(OFFSET($M12,0,0,1,$A$2)) -> 1196.1 | AA12: =SUM(OFFSET($P12,0,0,1,$A$2)) -> 1018.4 | AB12: =SUM(OFFSET($S12,0,0,1,$A$2)) -> 2738.1
I13: PPA | J13: =+J27+J220 -> 320 | K13: =+K27+K220 -> 162.5 | L13: =+L27+L220 -> 462.5 | M13: =+M27+M220 -> 0 | N13: =+N27+N220 -> 137.5 | O13: =+O27+O220 -> 175 | P13: =+P27+P220 -> 203 | Q13: =+Q27+Q220 -> 246.8 | ... U13: =+U27+U220 -> 745.8 | V13: =SUM(J13:U13) -> 3660.3 | W13: =SUM(OFFSET(J13,0,0,1,$A$1)) -> 1707.3 | Y13: =SUM(OFFSET($J13,0,0,1,$A$2)) -> 945 | Z13: =SUM(OFFSET($M13,0,0,1,$A$2)) -> 312.5 | AA13: =SUM(OFFSET($P13,0,0,1,$A$2)) -> 657 | AB13: =SUM(OFFSET($S13,0,0,1,$A$2)) -> 1745.8
I14: Merchant | J14: =+J28+J221 -> 154 | K14: =+K28+K221 -> 125 | L14: =+L28+L221 -> 355 | M14: =+M28+M221 -> 127.6 | N14: =+N28+N221 -> 249.8 | O14: =+O28+O221 -> 306.2 | P14: =+P28+P221 -> 0 | Q14: =+Q28+Q221 -> 86.4 | ... U14: =+U28+U221 -> 164.3 | V14: =SUM(J14:U14) -> 2446.3 | W14: =SUM(OFFSET(J14,0,0,1,$A$1)) -> 1404 | Y14: =SUM(OFFSET($J14,0,0,1,$A$2)) -> 634 | Z14: =SUM(OFFSET($M14,0,0,1,$A$2)) -> 683.6 | AA14: =SUM(OFFSET($P14,0,0,1,$A$2)) -> 136.4 | AB14: =SUM(OFFSET($S14,0,0,1,$A$2)) -> 992.3
I15: Group | J15: =+J29+J222 -> 0 | K15: =+K29+K222 -> 26 | L15: =+L29+L222 -> 31.2 | M15: =+M29+M222 -> 0 | N15: =+N29+N222 -> 150 | O15: =+O29+O222 -> 50 | P15: =+P29+P222 -> 0 | Q15: =+Q29+Q222 -> 0 | ... U15: =+U29+U222 -> 0 | V15: =SUM(J15:U15) -> 482.2 | W15: =SUM(OFFSET(J15,0,0,1,$A$1)) -> 257.2 | Y15: =SUM(OFFSET($J15,0,0,1,$A$2)) -> 57.2 | Z15: =SUM(OFFSET($M15,0,0,1,$A$2)) -> 200 | AA15: =SUM(OFFSET($P15,0,0,1,$A$2)) -> 225 | AB15: =SUM(OFFSET($S15,0,0,1,$A$2)) -> 0
I17: Plan / Actual | J17: 45748 | K17: 45778 | L17: 45809 | M17: 45839 | N17: 45870 | O17: 45901 | P17: 45931 | Q17: 45962 | R17: 45992 | S17: 46023 | T17: 46054 | U17: 46082 | V17: Total Capacity | W17: =+W3 -> Cumm till 30-Nov-25 | Y17: Q1 | Z17: Q2 | AA17: Q3 | AB17: Q4
B18: 1. AGEL Overall Solar FY 2025-26 (A + B + C) | I18: Plan | J18: =SUM(J19:J21) -> 932.5 | K18: =SUM(K19:K21) -> 350 | L18: =SUM(L19:L21) -> 1302 | M18: =SUM(M19:M21) -> 550 | N18: =SUM(N19:N21) -> 0 | O18: =SUM(O19:O21) -> 433 | P18: =SUM(P19:P21) -> 367 | Q18: =SUM(Q19:Q21) -> 525 | ... U18: =SUM(U19:U21) -> 0 | V18: =SUM(J18:U18) -> 5868.5 | W18: =SUM(OFFSET(J18,0,0,1,$A$1)) -> 4459.5 | Y18: =SUM(OFFSET($J18,0,0,1,$A$2)) -> 2584.5 | Z18: =SUM(OFFSET($M18,0,0,1,$A$2)) -> 983 | AA18: =SUM(OFFSET($P18,0,0,1,$A$2)) -> 1801 | AB18: =SUM(OFFSET($S18,0,0,1,$A$2)) -> 500
I19: PPA | J19: =J107+J134 -> 582.5 | K19: =K107+K134+K152 -> 0 | L19: =L107+L134+L152 -> 475 | M19: =M107+M134+M152 -> 550 | N19: =N107+N134+N152 -> 0 | O19: =O107+O134+O152 -> 433 | P19: =P107+P134+P152 -> 367 | Q19: =Q107+Q134+Q152 -> 325 | R19: =R107+R134+R152 -> 909 | ... U19: =U107+U134+U152 -> 0 | V19: =SUM(J19:U19) -> 3941.5 | W19: =SUM(OFFSET(J19,0,0,1,$A$1)) -> 2732.5 | Y19: =SUM(OFFSET($J19,0,0,1,$A$2)) -> 1057.5 | Z19: =SUM(OFFSET($M19,0,0,1,$A$2)) -> 983 | AA19: =SUM(OFFSET($P19,0,0,1,$A$2)) -> 1601 | AB19: =SUM(OFFSET($S19,0,0,1,$A$2)) -> 300
I20: Merchant | J20: =J108+J135 -> 350 | K20: =K108+K135+K153 -> 350 | L20: =L108+L135+L153 -> 402 | M20: =M108+M135+M153 -> 0 | N20: =N108+N135+N153 -> 0 | O20: =O108+O135+O153 -> 0 | P20: =P108+P135+P153 -> 0 | Q20: =Q108+Q135+Q153 -> 200 | R20: =R108+R135+R153 -> 0 | ... U20: =U108+U135+U153 -> 0 | V20: =SUM(J20:U20) -> 1502 | W20: =SUM(OFFSET(J20,0,0,1,$A$1)) -> 1302 | Y20: =SUM(OFFSET($J20,0,0,1,$A$2)) -> 1102 | Z20: =SUM(OFFSET($M20,0,0,1,$A$2)) -> 0 | AA20: =SUM(OFFSET($P20,0,0,1,$A$2)) -> 200 | AB20: =SUM(OFFSET($S20,0,0,1,$A$2)) -> 200
I21: Group | J21: =J109+J136 -> 0 | K21: =K109+K136+K154 -> 0 | L21: =L109+L136+L154 -> 425 | M21: =M109+M136+M154 -> 0 | N21: =N109+N136+N154 -> 0 | O21: =O109+O136+O154 -> 0 | P21: =P109+P136+P154 -> 0 | Q21: =Q109+Q136+Q154 -> 0 | R21: =R109+R136+R154 -> 0 | ... U21: =U109+U136+U154 -> 0 | V21: =SUM(J21:U21) -> 425 | W21: =SUM(OFFSET(J21,0,0,1,$A$1)) -> 425 | Y21: =SUM(OFFSET($J21,0,0,1,$A$2)) -> 425 | Z21: =SUM(OFFSET($M21,0,0,1,$A$2)) -> 0 | AA21: =SUM(OFFSET($P21,0,0,1,$A$2)) -> 0 | AB21: =SUM(OFFSET($S21,0,0,1,$A$2)) -> 0
I22: Rephase | J22: =SUM(J23:J25) -> 370 | K22: =SUM(K23:K25) -> 287.5 | L22: =SUM(L23:L25) -> 687.5 | M22: =SUM(M23:M25) -> 497.5 | N22: =SUM(N23:N25) -> 575 | O22: =SUM(O23:O25) -> 275 | P22: =SUM(P23:P25) -> 262 | Q22: =SUM(Q23:Q25) -> 355 | ... U22: =SUM(U23:U25) -> 258 | V22: =SUM(J22:U22) -> 5868.5 | W22: =SUM(OFFSET(J22,0,0,1,$A$1)) -> 3309.5 | Y22: =SUM(OFFSET($J22,0,0,1,$A$2)) -> 1345 | Z22: =SUM(OFFSET($M22,0,0,1,$A$2)) -> 1347.5 | AA22: =SUM(OFFSET($P22,0,0,1,$A$2)) -> 1301 | AB22: =SUM(OFFSET($S22,0,0,1,$A$2)) -> 1875
I23: PPA | J23: =J111+J138 -> 320 | K23: =K111+K138+K156 -> 162.5 | L23: =L111+L138+L156 -> 462.5 | M23: =M111+M138+M156 -> 187.5 | N23: =N111+N138+N156 -> 150 | O23: =O111+O138+O156 -> 200 | P23: =P111+P138+P156 -> 100 | Q23: =Q111+Q138+Q156 -> 150 | R23: =R111+R138+R156 -> 684 | ... U23: =U111+U138+U156 -> 258 | V23: =SUM(J23:U23) -> 3941.5 | W23: =SUM(OFFSET(J23,0,0,1,$A$1)) -> 1732.5 | Y23: =SUM(OFFSET($J23,0,0,1,$A$2)) -> 945 | Z23: =SUM(OFFSET($M23,0,0,1,$A$2)) -> 537.5 | AA23: =SUM(OFFSET($P23,0,0,1,$A$2)) -> 934 | AB23: =SUM(OFFSET($S23,0,0,1,$A$2)) -> 1525
I24: Merchant | J24: =J112+J139 -> 50 | K24: =K112+K139+K157 -> 125 | L24: =L112+L139+L157 -> 225 | M24: =M112+M139+M157 -> 160 | N24: =N112+N139+N157 -> 200 | O24: =O112+O139+O157 -> 75 | P24: =P112+P139+P157 -> 112 | Q24: =Q112+Q139+Q157 -> 205 | R24: =R112+R139+R157 -> 0 | ... U24: =U112+U139+U157 -> 0 | V24: =SUM(J24:U24) -> 1502 | W24: =SUM(OFFSET(J24,0,0,1,$A$1)) -> 1152 | Y24: =SUM(OFFSET($J24,0,0,1,$A$2)) -> 400 | Z24: =SUM(OFFSET($M24,0,0,1,$A$2)) -> 435 | AA24: =SUM(OFFSET($P24,0,0,1,$A$2)) -> 317 | AB24: =SUM(OFFSET($S24,0,0,1,$A$2)) -> 350
I25: Group | J25: =J113+J140 -> 0 | K25: =K113+K140+K158 -> 0 | L25: =L113+L140+L158 -> 0 | M25: =M113+M140+M158 -> 150 | N25: =N113+N140+N158 -> 225 | O25: =O113+O140+O158 -> 0 | P25: =P113+P140+P158 -> 50 | Q25: =Q113+Q140+Q158 -> 0 | R25: =R113+R140+R158 -> 0 | ... U25: =U113+U140+U158 -> 0 | V25: =SUM(J25:U25) -> 425 | W25: =SUM(OFFSET(J25,0,0,1,$A$1)) -> 425 | Y25: =SUM(OFFSET($J25,0,0,1,$A$2)) -> 0 | Z25: =SUM(OFFSET($M25,0,0,1,$A$2)) -> 375 | AA25: =SUM(OFFSET($P25,0,0,1,$A$2)) -> 50 | AB25: =SUM(OFFSET($S25,0,0,1,$A$2)) -> 0
I26: Actual / Fcst | J26: =SUM(J27:J29) -> 370 | K26: =SUM(K27:K29) -> 287.5 | L26: =SUM(L27:L29) -> 687.5 | M26: =SUM(M27:M29) -> 60 | N26: =SUM(N27:N29) -> 412.5 | O26: =SUM(O27:O29) -> 500 | P26: =SUM(P27:P29) -> 125 | Q26: =SUM(Q27:Q29) -> 250 | ... U26: =SUM(U27:U29) -> 725 | V26: =SUM(J26:U26) -> 5384.5 | W26: =SUM(OFFSET(J26,0,0,1,$A$1)) -> 2692.5 | Y26: =SUM(OFFSET($J26,0,0,1,$A$2)) -> 1345 | Z26: =SUM(OFFSET($M26,0,0,1,$A$2)) -> 972.5 | AA26: =SUM(OFFSET($P26,0,0,1,$A$2)) -> 800 | AB26: =SUM(OFFSET($S26,0,0,1,$A$2)) -> 2267
I27: PPA | J27: =J115+J142 -> 320 | K27: =K115+K142+K160 -> 162.5 | L27: =L115+L142+L160 -> 462.5 | M27: =M115+M142+M160 -> 0 | N27: =N115+N142+N160 -> 137.5 | O27: =O115+O142+O160 -> 175 | P27: =P115+P142+P160 -> 125 | Q27: =Q115+Q142+Q160 -> 200 | R27: =R115+R142+R160 -> 150 | ... U27: =U115+U142+U160 -> 725 | V27: =SUM(J27:U27) -> 3457.5 | W27: =SUM(OFFSET(J27,0,0,1,$A$1)) -> 1582.5 | Y27: =SUM(OFFSET($J27,0,0,1,$A$2)) -> 945 | Z27: =SUM(OFFSET($M27,0,0,1,$A$2)) -> 312.5 | AA27: =SUM(OFFSET($P27,0,0,1,$A$2)) -> 475 | AB27: =SUM(OFFSET($S27,0,0,1,$A$2)) -> 1725
I28: Merchant | J28: =J116+J143 -> 50 | K28: =K116+K143+K161 -> 125 | L28: =L116+L143+L161 -> 225 | M28: =M116+M143+M161 -> 60 | N28: =N116+N143+N161 -> 125 | O28: =O116+O143+O161 -> 275 | P28: =P116+P143+P161 -> 0 | Q28: =Q116+Q143+Q161 -> 50 | R28: =R116+R143+R161 -> 50 | ... U28: =U116+U143+U161 -> 0 | V28: =SUM(J28:U28) -> 1502 | W28: =SUM(OFFSET(J28,0,0,1,$A$1)) -> 910 | Y28: =SUM(OFFSET($J28,0,0,1,$A$2)) -> 400 | Z28: =SUM(OFFSET($M28,0,0,1,$A$2)) -> 460 | AA28: =SUM(OFFSET($P28,0,0,1,$A$2)) -> 100 | AB28: =SUM(OFFSET($S28,0,0,1,$A$2)) -> 542
I29: Group | J29: =J117+J144 -> 0 | K29: =K117+K144+K162 -> 0 | L29: =L117+L144+L162 -> 0 | M29: =M117+M144+M162 -> 0 | N29: =N117+N144+N162 -> 150 | O29: =O117+O144+O162 -> 50 | P29: =P117+P144+P162 -> 0 | Q29: =Q117+Q144+Q162 -> 0 | R29: =R117+R144+R162 -> 225 | ... U29: =U117+U144+U162 -> 0 | V29: =SUM(J29:U29) -> 425 | W29: =SUM(OFFSET(J29,0,0,1,$A$1)) -> 200 | Y29: =SUM(OFFSET($J29,0,0,1,$A$2)) -> 0 | Z29: =SUM(OFFSET($M29,0,0,1,$A$2)) -> 200 | AA29: =SUM(OFFSET($P29,0,0,1,$A$2)) -> 225 | AB29: =SUM(OFFSET($S29,0,0,1,$A$2)) -> 0
B31: S. No. | C31: Project Name | D31: SPV | E31: Type | F31: Plot / Location / PSS | G31: Capacity | H31: Type | I31: Plan Actual | J31: 45748 | K31: 45778 | L31: 45809 | M31: 45839 | N31: 45870 | O31: 45901 | P31: 45931 | Q31: 45962 | R31: 45992 | S31: 46023 | T31: 46054 | U31: 46082 | V31: Total Capacity | W31: =+W17 -> Cumm till 30-Nov-25 | Y31: Q1 | Z31: Q2 | AA31: Q3 | AB31: Q4
B32: A. Khavda Solar Projects
B33: 1 | C33: AGEL Merchant | D33: ARE56L | E33: Merchant | F33: S-08 | G33: 250 | H33: Merchant | I33: Plan | J33: ='KH Solar Plan'!AF4 -> 150 | K33: ='KH Solar Plan'!AG4 -> 100 | L33: ='KH Solar Plan'!AH4 -> 0 | M33: ='KH Solar Plan'!AI4 -> 0 | N33: ='KH Solar Plan'!AJ4 -> 0 | O33: ='KH Solar Plan'!AK4 -> 0 | P33: ='KH Solar Plan'!AL4 -> 0 | Q33: ='KH Solar Plan'!AM4 -> 0 | ... U33: ='KH Solar Plan'!AQ4 -> 0 | V33: =SUM(J33:U33) -> 250 | W33: =SUM(OFFSET(J33,0,0,1,$A$1)) -> 250 | Y33: =SUM(OFFSET($J33,0,0,1,$A$2)) -> 250 | Z33: =SUM(OFFSET($M33,0,0,1,$A$2)) -> 0 | AA33: =SUM(OFFSET($P33,0,0,1,$A$2)) -> 0 | AB33: =SUM(OFFSET($S33,0,0,1,$A$2)) -> 0
H34: Merchant | I34: Rephase | J34: ='KH Solar Rephase'!AE4 -> 0 | K34: ='KH Solar Rephase'!AF4 -> 75 | L34: ='KH Solar Rephase'!AG4 -> 50 | M34: ='KH Solar Rephase'!AH4 -> 50 | N34: ='KH Solar Rephase'!AI4 -> 75 | O34: ='KH Solar Rephase'!AJ4 -> 0 | P34: ='KH Solar Rephase'!AK4 -> 0 | Q34: ='KH Solar Rephase'!AL4 -> 0 | ... U34: ='KH Solar Rephase'!AP4 -> 0 | V34: =SUM(J34:U34) -> 250 | W34: =SUM(OFFSET(J34,0,0,1,$A$1)) -> 250 | Y34: =SUM(OFFSET($J34,0,0,1,$A$2)) -> 125 | Z34: =SUM(OFFSET($M34,0,0,1,$A$2)) -> 125 | AA34: =SUM(OFFSET($P34,0,0,1,$A$2)) -> 0 | AB34: =SUM(OFFSET($S34,0,0,1,$A$2)) -> 0
H35: Merchant | I35: Actual / Fcst | J35: ='KH Solar Actual'!O5 -> 0 | K35: ='KH Solar Actual'!P5 -> 75 | L35: ='KH Solar Actual'!Q5 -> 50 | M35: ='KH Solar Actual'!R5 -> 0 | N35: ='KH Solar Actual'!S5 -> 125 | O35: ='KH Solar Actual'!T5 -> 0 | P35: ='KH Solar Actual'!U5 -> 0 | Q35: ='KH Solar Actual'!V5 -> 0 | ... U35: ='KH Solar Actual'!Z5 -> 0 | V35: =SUM(J35:U35) -> 250 | W35: =SUM(OFFSET(J35,0,0,1,$A$1)) -> 250 | Y35: =SUM(OFFSET($J35,0,0,1,$A$2)) -> 125 | Z35: =SUM(OFFSET($M35,0,0,1,$A$2)) -> 125 | AA35: =SUM(OFFSET($P35,0,0,1,$A$2)) -> 0 | AB35: =SUM(OFFSET($S35,0,0,1,$A$2)) -> 0
B36: 2 | C36: AGEL Merchant | D36: ARE56L | E36: Merchant | F36: A-02 | G36: 50 | H36: Merchant | I36: Plan | J36: ='KH Solar Plan'!AF5 -> 50 | K36: ='KH Solar Plan'!AG5 -> 0 | L36: ='KH Solar Plan'!AH5 -> 0 | M36: ='KH Solar Plan'!AI5 -> 0 | N36: ='KH Solar Plan'!AJ5 -> 0 | O36: ='KH Solar Plan'!AK5 -> 0 | P36: ='KH Solar Plan'!AL5 -> 0 | Q36: ='KH Solar Plan'!AM5 -> 0 | ... U36: ='KH Solar Plan'!AQ5 -> 0 | V36: =SUM(J36:U36) -> 50 | W36: =SUM(OFFSET(J36,0,0,1,$A$1)) -> 50 | Y36: =SUM(OFFSET($J36,0,0,1,$A$2)) -> 50 | Z36: =SUM(OFFSET($M36,0,0,1,$A$2)) -> 0 | AA36: =SUM(OFFSET($P36,0,0,1,$A$2)) -> 0 | AB36: =SUM(OFFSET($S36,0,0,1,$A$2)) -> 0
B37: 2 | C37: AGEL Merchant | D37: ARE56L | E37: Merchant | F37: A-02 | H37: Merchant | I37: Rephase | J37: ='KH Solar Rephase'!AE5 -> 0 | K37: ='KH Solar Rephase'!AF5 -> 50 | L37: ='KH Solar Rephase'!AG5 -> 0 | M37: ='KH Solar Rephase'!AH5 -> 0 | N37: ='KH Solar Rephase'!AI5 -> 0 | O37: ='KH Solar Rephase'!AJ5 -> 0 | P37: ='KH Solar Rephase'!AK5 -> 0 | Q37: ='KH Solar Rephase'!AL5 -> 0 | ... U37: ='KH Solar Rephase'!AP5 -> 0 | V37: =SUM(J37:U37) -> 50 | W37: =SUM(OFFSET(J37,0,0,1,$A$1)) -> 50 | Y37: =SUM(OFFSET($J37,0,0,1,$A$2)) -> 50 | Z37: =SUM(OFFSET($M37,0,0,1,$A$2)) -> 0 | AA37: =SUM(OFFSET($P37,0,0,1,$A$2)) -> 0 | AB37: =SUM(OFFSET($S37,0,0,1,$A$2)) -> 0
B38: 2 | C38: AGEL Merchant | D38: ARE56L | E38: Merchant | F38: A-02 | H38: Merchant | I38: Actual / Fcst | J38: ='KH Solar Actual'!O6 -> 0 | K38: ='KH Solar Actual'!P6 -> 50 | L38: ='KH Solar Actual'!Q6 -> 0 | M38: ='KH Solar Actual'!R6 -> 0 | N38: ='KH Solar Actual'!S6 -> 0 | O38: ='KH Solar Actual'!T6 -> 0 | P38: ='KH Solar Actual'!U6 -> 0 | Q38: ='KH Solar Actual'!V6 -> 0 | ... U38: ='KH Solar Actual'!Z6 -> 0 | V38: =SUM(J38:U38) -> 50 | W38: =SUM(OFFSET(J38,0,0,1,$A$1)) -> 50 | Y38: =SUM(OFFSET($J38,0,0,1,$A$2)) -> 50 | Z38: =SUM(OFFSET($M38,0,0,1,$A$2)) -> 0 | AA38: =SUM(OFFSET($P38,0,0,1,$A$2)) -> 0 | AB38: =SUM(OFFSET($S38,0,0,1,$A$2)) -> 0
B39: 3 | C39: MLP AP New | D39: ARE57L | E39: PPA | F39: A-11 | G39: 187.5 | H39: PPA | I39: Plan | J39: ='KH Solar Plan'!AF6 -> 187.5 | K39: ='KH Solar Plan'!AG6 -> 0 | L39: ='KH Solar Plan'!AH6 -> 0 | M39: ='KH Solar Plan'!AI6 -> 0 | N39: ='KH Solar Plan'!AJ6 -> 0 | O39: ='KH Solar Plan'!AK6 -> 0 | P39: ='KH Solar Plan'!AL6 -> 0 | Q39: ='KH Solar Plan'!AM6 -> 0 | ... U39: ='KH Solar Plan'!AQ6 -> 0 | V39: =SUM(J39:U39) -> 187.5 | W39: =SUM(OFFSET(J39,0,0,1,$A$1)) -> 187.5 | Y39: =SUM(OFFSET($J39,0,0,1,$A$2)) -> 187.5 | Z39: =SUM(OFFSET($M39,0,0,1,$A$2)) -> 0 | AA39: =SUM(OFFSET($P39,0,0,1,$A$2)) -> 0 | AB39: =SUM(OFFSET($S39,0,0,1,$A$2)) -> 0
B40: 3 | C40: MLP AP New | D40: ARE57L | E40: PPA | F40: A-11 | H40: PPA | I40: Rephase | J40: ='KH Solar Rephase'!AE6 -> 75 | K40: ='KH Solar Rephase'!AF6 -> 112.5 | L40: ='KH Solar Rephase'!AG6 -> 0 | M40: ='KH Solar Rephase'!AH6 -> 0 | N40: ='KH Solar Rephase'!AI6 -> 0 | O40: ='KH Solar Rephase'!AJ6 -> 0 | P40: ='KH Solar Rephase'!AK6 -> 0 | Q40: ='KH Solar Rephase'!AL6 -> 0 | ... U40: ='KH Solar Rephase'!AP6 -> 0 | V40: =SUM(J40:U40) -> 187.5 | W40: =SUM(OFFSET(J40,0,0,1,$A$1)) -> 187.5 | Y40: =SUM(OFFSET($J40,0,0,1,$A$2)) -> 187.5 | Z40: =SUM(OFFSET($M40,0,0,1,$A$2)) -> 0 | AA40: =SUM(OFFSET($P40,0,0,1,$A$2)) -> 0 | AB40: =SUM(OFFSET($S40,0,0,1,$A$2)) -> 0
B41: 3 | C41: MLP AP New | D41: ARE57L | E41: PPA | F41: A-11 | H41: PPA | I41: Actual / Fcst | J41: ='KH Solar Actual'!O7 -> 75 | K41: ='KH Solar Actual'!P7 -> 112.5 | L41: ='KH Solar Actual'!Q7 -> 0 | M41: ='KH Solar Actual'!R7 -> 0 | N41: ='KH Solar Actual'!S7 -> 0 | O41: ='KH Solar Actual'!T7 -> 0 | P41: ='KH Solar Actual'!U7 -> 0 | Q41: ='KH Solar Actual'!V7 -> 0 | ... U41: ='KH Solar Actual'!Z7 -> 0 | V41: =SUM(J41:U41) -> 187.5 | W41: =SUM(OFFSET(J41,0,0,1,$A$1)) -> 187.5 | Y41: =SUM(OFFSET($J41,0,0,1,$A$2)) -> 187.5 | Z41: =SUM(OFFSET($M41,0,0,1,$A$2)) -> 0 | AA41: =SUM(OFFSET($P41,0,0,1,$A$2)) -> 0 | AB41: =SUM(OFFSET($S41,0,0,1,$A$2)) -> 0
B42: 4 | C42: MLP AP New | D42: ARE57L | E42: PPA | F42: A-12 | G42: 350 | H42: PPA | I42: Plan | J42: ='KH Solar Plan'!AF7 -> 0 | K42: ='KH Solar Plan'!AG7 -> 0 | L42: ='KH Solar Plan'!AH7 -> 100 | M42: ='KH Solar Plan'!AI7 -> 250 | N42: ='KH Solar Plan'!AJ7 -> 0 | O42: ='KH Solar Plan'!AK7 -> 0 | P42: ='KH Solar Plan'!AL7 -> 0 | Q42: ='KH Solar Plan'!AM7 -> 0 | ... U42: ='KH Solar Plan'!AQ7 -> 0 | V42: =SUM(J42:U42) -> 350 | W42: =SUM(OFFSET(J42,0,0,1,$A$1)) -> 350 | Y42: =SUM(OFFSET($J42,0,0,1,$A$2)) -> 100 | Z42: =SUM(OFFSET($M42,0,0,1,$A$2)) -> 250 | AA42: =SUM(OFFSET($P42,0,0,1,$A$2)) -> 0 | AB42: =SUM(OFFSET($S42,0,0,1,$A$2)) -> 0
B43: 4 | C43: MLP AP New | D43: ARE57L | E43: PPA | F43: A-12 | H43: PPA | I43: Rephase | J43: ='KH Solar Rephase'!AE7 -> 0 | K43: ='KH Solar Rephase'!AF7 -> 50 | L43: ='KH Solar Rephase'!AG7 -> 175 | M43: ='KH Solar Rephase'!AH7 -> 0 | N43: ='KH Solar Rephase'!AI7 -> 75 | O43: ='KH Solar Rephase'!AJ7 -> 50 | P43: ='KH Solar Rephase'!AK7 -> 0 | Q43: ='KH Solar Rephase'!AL7 -> 0 | ... U43: ='KH Solar Rephase'!AP7 -> 0 | V43: =SUM(J43:U43) -> 350 | W43: =SUM(OFFSET(J43,0,0,1,$A$1)) -> 350 | Y43: =SUM(OFFSET($J43,0,0,1,$A$2)) -> 225 | Z43: =SUM(OFFSET($M43,0,0,1,$A$2)) -> 125 | AA43: =SUM(OFFSET($P43,0,0,1,$A$2)) -> 0 | AB43: =SUM(OFFSET($S43,0,0,1,$A$2)) -> 0
B44: 4 | C44: MLP AP New | D44: ARE57L | E44: PPA | F44: A-12 | H44: PPA | I44: Actual / Fcst | J44: ='KH Solar Actual'!O8 -> 0 | K44: ='KH Solar Actual'!P8 -> 50 | L44: ='KH Solar Actual'!Q8 -> 175 | M44: ='KH Solar Actual'!R8 -> 0 | N44: ='KH Solar Actual'!S8 -> 0 | O44: ='KH Solar Actual'!T8 -> 0 | P44: ='KH Solar Actual'!U8 -> 0 | Q44: ='KH Solar Actual'!V8 -> 125 | ... U44: ='KH Solar Actual'!Z8 -> 0 | V44: =SUM(J44:U44) -> 350 | W44: =SUM(OFFSET(J44,0,0,1,$A$1)) -> 350 | Y44: =SUM(OFFSET($J44,0,0,1,$A$2)) -> 225 | Z44: =SUM(OFFSET($M44,0,0,1,$A$2)) -> 0 | AA44: =SUM(OFFSET($P44,0,0,1,$A$2)) -> 125 | AB44: =SUM(OFFSET($S44,0,0,1,$A$2)) -> 0
B45: 5 | C45: SECI H-3 | D45: AHEJ5L | E45: PPA | F45: A-13 | G45: 570 | H45: PPA | I45: Plan | J45: ='KH Solar Plan'!AF8 -> 295 | K45: ='KH Solar Plan'!AG8 -> 0 | L45: ='KH Solar Plan'!AH8 -> 275 | M45: ='KH Solar Plan'!AI8 -> 0 | N45: ='KH Solar Plan'!AJ8 -> 0 | O45: ='KH Solar Plan'!AK8 -> 0 | P45: ='KH Solar Plan'!AL8 -> 0 | Q45: ='KH Solar Plan'!AM8 -> 0 | ... U45: ='KH Solar Plan'!AQ8 -> 0 | V45: =SUM(J45:U45) -> 570 | W45: =SUM(OFFSET(J45,0,0,1,$A$1)) -> 570 | Y45: =SUM(OFFSET($J45,0,0,1,$A$2)) -> 570 | Z45: =SUM(OFFSET($M45,0,0,1,$A$2)) -> 0 | AA45: =SUM(OFFSET($P45,0,0,1,$A$2)) -> 0 | AB45: =SUM(OFFSET($S45,0,0,1,$A$2)) -> 0
B46: 5 | C46: SECI H-3 | D46: AHEJ5L | E46: PPA | F46: A-13 | H46: PPA | I46: Rephase | J46: ='KH Solar Rephase'!AE8 -> 145 | K46: ='KH Solar Rephase'!AF8 -> 0 | L46: ='KH Solar Rephase'!AG8 -> 150 | M46: ='KH Solar Rephase'!AH8 -> 75 | N46: ='KH Solar Rephase'!AI8 -> 0 | O46: ='KH Solar Rephase'!AJ8 -> 50 | P46: ='KH Solar Rephase'!AK8 -> 50 | Q46: ='KH Solar Rephase'!AL8 -> 100 | ... U46: ='KH Solar Rephase'!AP8 -> 0 | V46: =SUM(J46:U46) -> 570 | W46: =SUM(OFFSET(J46,0,0,1,$A$1)) -> 570 | Y46: =SUM(OFFSET($J46,0,0,1,$A$2)) -> 295 | Z46: =SUM(OFFSET($M46,0,0,1,$A$2)) -> 125 | AA46: =SUM(OFFSET($P46,0,0,1,$A$2)) -> 150 | AB46: =SUM(OFFSET($S46,0,0,1,$A$2)) -> 0
B47: 5 | C47: SECI H-3 | D47: AHEJ5L | E47: PPA | F47: A-13 | H47: PPA | I47: Actual / Fcst | J47: ='KH Solar Actual'!O9 -> 145 | K47: ='KH Solar Actual'!P9 -> 0 | L47: ='KH Solar Actual'!Q9 -> 150 | M47: ='KH Solar Actual'!R9 -> 0 | N47: ='KH Solar Actual'!S9 -> 50 | O47: ='KH Solar Actual'!T9 -> 75 | P47: ='KH Solar Actual'!U9 -> 75 | Q47: ='KH Solar Actual'!V9 -> 0 | ... U47: ='KH Solar Actual'!Z9 -> 0 | V47: =SUM(J47:U47) -> 570 | W47: =SUM(OFFSET(J47,0,0,1,$A$1)) -> 495 | Y47: =SUM(OFFSET($J47,0,0,1,$A$2)) -> 295 | Z47: =SUM(OFFSET($M47,0,0,1,$A$2)) -> 125 | AA47: =SUM(OFFSET($P47,0,0,1,$A$2)) -> 150 | AB47: =SUM(OFFSET($S47,0,0,1,$A$2)) -> 0
B48: 6 | C48: AGEL Merchant | D48: ARE45L | E48: Merchant | F48: A-14 | G48: 250 | H48: Merchant | I48: Plan | J48: ='KH Solar Plan'!AF9 -> 150 | K48: ='KH Solar Plan'!AG9 -> 100 | L48: ='KH Solar Plan'!AH9 -> 0 | M48: ='KH Solar Plan'!AI9 -> 0 | N48: ='KH Solar Plan'!AJ9 -> 0 | O48: ='KH Solar Plan'!AK9 -> 0 | P48: ='KH Solar Plan'!AL9 -> 0 | Q48: ='KH Solar Plan'!AM9 -> 0 | ... U48: ='KH Solar Plan'!AQ9 -> 0 | V48: =SUM(J48:U48) -> 250 | W48: =SUM(OFFSET(J48,0,0,1,$A$1)) -> 250 | Y48: =SUM(OFFSET($J48,0,0,1,$A$2)) -> 250 | Z48: =SUM(OFFSET($M48,0,0,1,$A$2)) -> 0 | AA48: =SUM(OFFSET($P48,0,0,1,$A$2)) -> 0 | AB48: =SUM(OFFSET($S48,0,0,1,$A$2)) -> 0
B49: 6 | C49: AGEL Merchant | D49: ARE45L | E49: Merchant | F49: A-14 | H49: Merchant | I49: Rephase | J49: ='KH Solar Rephase'!AE9 -> 50 | K49: ='KH Solar Rephase'!AF9 -> 0 | L49: ='KH Solar Rephase'!AG9 -> 125 | M49: ='KH Solar Rephase'!AH9 -> 0 | N49: ='KH Solar Rephase'!AI9 -> 75 | O49: ='KH Solar Rephase'!AJ9 -> 0 | P49: ='KH Solar Rephase'!AK9 -> 0 | Q49: ='KH Solar Rephase'!AL9 -> 0 | ... U49: ='KH Solar Rephase'!AP9 -> 0 | V49: =SUM(J49:U49) -> 250 | W49: =SUM(OFFSET(J49,0,0,1,$A$1)) -> 250 | Y49: =SUM(OFFSET($J49,0,0,1,$A$2)) -> 175 | Z49: =SUM(OFFSET($M49,0,0,1,$A$2)) -> 75 | AA49: =SUM(OFFSET($P49,0,0,1,$A$2)) -> 0 | AB49: =SUM(OFFSET($S49,0,0,1,$A$2)) -> 0
B50: 6 | C50: AGEL Merchant | D50: ARE45L | E50: Merchant | F50: A-14 | H50: Merchant | I50: Actual / Fcst | J50: ='KH Solar Actual'!O10 -> 50 | K50: ='KH Solar Actual'!P10 -> 0 | L50: ='KH Solar Actual'!Q10 -> 125 | M50: ='KH Solar Actual'!R10 -> 0 | N50: ='KH Solar Actual'!S10 -> 0 | O50: ='KH Solar Actual'!T10 -> 75 | P50: ='KH Solar Actual'!U10 -> 0 | Q50: ='KH Solar Actual'!V10 -> 0 | ... U50: ='KH Solar Actual'!Z10 -> 0 | V50: =SUM(J50:U50) -> 250 | W50: =SUM(OFFSET(J50,0,0,1,$A$1)) -> 250 | Y50: =SUM(OFFSET($J50,0,0,1,$A$2)) -> 175 | Z50: =SUM(OFFSET($M50,0,0,1,$A$2)) -> 75 | AA50: =SUM(OFFSET($P50,0,0,1,$A$2)) -> 0 | AB50: =SUM(OFFSET($S50,0,0,1,$A$2)) -> 0
B51: 7 | C51: MLP T3 AP | D51: ARE56L | E51: PPA | F51: S-06 | G51: 500 | H51: PPA | I51: Plan | J51: ='KH Solar Plan'!AF10 -> 100 | K51: ='KH Solar Plan'!AG10 -> 0 | L51: ='KH Solar Plan'!AH10 -> 100 | M51: ='KH Solar Plan'!AI10 -> 300 | N51: ='KH Solar Plan'!AJ10 -> 0 | O51: ='KH Solar Plan'!AK10 -> 0 | P51: ='KH Solar Plan'!AL10 -> 0 | Q51: ='KH Solar Plan'!AM10 -> 0 | ... U51: ='KH Solar Plan'!AQ10 -> 0 | V51: =SUM(J51:U51) -> 500 | W51: =SUM(OFFSET(J51,0,0,1,$A$1)) -> 500 | Y51: =SUM(OFFSET($J51,0,0,1,$A$2)) -> 200 | Z51: =SUM(OFFSET($M51,0,0,1,$A$2)) -> 300 | AA51: =SUM(OFFSET($P51,0,0,1,$A$2)) -> 0 | AB51: =SUM(OFFSET($S51,0,0,1,$A$2)) -> 0
B52: 7 | C52: MLP T3 AP | D52: ARE56L | E52: PPA | F52: S-06 | H52: PPA | I52: Rephase | J52: ='KH Solar Rephase'!AE10 -> 100 | K52: ='KH Solar Rephase'!AF10 -> 0 | L52: ='KH Solar Rephase'!AG10 -> 137.5 | M52: ='KH Solar Rephase'!AH10 -> 112.5 | N52: ='KH Solar Rephase'!AI10 -> 0 | O52: ='KH Solar Rephase'!AJ10 -> 50 | P52: ='KH Solar Rephase'!AK10 -> 50 | Q52: ='KH Solar Rephase'!AL10 -> 50 | ... U52: ='KH Solar Rephase'!AP10 -> 0 | V52: =SUM(J52:U52) -> 500 | W52: =SUM(OFFSET(J52,0,0,1,$A$1)) -> 500 | Y52: =SUM(OFFSET($J52,0,0,1,$A$2)) -> 237.5 | Z52: =SUM(OFFSET($M52,0,0,1,$A$2)) -> 162.5 | AA52: =SUM(OFFSET($P52,0,0,1,$A$2)) -> 100 | AB52: =SUM(OFFSET($S52,0,0,1,$A$2)) -> 0
B53: 7 | C53: MLP T3 AP | D53: ARE56L | E53: PPA | F53: S-06 | H53: PPA | I53: Actual / Fcst | J53: ='KH Solar Actual'!O11 -> 100 | K53: ='KH Solar Actual'!P11 -> 0 | L53: ='KH Solar Actual'!Q11 -> 137.5 | M53: ='KH Solar Actual'!R11 -> 0 | N53: ='KH Solar Actual'!S11 -> 87.5 | O53: ='KH Solar Actual'!T11 -> 100 | P53: ='KH Solar Actual'!U11 -> 0 | Q53: ='KH Solar Actual'!V11 -> 75 | ... U53: ='KH Solar Actual'!Z11 -> 0 | V53: =SUM(J53:U53) -> 500 | W53: =SUM(OFFSET(J53,0,0,1,$A$1)) -> 500 | Y53: =SUM(OFFSET($J53,0,0,1,$A$2)) -> 237.5 | Z53: =SUM(OFFSET($M53,0,0,1,$A$2)) -> 187.5 | AA53: =SUM(OFFSET($P53,0,0,1,$A$2)) -> 75 | AB53: =SUM(OFFSET($S53,0,0,1,$A$2)) -> 0
B54: 8 | C54: Google Hybrid | D54: ARE3L | E54: Merchant | F54: A-6 | G54: 25 | H54: Merchant | I54: Plan | J54: ='KH Solar Plan'!AF23 -> 0 | K54: ='KH Solar Plan'!AG23 -> 0 | L54: ='KH Solar Plan'!AH23 -> 25 | M54: ='KH Solar Plan'!AI23 -> 0 | N54: ='KH Solar Plan'!AJ23 -> 0 | O54: ='KH Solar Plan'!AK23 -> 0 | P54: ='KH Solar Plan'!AL23 -> 0 | Q54: ='KH Solar Plan'!AM23 -> 0 | ... U54: ='KH Solar Plan'!AQ23 -> 0 | V54: =SUM(J54:U54) -> 25 | W54: =SUM(OFFSET(J54,0,0,1,$A$1)) -> 25 | Y54: =SUM(OFFSET($J54,0,0,1,$A$2)) -> 25 | Z54: =SUM(OFFSET($M54,0,0,1,$A$2)) -> 0 | AA54: =SUM(OFFSET($P54,0,0,1,$A$2)) -> 0 | AB54: =SUM(OFFSET($S54,0,0,1,$A$2)) -> 0
B55: 8 | C55: Google Hybrid | D55: ARE3L | E55: Merchant | F55: A-6 | H55: Merchant | I55: Rephase | J55: ='KH Solar Rephase'!AE14 -> 0 | K55: ='KH Solar Rephase'!AF14 -> 0 | L55: ='KH Solar Rephase'!AG14 -> 0 | M55: ='KH Solar Rephase'!AH14 -> 25 | N55: ='KH Solar Rephase'!AI14 -> 0 | O55: ='KH Solar Rephase'!AJ14 -> 0 | P55: ='KH Solar Rephase'!AK14 -> 0 | Q55: ='KH Solar Rephase'!AL14 -> 0 | ... U55: ='KH Solar Rephase'!AP14 -> 0 | V55: =SUM(J55:U55) -> 25 | W55: =SUM(OFFSET(J55,0,0,1,$A$1)) -> 25 | Y55: =SUM(OFFSET($J55,0,0,1,$A$2)) -> 0 | Z55: =SUM(OFFSET($M55,0,0,1,$A$2)) -> 25 | AA55: =SUM(OFFSET($P55,0,0,1,$A$2)) -> 0 | AB55: =SUM(OFFSET($S55,0,0,1,$A$2)) -> 0
B56: 8 | C56: Google Hybrid | D56: ARE3L | E56: Merchant | F56: A-6 | H56: Merchant | I56: Actual / Fcst | J56: ='KH Solar Actual'!O12 -> 0 | K56: ='KH Solar Actual'!P12 -> 0 | L56: ='KH Solar Actual'!Q12 -> 0 | M56: ='KH Solar Actual'!R12 -> 25 | N56: ='KH Solar Actual'!S12 -> 0 | O56: ='KH Solar Actual'!T12 -> 0 | P56: ='KH Solar Actual'!U12 -> 0 | Q56: ='KH Solar Actual'!V12 -> 0 | ... U56: ='KH Solar Actual'!Z12 -> 0 | V56: =SUM(J56:U56) -> 25 | W56: =SUM(OFFSET(J56,0,0,1,$A$1)) -> 25 | Y56: =SUM(OFFSET($J56,0,0,1,$A$2)) -> 0 | Z56: =SUM(OFFSET($M56,0,0,1,$A$2)) -> 25 | AA56: =SUM(OFFSET($P56,0,0,1,$A$2)) -> 0 | AB56: =SUM(OFFSET($S56,0,0,1,$A$2)) -> 0
B57: 9 | C57: AGEL Merchant | D57: ASEJ6PL | E57: Merchant | F57: A-6 | G57: 35 | H57: Merchant | I57: Plan | J57: ='KH Solar Plan'!AF24 -> 0 | K57: ='KH Solar Plan'!AG24 -> 0 | L57: ='KH Solar Plan'!AH24 -> 35 | M57: ='KH Solar Plan'!AI24 -> 0 | N57: ='KH Solar Plan'!AJ24 -> 0 | O57: ='KH Solar Plan'!AK24 -> 0 | P57: ='KH Solar Plan'!AL24 -> 0 | Q57: ='KH Solar Plan'!AM24 -> 0 | ... U57: ='KH Solar Plan'!AQ24 -> 0 | V57: =SUM(J57:U57) -> 35 | W57: =SUM(OFFSET(J57,0,0,1,$A$1)) -> 35 | Y57: =SUM(OFFSET($J57,0,0,1,$A$2)) -> 35 | Z57: =SUM(OFFSET($M57,0,0,1,$A$2)) -> 0 | AA57: =SUM(OFFSET($P57,0,0,1,$A$2)) -> 0 | AB57: =SUM(OFFSET($S57,0,0,1,$A$2)) -> 0
B58: 9 | C58: AGEL Merchant | D58: ASEJ6PL | E58: Merchant | F58: A-6 | H58: Merchant | I58: Rephase | J58: ='KH Solar Rephase'!AE15 -> 0 | K58: ='KH Solar Rephase'!AF15 -> 0 | L58: ='KH Solar Rephase'!AG15 -> 0 | M58: ='KH Solar Rephase'!AH15 -> 35 | N58: ='KH Solar Rephase'!AI15 -> 0 | O58: ='KH Solar Rephase'!AJ15 -> 0 | P58: ='KH Solar Rephase'!AK15 -> 0 | Q58: ='KH Solar Rephase'!AL15 -> 0 | ... U58: ='KH Solar Rephase'!AP15 -> 0 | V58: =SUM(J58:U58) -> 35 | W58: =SUM(OFFSET(J58,0,0,1,$A$1)) -> 35 | Y58: =SUM(OFFSET($J58,0,0,1,$A$2)) -> 0 | Z58: =SUM(OFFSET($M58,0,0,1,$A$2)) -> 35 | AA58: =SUM(OFFSET($P58,0,0,1,$A$2)) -> 0 | AB58: =SUM(OFFSET($S58,0,0,1,$A$2)) -> 0
B59: 9 | C59: AGEL Merchant | D59: ASEJ6PL | E59: Merchant | F59: A-6 | H59: Merchant | I59: Actual / Fcst | J59: ='KH Solar Actual'!O13 -> 0 | K59: ='KH Solar Actual'!P13 -> 0 | L59: ='KH Solar Actual'!Q13 -> 0 | M59: ='KH Solar Actual'!R13 -> 35 | N59: ='KH Solar Actual'!S13 -> 0 | O59: ='KH Solar Actual'!T13 -> 0 | P59: ='KH Solar Actual'!U13 -> 0 | Q59: ='KH Solar Actual'!V13 -> 0 | ... U59: ='KH Solar Actual'!Z13 -> 0 | V59: =SUM(J59:U59) -> 35 | W59: =SUM(OFFSET(J59,0,0,1,$A$1)) -> 35 | Y59: =SUM(OFFSET($J59,0,0,1,$A$2)) -> 0 | Z59: =SUM(OFFSET($M59,0,0,1,$A$2)) -> 35 | AA59: =SUM(OFFSET($P59,0,0,1,$A$2)) -> 0 | AB59: =SUM(OFFSET($S59,0,0,1,$A$2)) -> 0
B60: 10 | C60: AGEL Hybrid Merchant | D60: AGE25BL | E60: Merchant | F60: S-8 | G60: 100 | H60: Merchant | I60: Plan | J60: ='KH Solar Plan'!AF25 -> 0 | K60: ='KH Solar Plan'!AG25 -> 0 | L60: ='KH Solar Plan'!AH25 -> 0 | M60: ='KH Solar Plan'!AI25 -> 0 | N60: ='KH Solar Plan'!AJ25 -> 0 | O60: ='KH Solar Plan'!AK25 -> 0 | P60: ='KH Solar Plan'!AL25 -> 0 | Q60: ='KH Solar Plan'!AM25 -> 0 | ... U60: ='KH Solar Plan'!AQ25 -> 0 | V60: =SUM(J60:U60) -> 100 | W60: =SUM(OFFSET(J60,0,0,1,$A$1)) -> 0 | Y60: =SUM(OFFSET($J60,0,0,1,$A$2)) -> 0 | Z60: =SUM(OFFSET($M60,0,0,1,$A$2)) -> 0 | AA60: =SUM(OFFSET($P60,0,0,1,$A$2)) -> 0 | AB60: =SUM(OFFSET($S60,0,0,1,$A$2)) -> 100
B61: 10 | C61: AGEL Hybrid Merchant | D61: AGE25BL | E61: Merchant | F61: S-8 | H61: Merchant | I61: Rephase | J61: ='KH Solar Rephase'!AE16 -> 0 | K61: ='KH Solar Rephase'!AF16 -> 0 | L61: ='KH Solar Rephase'!AG16 -> 0 | M61: ='KH Solar Rephase'!AH16 -> 0 | N61: ='KH Solar Rephase'!AI16 -> 50 | O61: ='KH Solar Rephase'!AJ16 -> 0 | P61: ='KH Solar Rephase'!AK16 -> 0 | Q61: ='KH Solar Rephase'!AL16 -> 50 | ... U61: ='KH Solar Rephase'!AP16 -> 0 | V61: =SUM(J61:U61) -> 100 | W61: =SUM(OFFSET(J61,0,0,1,$A$1)) -> 100 | Y61: =SUM(OFFSET($J61,0,0,1,$A$2)) -> 0 | Z61: =SUM(OFFSET($M61,0,0,1,$A$2)) -> 50 | AA61: =SUM(OFFSET($P61,0,0,1,$A$2)) -> 50 | AB61: =SUM(OFFSET($S61,0,0,1,$A$2)) -> 0
B62: 10 | C62: AGEL Hybrid Merchant | D62: AGE25BL | E62: Merchant | F62: S-8 | H62: Merchant | I62: Actual / Fcst | J62: ='KH Solar Actual'!O14 -> 0 | K62: ='KH Solar Actual'!P14 -> 0 | L62: ='KH Solar Actual'!Q14 -> 0 | M62: ='KH Solar Actual'!R14 -> 0 | N62: ='KH Solar Actual'!S14 -> 0 | O62: ='KH Solar Actual'!T14 -> 100 | P62: ='KH Solar Actual'!U14 -> 0 | Q62: ='KH Solar Actual'!V14 -> 0 | ... U62: ='KH Solar Actual'!Z14 -> 0 | V62: =SUM(J62:U62) -> 100 | W62: =SUM(OFFSET(J62,0,0,1,$A$1)) -> 100 | Y62: =SUM(OFFSET($J62,0,0,1,$A$2)) -> 0 | Z62: =SUM(OFFSET($M62,0,0,1,$A$2)) -> 100 | AA62: =SUM(OFFSET($P62,0,0,1,$A$2)) -> 0 | AB62: =SUM(OFFSET($S62,0,0,1,$A$2)) -> 0
B63: 11 | C63: AGEL Merchant | D63: AHEJ5L | E63: Merchant | F63: A-15a | G63: 150 | H63: Merchant | I63: Plan | J63: ='KH Solar Plan'!AF26 -> 0 | K63: ='KH Solar Plan'!AG26 -> 0 | L63: ='KH Solar Plan'!AH26 -> 0 | M63: ='KH Solar Plan'!AI26 -> 0 | N63: ='KH Solar Plan'!AJ26 -> 0 | O63: ='KH Solar Plan'!AK26 -> 0 | P63: ='KH Solar Plan'!AL26 -> 0 | Q63: ='KH Solar Plan'!AM26 -> 50 | ... U63: ='KH Solar Plan'!AQ26 -> 0 | V63: =SUM(J63:U63) -> 150 | W63: =SUM(OFFSET(J63,0,0,1,$A$1)) -> 50 | Y63: =SUM(OFFSET($J63,0,0,1,$A$2)) -> 0 | Z63: =SUM(OFFSET($M63,0,0,1,$A$2)) -> 0 | AA63: =SUM(OFFSET($P63,0,0,1,$A$2)) -> 50 | AB63: =SUM(OFFSET($S63,0,0,1,$A$2)) -> 100
B64: 11 | C64: AGEL Merchant | D64: AHEJ5L | E64: Merchant | F64: A-15a | H64: Merchant | I64: Rephase | J64: ='KH Solar Rephase'!AE17 -> 0 | K64: ='KH Solar Rephase'!AF17 -> 0 | L64: ='KH Solar Rephase'!AG17 -> 0 | M64: ='KH Solar Rephase'!AH17 -> 0 | N64: ='KH Solar Rephase'!AI17 -> 0 | O64: ='KH Solar Rephase'!AJ17 -> 0 | P64: ='KH Solar Rephase'!AK17 -> 50 | Q64: ='KH Solar Rephase'!AL17 -> 50 | ... U64: ='KH Solar Rephase'!AP17 -> 0 | V64: =SUM(J64:U64) -> 150 | W64: =SUM(OFFSET(J64,0,0,1,$A$1)) -> 100 | Y64: =SUM(OFFSET($J64,0,0,1,$A$2)) -> 0 | Z64: =SUM(OFFSET($M64,0,0,1,$A$2)) -> 0 | AA64: =SUM(OFFSET($P64,0,0,1,$A$2)) -> 100 | AB64: =SUM(OFFSET($S64,0,0,1,$A$2)) -> 50
B65: 11 | C65: AGEL Merchant | D65: AHEJ5L | E65: Merchant | F65: A-15a | H65: Merchant | I65: Actual / Fcst | J65: ='KH Solar Actual'!O15 -> 0 | K65: ='KH Solar Actual'!P15 -> 0 | L65: ='KH Solar Actual'!Q15 -> 0 | M65: ='KH Solar Actual'!R15 -> 0 | N65: ='KH Solar Actual'!S15 -> 0 | O65: ='KH Solar Actual'!T15 -> 50 | P65: ='KH Solar Actual'!U15 -> 0 | Q65: ='KH Solar Actual'!V15 -> 0 | ... U65: ='KH Solar Actual'!Z15 -> 0 | V65: =SUM(J65:U65) -> 150 | W65: =SUM(OFFSET(J65,0,0,1,$A$1)) -> 50 | Y65: =SUM(OFFSET($J65,0,0,1,$A$2)) -> 0 | Z65: =SUM(OFFSET($M65,0,0,1,$A$2)) -> 50 | AA65: =SUM(OFFSET($P65,0,0,1,$A$2)) -> 0 | AB65: =SUM(OFFSET($S65,0,0,1,$A$2)) -> 100
B66: 12 | C66: AGEL Hybrid Merchant | D66: AGE26BL | E66: Merchant | F66: S-5 | G66: 292 | H66: Merchant | I66: Plan | J66: =J69+J72 -> 0 | K66: =K69+K72 -> 100 | L66: =L69+L72 -> 192 | M66: =M69+M72 -> 0 | N66: =N69+N72 -> 0 | O66: =O69+O72 -> 0 | P66: =P69+P72 -> 0 | Q66: =Q69+Q72 -> 0 | ... U66: =U69+U72 -> 0 | V66: =SUM(J66:U66) -> 292 | W66: =SUM(OFFSET(J66,0,0,1,$A$1)) -> 292 | Y66: =SUM(OFFSET($J66,0,0,1,$A$2)) -> 292 | Z66: =SUM(OFFSET($M66,0,0,1,$A$2)) -> 0 | AA66: =SUM(OFFSET($P66,0,0,1,$A$2)) -> 0 | AB66: =SUM(OFFSET($S66,0,0,1,$A$2)) -> 0
B67: 12 | C67: AGEL Hybrid Merchant | D67: AGE26BL | E67: Merchant | F67: S-5 | H67: Merchant | I67: Rephase | J67: =J70+J73 -> 0 | K67: =K70+K73 -> 0 | L67: =L70+L73 -> 0 | M67: =M70+M73 -> 50 | N67: =N70+N73 -> 0 | O67: =O70+O73 -> 75 | P67: =P70+P73 -> 62 | Q67: =Q70+Q73 -> 105 | ... U67: =U70+U73 -> 0 | V67: =SUM(J67:U67) -> 292 | W67: =SUM(OFFSET(J67,0,0,1,$A$1)) -> 292 | Y67: =SUM(OFFSET($J67,0,0,1,$A$2)) -> 0 | Z67: =SUM(OFFSET($M67,0,0,1,$A$2)) -> 125 | AA67: =SUM(OFFSET($P67,0,0,1,$A$2)) -> 167 | AB67: =SUM(OFFSET($S67,0,0,1,$A$2)) -> 0
B68: 12 | C68: AGEL Hybrid Merchant | D68: AGE26BL | E68: Merchant | F68: S-5 | H68: Merchant | I68: Actual / Fcst | J68: =J71+J74 -> 0 | K68: =K71+K74 -> 0 | L68: =L71+L74 -> 0 | M68: =M71+M74 -> 0 | N68: =N71+N74 -> 0 | O68: =O71+O74 -> 50 | P68: =P71+P74 -> 0 | Q68: =Q71+Q74 -> 50 | ... U68: =U71+U74 -> 0 | V68: =SUM(J68:U68) -> 292 | W68: =SUM(OFFSET(J68,0,0,1,$A$1)) -> 100 | Y68: =SUM(OFFSET($J68,0,0,1,$A$2)) -> 0 | Z68: =SUM(OFFSET($M68,0,0,1,$A$2)) -> 50 | AA68: =SUM(OFFSET($P68,0,0,1,$A$2)) -> 100 | AB68: =SUM(OFFSET($S68,0,0,1,$A$2)) -> 142
B69: 12a | C69: AGEL Hybrid Merchant | D69: AGE26BL | E69: Merchant | F69: S-5 | G69: 142 | J69: ='KH Solar Plan'!AF27 -> 0 | K69: ='KH Solar Plan'!AG27 -> 100 | L69: ='KH Solar Plan'!AH27 -> 42 | M69: ='KH Solar Plan'!AI27 -> 0 | N69: ='KH Solar Plan'!AJ27 -> 0 | O69: ='KH Solar Plan'!AK27 -> 0 | P69: ='KH Solar Plan'!AL27 -> 0 | Q69: ='KH Solar Plan'!AM27 -> 0 | ... U69: ='KH Solar Plan'!AQ27 -> 0 | V69: =SUM(J69:U69) -> 142 | W69: =SUM(OFFSET(J69,0,0,1,$A$1)) -> 142 | Y69: =SUM(OFFSET($J69,0,0,1,$A$2)) -> 142 | Z69: =SUM(OFFSET($M69,0,0,1,$A$2)) -> 0 | AA69: =SUM(OFFSET($P69,0,0,1,$A$2)) -> 0 | AB69: =SUM(OFFSET($S69,0,0,1,$A$2)) -> 0
B70: 12 | C70: AGEL Hybrid Merchant | D70: AGE26BL | E70: Merchant | F70: S-5 | J70: ='KH Solar Rephase'!AE18 -> 0 | K70: ='KH Solar Rephase'!AF18 -> 0 | L70: ='KH Solar Rephase'!AG18 -> 0 | M70: ='KH Solar Rephase'!AH18 -> 50 | N70: ='KH Solar Rephase'!AI18 -> 0 | O70: ='KH Solar Rephase'!AJ18 -> 75 | P70: ='KH Solar Rephase'!AK18 -> 17 | Q70: ='KH Solar Rephase'!AL18 -> 0 | ... U70: ='KH Solar Rephase'!AP18 -> 0 | V70: =SUM(J70:U70) -> 142 | W70: =SUM(OFFSET(J70,0,0,1,$A$1)) -> 142 | Y70: =SUM(OFFSET($J70,0,0,1,$A$2)) -> 0 | Z70: =SUM(OFFSET($M70,0,0,1,$A$2)) -> 125 | AA70: =SUM(OFFSET($P70,0,0,1,$A$2)) -> 17 | AB70: =SUM(OFFSET($S70,0,0,1,$A$2)) -> 0
B71: 12 | C71: AGEL Hybrid Merchant | D71: AGE26BL | E71: Merchant | F71: S-5 | J71: ='KH Solar Actual'!O17 -> 0 | K71: ='KH Solar Actual'!P17 -> 0 | L71: ='KH Solar Actual'!Q17 -> 0 | M71: ='KH Solar Actual'!R17 -> 0 | N71: ='KH Solar Actual'!S17 -> 0 | O71: ='KH Solar Actual'!T17 -> 50 | P71: ='KH Solar Actual'!U17 -> 0 | Q71: ='KH Solar Actual'!V17 -> 50 | ... U71: ='KH Solar Actual'!Z17 -> 0 | V71: =SUM(J71:U71) -> 142 | W71: =SUM(OFFSET(J71,0,0,1,$A$1)) -> 100 | Y71: =SUM(OFFSET($J71,0,0,1,$A$2)) -> 0 | Z71: =SUM(OFFSET($M71,0,0,1,$A$2)) -> 50 | AA71: =SUM(OFFSET($P71,0,0,1,$A$2)) -> 50 | AB71: =SUM(OFFSET($S71,0,0,1,$A$2)) -> 42
B72: 12b | C72: AGEL Merchant | D72: AGE26BL | E72: Merchant | F72: S-5 | G72: 150 | J72: ='KH Solar Plan'!AF28 -> 0 | K72: ='KH Solar Plan'!AG28 -> 0 | L72: ='KH Solar Plan'!AH28 -> 150 | M72: ='KH Solar Plan'!AI28 -> 0 | N72: ='KH Solar Plan'!AJ28 -> 0 | O72: ='KH Solar Plan'!AK28 -> 0 | P72: ='KH Solar Plan'!AL28 -> 0 | Q72: ='KH Solar Plan'!AM28 -> 0 | ... U72: ='KH Solar Plan'!AQ28 -> 0 | V72: =SUM(J72:U72) -> 150 | W72: =SUM(OFFSET(J72,0,0,1,$A$1)) -> 150 | Y72: =SUM(OFFSET($J72,0,0,1,$A$2)) -> 150 | Z72: =SUM(OFFSET($M72,0,0,1,$A$2)) -> 0 | AA72: =SUM(OFFSET($P72,0,0,1,$A$2)) -> 0 | AB72: =SUM(OFFSET($S72,0,0,1,$A$2)) -> 0
B73: 12 | C73: AGEL Hybrid Merchant | D73: AGE26BL | E73: Merchant | F73: S-5 | J73: ='KH Solar Rephase'!AE19 -> 0 | K73: ='KH Solar Rephase'!AF19 -> 0 | L73: ='KH Solar Rephase'!AG19 -> 0 | M73: ='KH Solar Rephase'!AH19 -> 0 | N73: ='KH Solar Rephase'!AI19 -> 0 | O73: ='KH Solar Rephase'!AJ19 -> 0 | P73: ='KH Solar Rephase'!AK19 -> 45 | Q73: ='KH Solar Rephase'!AL19 -> 105 | ... U73: ='KH Solar Rephase'!AP19 -> 0 | V73: =SUM(J73:U73) -> 150 | W73: =SUM(OFFSET(J73,0,0,1,$A$1)) -> 150 | Y73: =SUM(OFFSET($J73,0,0,1,$A$2)) -> 0 | Z73: =SUM(OFFSET($M73,0,0,1,$A$2)) -> 0 | AA73: =SUM(OFFSET($P73,0,0,1,$A$2)) -> 150 | AB73: =SUM(OFFSET($S73,0,0,1,$A$2)) -> 0
B74: 12 | C74: AGEL Hybrid Merchant | D74: AGE26BL | E74: Merchant | F74: S-5 | J74: ='KH Solar Actual'!O18 -> 0 | K74: ='KH Solar Actual'!P18 -> 0 | L74: ='KH Solar Actual'!Q18 -> 0 | M74: ='KH Solar Actual'!R18 -> 0 | N74: ='KH Solar Actual'!S18 -> 0 | O74: ='KH Solar Actual'!T18 -> 0 | P74: ='KH Solar Actual'!U18 -> 0 | Q74: ='KH Solar Actual'!V18 -> 0 | ... U74: ='KH Solar Actual'!Z18 -> 0 | V74: =SUM(J74:U74) -> 150 | W74: =SUM(OFFSET(J74,0,0,1,$A$1)) -> 0 | Y74: =SUM(OFFSET($J74,0,0,1,$A$2)) -> 0 | Z74: =SUM(OFFSET($M74,0,0,1,$A$2)) -> 0 | AA74: =SUM(OFFSET($P74,0,0,1,$A$2)) -> 50 | AB74: =SUM(OFFSET($S74,0,0,1,$A$2)) -> 100
B75: 13 | C75: AGEL Merchant | D75: AGE24L | E75: Merchant | F75: S-5 | G75: 150 | H75: Merchant | I75: Plan | J75: ='KH Solar Plan'!AF29 -> 0 | K75: ='KH Solar Plan'!AG29 -> 50 | L75: ='KH Solar Plan'!AH29 -> 100 | M75: ='KH Solar Plan'!AI29 -> 0 | N75: ='KH Solar Plan'!AJ29 -> 0 | O75: ='KH Solar Plan'!AK29 -> 0 | P75: ='KH Solar Plan'!AL29 -> 0 | Q75: ='KH Solar Plan'!AM29 -> 0 | ... U75: ='KH Solar Plan'!AQ29 -> 0 | V75: =SUM(J75:U75) -> 150 | W75: =SUM(OFFSET(J75,0,0,1,$A$1)) -> 150 | Y75: =SUM(OFFSET($J75,0,0,1,$A$2)) -> 150 | Z75: =SUM(OFFSET($M75,0,0,1,$A$2)) -> 0 | AA75: =SUM(OFFSET($P75,0,0,1,$A$2)) -> 0 | AB75: =SUM(OFFSET($S75,0,0,1,$A$2)) -> 0
B76: 13 | C76: AGEL Merchant | D76: AGE24L | E76: Merchant | F76: S-5 | H76: Merchant | I76: Rephase | J76: ='KH Solar Rephase'!AE20 -> 0 | K76: ='KH Solar Rephase'!AF20 -> 0 | L76: ='KH Solar Rephase'!AG20 -> 0 | M76: ='KH Solar Rephase'!AH20 -> 0 | N76: ='KH Solar Rephase'!AI20 -> 0 | O76: ='KH Solar Rephase'!AJ20 -> 0 | P76: ='KH Solar Rephase'!AK20 -> 0 | Q76: ='KH Solar Rephase'!AL20 -> 0 | ... U76: ='KH Solar Rephase'!AP20 -> 0 | V76: =SUM(J76:U76) -> 150 | W76: =SUM(OFFSET(J76,0,0,1,$A$1)) -> 0 | Y76: =SUM(OFFSET($J76,0,0,1,$A$2)) -> 0 | Z76: =SUM(OFFSET($M76,0,0,1,$A$2)) -> 0 | AA76: =SUM(OFFSET($P76,0,0,1,$A$2)) -> 0 | AB76: =SUM(OFFSET($S76,0,0,1,$A$2)) -> 150
B77: 13 | C77: AGEL Merchant | D77: AGE24L | E77: Merchant | F77: S-5 | H77: Merchant | I77: Actual / Fcst | J77: ='KH Solar Actual'!O19 -> 0 | K77: ='KH Solar Actual'!P19 -> 0 | L77: ='KH Solar Actual'!Q19 -> 0 | M77: ='KH Solar Actual'!R19 -> 0 | N77: ='KH Solar Actual'!S19 -> 0 | O77: ='KH Solar Actual'!T19 -> 0 | P77: ='KH Solar Actual'!U19 -> 0 | Q77: ='KH Solar Actual'!V19 -> 0 | ... U77: ='KH Solar Actual'!Z19 -> 0 | V77: =SUM(J77:U77) -> 150 | W77: =SUM(OFFSET(J77,0,0,1,$A$1)) -> 0 | Y77: =SUM(OFFSET($J77,0,0,1,$A$2)) -> 0 | Z77: =SUM(OFFSET($M77,0,0,1,$A$2)) -> 0 | AA77: =SUM(OFFSET($P77,0,0,1,$A$2)) -> 0 | AB77: =SUM(OFFSET($S77,0,0,1,$A$2)) -> 150
B78: 14 | C78: AGEL Merchant | D78: AGE24L | E78: Merchant | F78: A-14 | G78: 150 | H78: Merchant | I78: Plan | J78: ='KH Solar Plan'!AF30 -> 0 | K78: ='KH Solar Plan'!AG30 -> 0 | L78: ='KH Solar Plan'!AH30 -> 0 | M78: ='KH Solar Plan'!AI30 -> 0 | N78: ='KH Solar Plan'!AJ30 -> 0 | O78: ='KH Solar Plan'!AK30 -> 0 | P78: ='KH Solar Plan'!AL30 -> 0 | Q78: ='KH Solar Plan'!AM30 -> 150 | ... U78: ='KH Solar Plan'!AQ30 -> 0 | V78: =SUM(J78:U78) -> 150 | W78: =SUM(OFFSET(J78,0,0,1,$A$1)) -> 150 | Y78: =SUM(OFFSET($J78,0,0,1,$A$2)) -> 0 | Z78: =SUM(OFFSET($M78,0,0,1,$A$2)) -> 0 | AA78: =SUM(OFFSET($P78,0,0,1,$A$2)) -> 150 | AB78: =SUM(OFFSET($S78,0,0,1,$A$2)) -> 0
B79: 14 | C79: AGEL Merchant | D79: AGE24L | E79: Merchant | F79: A-14 | H79: Merchant | I79: Rephase | J79: ='KH Solar Rephase'!AE21 -> 0 | K79: ='KH Solar Rephase'!AF21 -> 0 | L79: ='KH Solar Rephase'!AG21 -> 0 | M79: ='KH Solar Rephase'!AH21 -> 0 | N79: ='KH Solar Rephase'!AI21 -> 0 | O79: ='KH Solar Rephase'!AJ21 -> 0 | P79: ='KH Solar Rephase'!AK21 -> 0 | Q79: ='KH Solar Rephase'!AL21 -> 0 | ... U79: ='KH Solar Rephase'!AP21 -> 0 | V79: =SUM(J79:U79) -> 150 | W79: =SUM(OFFSET(J79,0,0,1,$A$1)) -> 0 | Y79: =SUM(OFFSET($J79,0,0,1,$A$2)) -> 0 | Z79: =SUM(OFFSET($M79,0,0,1,$A$2)) -> 0 | AA79: =SUM(OFFSET($P79,0,0,1,$A$2)) -> 0 | AB79: =SUM(OFFSET($S79,0,0,1,$A$2)) -> 150
B80: 14 | C80: AGEL Merchant | D80: AGE24L | E80: Merchant | F80: A-14 | H80: Merchant | I80: Actual / Fcst | J80: ='KH Solar Actual'!O20 -> 0 | K80: ='KH Solar Actual'!P20 -> 0 | L80: ='KH Solar Actual'!Q20 -> 0 | M80: ='KH Solar Actual'!R20 -> 0 | N80: ='KH Solar Actual'!S20 -> 0 | O80: ='KH Solar Actual'!T20 -> 0 | P80: ='KH Solar Actual'!U20 -> 0 | Q80: ='KH Solar Actual'!V20 -> 0 | ... U80: ='KH Solar Actual'!Z20 -> 0 | V80: =SUM(J80:U80) -> 150 | W80: =SUM(OFFSET(J80,0,0,1,$A$1)) -> 0 | Y80: =SUM(OFFSET($J80,0,0,1,$A$2)) -> 0 | Z80: =SUM(OFFSET($M80,0,0,1,$A$2)) -> 0 | AA80: =SUM(OFFSET($P80,0,0,1,$A$2)) -> 0 | AB80: =SUM(OFFSET($S80,0,0,1,$A$2)) -> 150
B81: 15 | C81: Cement - Hybrid | D81: ACL | E81: Group | F81: A-1 | G81: 125 | H81: Group | I81: Plan | J81: ='KH Solar Plan'!AF31 -> 0 | K81: ='KH Solar Plan'!AG31 -> 0 | L81: ='KH Solar Plan'!AH31 -> 125 | M81: ='KH Solar Plan'!AI31 -> 0 | N81: ='KH Solar Plan'!AJ31 -> 0 | O81: ='KH Solar Plan'!AK31 -> 0 | P81: ='KH Solar Plan'!AL31 -> 0 | Q81: ='KH Solar Plan'!AM31 -> 0 | ... U81: ='KH Solar Plan'!AQ31 -> 0 | V81: =SUM(J81:U81) -> 125 | W81: =SUM(OFFSET(J81,0,0,1,$A$1)) -> 125 | Y81: =SUM(OFFSET($J81,0,0,1,$A$2)) -> 125 | Z81: =SUM(OFFSET($M81,0,0,1,$A$2)) -> 0 | AA81: =SUM(OFFSET($P81,0,0,1,$A$2)) -> 0 | AB81: =SUM(OFFSET($S81,0,0,1,$A$2)) -> 0
B82: 15 | C82: Cement - Hybrid | D82: ACL | E82: Group | F82: A-1 | H82: Group | I82: Rephase | J82: ='KH Solar Rephase'!AE22 -> 0 | K82: ='KH Solar Rephase'!AF22 -> 0 | L82: ='KH Solar Rephase'!AG22 -> 0 | M82: ='KH Solar Rephase'!AH22 -> 0 | N82: ='KH Solar Rephase'!AI22 -> 75 | O82: ='KH Solar Rephase'!AJ22 -> 0 | P82: ='KH Solar Rephase'!AK22 -> 50 | Q82: ='KH Solar Rephase'!AL22 -> 0 | ... U82: ='KH Solar Rephase'!AP22 -> 0 | V82: =SUM(J82:U82) -> 125 | W82: =SUM(OFFSET(J82,0,0,1,$A$1)) -> 125 | Y82: =SUM(OFFSET($J82,0,0,1,$A$2)) -> 0 | Z82: =SUM(OFFSET($M82,0,0,1,$A$2)) -> 75 | AA82: =SUM(OFFSET($P82,0,0,1,$A$2)) -> 50 | AB82: =SUM(OFFSET($S82,0,0,1,$A$2)) -> 0
B83: 15 | C83: Cement - Hybrid | D83: ACL | E83: Group | F83: A-1 | H83: Group | I83: Actual / Fcst | J83: ='KH Solar Actual'!O21 -> 0 | K83: ='KH Solar Actual'!P21 -> 0 | L83: ='KH Solar Actual'!Q21 -> 0 | M83: ='KH Solar Actual'!R21 -> 0 | N83: ='KH Solar Actual'!S21 -> 0 | O83: ='KH Solar Actual'!T21 -> 50 | P83: ='KH Solar Actual'!U21 -> 0 | Q83: ='KH Solar Actual'!V21 -> 0 | ... U83: ='KH Solar Actual'!Z21 -> 0 | V83: =SUM(J83:U83) -> 125 | W83: =SUM(OFFSET(J83,0,0,1,$A$1)) -> 50 | Y83: =SUM(OFFSET($J83,0,0,1,$A$2)) -> 0 | Z83: =SUM(OFFSET($M83,0,0,1,$A$2)) -> 50 | AA83: =SUM(OFFSET($P83,0,0,1,$A$2)) -> 75 | AB83: =SUM(OFFSET($S83,0,0,1,$A$2)) -> 0
B84: 16 | C84: MLP T3 AP | D84: AGE25CL | E84: PPA | F84: A-6 | G84: 75 | H84: PPA | I84: Plan | J84: ='KH Solar Plan'!AF32 -> 0 | K84: ='KH Solar Plan'!AG32 -> 0 | L84: ='KH Solar Plan'!AH32 -> 0 | M84: ='KH Solar Plan'!AI32 -> 0 | N84: ='KH Solar Plan'!AJ32 -> 0 | O84: ='KH Solar Plan'!AK32 -> 0 | P84: ='KH Solar Plan'!AL32 -> 0 | Q84: ='KH Solar Plan'!AM32 -> 75 | ... U84: ='KH Solar Plan'!AQ32 -> 0 | V84: =SUM(J84:U84) -> 75 | W84: =SUM(OFFSET(J84,0,0,1,$A$1)) -> 75 | Y84: =SUM(OFFSET($J84,0,0,1,$A$2)) -> 0 | Z84: =SUM(OFFSET($M84,0,0,1,$A$2)) -> 0 | AA84: =SUM(OFFSET($P84,0,0,1,$A$2)) -> 75 | AB84: =SUM(OFFSET($S84,0,0,1,$A$2)) -> 0
B85: 16 | C85: MLP T3 AP | D85: AGE25CL | E85: PPA | F85: A-6 | H85: PPA | I85: Rephase | J85: ='KH Solar Rephase'!AE23 -> 0 | K85: ='KH Solar Rephase'!AF23 -> 0 | L85: ='KH Solar Rephase'!AG23 -> 0 | M85: ='KH Solar Rephase'!AH23 -> 0 | N85: ='KH Solar Rephase'!AI23 -> 75 | O85: ='KH Solar Rephase'!AJ23 -> 0 | P85: ='KH Solar Rephase'!AK23 -> 0 | Q85: ='KH Solar Rephase'!AL23 -> 0 | ... U85: ='KH Solar Rephase'!AP23 -> 0 | V85: =SUM(J85:U85) -> 75 | W85: =SUM(OFFSET(J85,0,0,1,$A$1)) -> 75 | Y85: =SUM(OFFSET($J85,0,0,1,$A$2)) -> 0 | Z85: =SUM(OFFSET($M85,0,0,1,$A$2)) -> 75 | AA85: =SUM(OFFSET($P85,0,0,1,$A$2)) -> 0 | AB85: =SUM(OFFSET($S85,0,0,1,$A$2)) -> 0
B86: 16 | C86: MLP T3 AP | D86: AGE25CL | E86: PPA | F86: A-6 | H86: PPA | I86: Actual / Fcst | J86: ='KH Solar Actual'!O22 -> 0 | K86: ='KH Solar Actual'!P22 -> 0 | L86: ='KH Solar Actual'!Q22 -> 0 | M86: ='KH Solar Actual'!R22 -> 0 | N86: ='KH Solar Actual'!S22 -> 0 | O86: ='KH Solar Actual'!T22 -> 0 | P86: ='KH Solar Actual'!U22 -> 0 | Q86: ='KH Solar Actual'!V22 -> 0 | ... U86: ='KH Solar Actual'!Z22 -> 0 | V86: =SUM(J86:U86) -> 75 | W86: =SUM(OFFSET(J86,0,0,1,$A$1)) -> 0 | Y86: =SUM(OFFSET($J86,0,0,1,$A$2)) -> 0 | Z86: =SUM(OFFSET($M86,0,0,1,$A$2)) -> 0 | AA86: =SUM(OFFSET($P86,0,0,1,$A$2)) -> 75 | AB86: =SUM(OFFSET($S86,0,0,1,$A$2)) -> 0
B87: 17 | C87: MLP T1 J&K | D87: AGE26AL | E87: PPA | F87: A-16 | G87: 50 | H87: PPA | I87: Plan | J87: ='KH Solar Plan'!AF33 -> 0 | K87: ='KH Solar Plan'!AG33 -> 0 | L87: ='KH Solar Plan'!AH33 -> 0 | M87: ='KH Solar Plan'!AI33 -> 0 | N87: ='KH Solar Plan'!AJ33 -> 0 | O87: ='KH Solar Plan'!AK33 -> 50 | P87: ='KH Solar Plan'!AL33 -> 0 | Q87: ='KH Solar Plan'!AM33 -> 0 | ... U87: ='KH Solar Plan'!AQ33 -> 0 | V87: =SUM(J87:U87) -> 50 | W87: =SUM(OFFSET(J87,0,0,1,$A$1)) -> 50 | Y87: =SUM(OFFSET($J87,0,0,1,$A$2)) -> 0 | Z87: =SUM(OFFSET($M87,0,0,1,$A$2)) -> 50 | AA87: =SUM(OFFSET($P87,0,0,1,$A$2)) -> 0 | AB87: =SUM(OFFSET($S87,0,0,1,$A$2)) -> 0
B88: 17 | C88: MLP T1 J&K | D88: AGE26AL | E88: PPA | F88: A-16 | H88: PPA | I88: Rephase | J88: ='KH Solar Rephase'!AE24 -> 0 | K88: ='KH Solar Rephase'!AF24 -> 0 | L88: ='KH Solar Rephase'!AG24 -> 0 | M88: ='KH Solar Rephase'!AH24 -> 0 | N88: ='KH Solar Rephase'!AI24 -> 0 | O88: ='KH Solar Rephase'!AJ24 -> 0 | P88: ='KH Solar Rephase'!AK24 -> 0 | Q88: ='KH Solar Rephase'!AL24 -> 0 | ... U88: ='KH Solar Rephase'!AP24 -> 0 | V88: =SUM(J88:U88) -> 50 | W88: =SUM(OFFSET(J88,0,0,1,$A$1)) -> 0 | Y88: =SUM(OFFSET($J88,0,0,1,$A$2)) -> 0 | Z88: =SUM(OFFSET($M88,0,0,1,$A$2)) -> 0 | AA88: =SUM(OFFSET($P88,0,0,1,$A$2)) -> 50 | AB88: =SUM(OFFSET($S88,0,0,1,$A$2)) -> 0
B89: 17 | C89: MLP T1 J&K | D89: AGE26AL | E89: PPA | F89: A-16 | H89: PPA | I89: Actual / Fcst | J89: ='KH Solar Actual'!O23 -> 0 | K89: ='KH Solar Actual'!P23 -> 0 | L89: ='KH Solar Actual'!Q23 -> 0 | M89: ='KH Solar Actual'!R23 -> 0 | N89: ='KH Solar Actual'!S23 -> 0 | O89: ='KH Solar Actual'!T23 -> 0 | P89: ='KH Solar Actual'!U23 -> 0 | Q89: ='KH Solar Actual'!V23 -> 0 | ... U89: ='KH Solar Actual'!Z23 -> 0 | V89: =SUM(J89:U89) -> 50 | W89: =SUM(OFFSET(J89,0,0,1,$A$1)) -> 0 | Y89: =SUM(OFFSET($J89,0,0,1,$A$2)) -> 0 | Z89: =SUM(OFFSET($M89,0,0,1,$A$2)) -> 0 | AA89: =SUM(OFFSET($P89,0,0,1,$A$2)) -> 0 | AB89: =SUM(OFFSET($S89,0,0,1,$A$2)) -> 50
B90: 18 | C90: MLP T1 CG | D90: AGE26AL | E90: PPA | F90: A-16 | G90: 200 | H90: PPA | I90: Plan | J90: ='KH Solar Plan'!AF34 -> 0 | K90: ='KH Solar Plan'!AG34 -> 0 | L90: ='KH Solar Plan'!AH34 -> 0 | M90: ='KH Solar Plan'!AI34 -> 0 | N90: ='KH Solar Plan'!AJ34 -> 0 | O90: ='KH Solar Plan'!AK34 -> 0 | P90: ='KH Solar Plan'!AL34 -> 200 | Q90: ='KH Solar Plan'!AM34 -> 0 | ... U90: ='KH Solar Plan'!AQ34 -> 0 | V90: =SUM(J90:U90) -> 200 | W90: =SUM(OFFSET(J90,0,0,1,$A$1)) -> 200 | Y90: =SUM(OFFSET($J90,0,0,1,$A$2)) -> 0 | Z90: =SUM(OFFSET($M90,0,0,1,$A$2)) -> 0 | AA90: =SUM(OFFSET($P90,0,0,1,$A$2)) -> 200 | AB90: =SUM(OFFSET($S90,0,0,1,$A$2)) -> 0
B91: 18 | C91: MLP T1 CG | D91: AGE26AL | E91: PPA | F91: A-16 | H91: PPA | I91: Rephase | J91: ='KH Solar Rephase'!AE25 -> 0 | K91: ='KH Solar Rephase'!AF25 -> 0 | L91: ='KH Solar Rephase'!AG25 -> 0 | M91: ='KH Solar Rephase'!AH25 -> 0 | N91: ='KH Solar Rephase'!AI25 -> 0 | O91: ='KH Solar Rephase'!AJ25 -> 0 | P91: ='KH Solar Rephase'!AK25 -> 0 | Q91: ='KH Solar Rephase'!AL25 -> 0 | ... U91: ='KH Solar Rephase'!AP25 -> 0 | V91: =SUM(J91:U91) -> 200 | W91: =SUM(OFFSET(J91,0,0,1,$A$1)) -> 0 | Y91: =SUM(OFFSET($J91,0,0,1,$A$2)) -> 0 | Z91: =SUM(OFFSET($M91,0,0,1,$A$2)) -> 0 | AA91: =SUM(OFFSET($P91,0,0,1,$A$2)) -> 50 | AB91: =SUM(OFFSET($S91,0,0,1,$A$2)) -> 150
B92: 18 | C92: MLP T1 CG | D92: AGE26AL | E92: PPA | F92: A-16 | H92: PPA | I92: Actual / Fcst | J92: ='KH Solar Actual'!O24 -> 0 | K92: ='KH Solar Actual'!P24 -> 0 | L92: ='KH Solar Actual'!Q24 -> 0 | M92: ='KH Solar Actual'!R24 -> 0 | N92: ='KH Solar Actual'!S24 -> 0 | O92: ='KH Solar Actual'!T24 -> 0 | P92: ='KH Solar Actual'!U24 -> 0 | Q92: ='KH Solar Actual'!V24 -> 0 | ... U92: ='KH Solar Actual'!Z24 -> 0 | V92: =SUM(J92:U92) -> 200 | W92: =SUM(OFFSET(J92,0,0,1,$A$1)) -> 0 | Y92: =SUM(OFFSET($J92,0,0,1,$A$2)) -> 0 | Z92: =SUM(OFFSET($M92,0,0,1,$A$2)) -> 0 | AA92: =SUM(OFFSET($P92,0,0,1,$A$2)) -> 0 | AB92: =SUM(OFFSET($S92,0,0,1,$A$2)) -> 200
B93: 19 | C93: MLP T1 TN | D93: AGE26AL | E93: PPA | F93: A-16 | G93: 167 | H93: PPA | I93: Plan | J93: ='KH Solar Plan'!AF35 -> 0 | K93: ='KH Solar Plan'!AG35 -> 0 | L93: ='KH Solar Plan'!AH35 -> 0 | M93: ='KH Solar Plan'!AI35 -> 0 | N93: ='KH Solar Plan'!AJ35 -> 0 | O93: ='KH Solar Plan'!AK35 -> 0 | P93: ='KH Solar Plan'!AL35 -> 167 | Q93: ='KH Solar Plan'!AM35 -> 0 | ... U93: ='KH Solar Plan'!AQ35 -> 0 | V93: =SUM(J93:U93) -> 167 | W93: =SUM(OFFSET(J93,0,0,1,$A$1)) -> 167 | Y93: =SUM(OFFSET($J93,0,0,1,$A$2)) -> 0 | Z93: =SUM(OFFSET($M93,0,0,1,$A$2)) -> 0 | AA93: =SUM(OFFSET($P93,0,0,1,$A$2)) -> 167 | AB93: =SUM(OFFSET($S93,0,0,1,$A$2)) -> 0
B94: 19 | C94: MLP T1 TN | D94: AGE26AL | E94: PPA | F94: A-16 | H94: PPA | I94: Rephase | J94: ='KH Solar Rephase'!AE26 -> 0 | K94: ='KH Solar Rephase'!AF26 -> 0 | L94: ='KH Solar Rephase'!AG26 -> 0 | M94: ='KH Solar Rephase'!AH26 -> 0 | N94: ='KH Solar Rephase'!AI26 -> 0 | O94: ='KH Solar Rephase'!AJ26 -> 0 | P94: ='KH Solar Rephase'!AK26 -> 0 | Q94: ='KH Solar Rephase'!AL26 -> 0 | ... U94: ='KH Solar Rephase'!AP26 -> 0 | V94: =SUM(J94:U94) -> 167 | W94: =SUM(OFFSET(J94,0,0,1,$A$1)) -> 0 | Y94: =SUM(OFFSET($J94,0,0,1,$A$2)) -> 0 | Z94: =SUM(OFFSET($M94,0,0,1,$A$2)) -> 0 | AA94: =SUM(OFFSET($P94,0,0,1,$A$2)) -> 50 | AB94: =SUM(OFFSET($S94,0,0,1,$A$2)) -> 117
B95: 19 | C95: MLP T1 TN | D95: AGE26AL | E95: PPA | F95: A-16 | H95: PPA | I95: Actual / Fcst | J95: ='KH Solar Actual'!O25 -> 0 | K95: ='KH Solar Actual'!P25 -> 0 | L95: ='KH Solar Actual'!Q25 -> 0 | M95: ='KH Solar Actual'!R25 -> 0 | N95: ='KH Solar Actual'!S25 -> 0 | O95: ='KH Solar Actual'!T25 -> 0 | P95: ='KH Solar Actual'!U25 -> 0 | Q95: ='KH Solar Actual'!V25 -> 0 | ... U95: ='KH Solar Actual'!Z25 -> 0 | V95: =SUM(J95:U95) -> 167 | W95: =SUM(OFFSET(J95,0,0,1,$A$1)) -> 0 | Y95: =SUM(OFFSET($J95,0,0,1,$A$2)) -> 0 | Z95: =SUM(OFFSET($M95,0,0,1,$A$2)) -> 0 | AA95: =SUM(OFFSET($P95,0,0,1,$A$2)) -> 0 | AB95: =SUM(OFFSET($S95,0,0,1,$A$2)) -> 167
B96: 20 | C96: MLP T1 OR | D96: AGE26AL | E96: PPA | F96: A-16 | G96: 333 | H96: PPA | I96: Plan | J96: ='KH Solar Plan'!AF36 -> 0 | K96: ='KH Solar Plan'!AG36 -> 0 | L96: ='KH Solar Plan'!AH36 -> 0 | M96: ='KH Solar Plan'!AI36 -> 0 | N96: ='KH Solar Plan'!AJ36 -> 0 | O96: ='KH Solar Plan'!AK36 -> 333 | P96: ='KH Solar Plan'!AL36 -> 0 | Q96: ='KH Solar Plan'!AM36 -> 0 | ... U96: ='KH Solar Plan'!AQ36 -> 0 | V96: =SUM(J96:U96) -> 333 | W96: =SUM(OFFSET(J96,0,0,1,$A$1)) -> 333 | Y96: =SUM(OFFSET($J96,0,0,1,$A$2)) -> 0 | Z96: =SUM(OFFSET($M96,0,0,1,$A$2)) -> 333 | AA96: =SUM(OFFSET($P96,0,0,1,$A$2)) -> 0 | AB96: =SUM(OFFSET($S96,0,0,1,$A$2)) -> 0
B97: 20 | C97: MLP T1 OR | D97: AGE26AL | E97: PPA | F97: A-16 | H97: PPA | I97: Rephase | J97: ='KH Solar Rephase'!AE27 -> 0 | K97: ='KH Solar Rephase'!AF27 -> 0 | L97: ='KH Solar Rephase'!AG27 -> 0 | M97: ='KH Solar Rephase'!AH27 -> 0 | N97: ='KH Solar Rephase'!AI27 -> 0 | O97: ='KH Solar Rephase'!AJ27 -> 0 | P97: ='KH Solar Rephase'!AK27 -> 0 | Q97: ='KH Solar Rephase'!AL27 -> 0 | ... U97: ='KH Solar Rephase'!AP27 -> 133 | V97: =SUM(J97:U97) -> 333 | W97: =SUM(OFFSET(J97,0,0,1,$A$1)) -> 0 | Y97: =SUM(OFFSET($J97,0,0,1,$A$2)) -> 0 | Z97: =SUM(OFFSET($M97,0,0,1,$A$2)) -> 0 | AA97: =SUM(OFFSET($P97,0,0,1,$A$2)) -> 0 | AB97: =SUM(OFFSET($S97,0,0,1,$A$2)) -> 333
B98: 20 | C98: MLP T1 OR | D98: AGE26AL | E98: PPA | F98: A-16 | H98: PPA | I98: Actual / Fcst | J98: ='KH Solar Actual'!O26 -> 0 | K98: ='KH Solar Actual'!P26 -> 0 | L98: ='KH Solar Actual'!Q26 -> 0 | M98: ='KH Solar Actual'!R26 -> 0 | N98: ='KH Solar Actual'!S26 -> 0 | O98: ='KH Solar Actual'!T26 -> 0 | P98: ='KH Solar Actual'!U26 -> 0 | Q98: ='KH Solar Actual'!V26 -> 0 | ... U98: ='KH Solar Actual'!Z26 -> 0 | V98: =SUM(J98:U98) -> 333 | W98: =SUM(OFFSET(J98,0,0,1,$A$1)) -> 0 | Y98: =SUM(OFFSET($J98,0,0,1,$A$2)) -> 0 | Z98: =SUM(OFFSET($M98,0,0,1,$A$2)) -> 0 | AA98: =SUM(OFFSET($P98,0,0,1,$A$2)) -> 0 | AB98: =SUM(OFFSET($S98,0,0,1,$A$2)) -> 333
B99: 21 | C99: MLP T1 TR | D99: AGE26AL | E99: PPA | F99: A10a | G99: 50 | H99: PPA | I99: Plan | J99: ='KH Solar Plan'!AF37 -> 0 | K99: ='KH Solar Plan'!AG37 -> 0 | L99: ='KH Solar Plan'!AH37 -> 0 | M99: ='KH Solar Plan'!AI37 -> 0 | N99: ='KH Solar Plan'!AJ37 -> 0 | O99: ='KH Solar Plan'!AK37 -> 50 | P99: ='KH Solar Plan'!AL37 -> 0 | Q99: ='KH Solar Plan'!AM37 -> 0 | ... U99: ='KH Solar Plan'!AQ37 -> 0 | V99: =SUM(J99:U99) -> 50 | W99: =SUM(OFFSET(J99,0,0,1,$A$1)) -> 50 | Y99: =SUM(OFFSET($J99,0,0,1,$A$2)) -> 0 | Z99: =SUM(OFFSET($M99,0,0,1,$A$2)) -> 50 | AA99: =SUM(OFFSET($P99,0,0,1,$A$2)) -> 0 | AB99: =SUM(OFFSET($S99,0,0,1,$A$2)) -> 0
B100: 21 | C100: MLP T1 TR | D100: AGE26AL | E100: PPA | F100: A10a | H100: PPA | I100: Rephase | J100: ='KH Solar Rephase'!AE28 -> 0 | K100: ='KH Solar Rephase'!AF28 -> 0 | L100: ='KH Solar Rephase'!AG28 -> 0 | M100: ='KH Solar Rephase'!AH28 -> 0 | N100: ='KH Solar Rephase'!AI28 -> 0 | O100: ='KH Solar Rephase'!AJ28 -> 50 | P100: ='KH Solar Rephase'!AK28 -> 0 | Q100: ='KH Solar Rephase'!AL28 -> 0 | ... U100: ='KH Solar Rephase'!AP28 -> 0 | V100: =SUM(J100:U100) -> 50 | W100: =SUM(OFFSET(J100,0,0,1,$A$1)) -> 50 | Y100: =SUM(OFFSET($J100,0,0,1,$A$2)) -> 0 | Z100: =SUM(OFFSET($M100,0,0,1,$A$2)) -> 50 | AA100: =SUM(OFFSET($P100,0,0,1,$A$2)) -> 0 | AB100: =SUM(OFFSET($S100,0,0,1,$A$2)) -> 0
B101: 21 | C101: MLP T1 TR | D101: AGE26AL | E101: PPA | F101: A10a | H101: PPA | I101: Actual / Fcst | J101: ='KH Solar Actual'!O27 -> 0 | K101: ='KH Solar Actual'!P27 -> 0 | L101: ='KH Solar Actual'!Q27 -> 0 | M101: ='KH Solar Actual'!R27 -> 0 | N101: ='KH Solar Actual'!S27 -> 0 | O101: ='KH Solar Actual'!T27 -> 0 | P101: ='KH Solar Actual'!U27 -> 50 | Q101: ='KH Solar Actual'!V27 -> 0 | ... U101: ='KH Solar Actual'!Z27 -> 0 | V101: =SUM(J101:U101) -> 50 | W101: =SUM(OFFSET(J101,0,0,1,$A$1)) -> 50 | Y101: =SUM(OFFSET($J101,0,0,1,$A$2)) -> 0 | Z101: =SUM(OFFSET($M101,0,0,1,$A$2)) -> 0 | AA101: =SUM(OFFSET($P101,0,0,1,$A$2)) -> 50 | AB101: =SUM(OFFSET($S101,0,0,1,$A$2)) -> 0
B102: 22 | C102: MLP T3 AP | D102: AGE25CL | E102: PPA | F102: A-6 | G102: 425 | H102: PPA | I102: Plan | J102: ='KH Solar Plan'!AF38 -> 0 | K102: ='KH Solar Plan'!AG38 -> 0 | L102: ='KH Solar Plan'!AH38 -> 0 | M102: ='KH Solar Plan'!AI38 -> 0 | N102: ='KH Solar Plan'!AJ38 -> 0 | O102: ='KH Solar Plan'!AK38 -> 0 | P102: ='KH Solar Plan'!AL38 -> 0 | Q102: ='KH Solar Plan'!AM38 -> 0 | ... U102: ='KH Solar Plan'!AQ38 -> 0 | V102: =SUM(J102:U102) -> 425 | W102: =SUM(OFFSET(J102,0,0,1,$A$1)) -> 0 | Y102: =SUM(OFFSET($J102,0,0,1,$A$2)) -> 0 | Z102: =SUM(OFFSET($M102,0,0,1,$A$2)) -> 0 | AA102: =SUM(OFFSET($P102,0,0,1,$A$2)) -> 425 | AB102: =SUM(OFFSET($S102,0,0,1,$A$2)) -> 0
...

Sheet KH Wind Actual
I1: Out of 57.2 MW (11 WTGs), 7 WTG TR Done in Nov-25, but COD in Dec-25
H2: Forecast | I2: Actual
A3: FY 2025-26 | Khavda Wind Projects Monthly Commissioning Plan (MWac) | R3: Date: 30-Dec-25
A4: Sl. | B4: Project | C4: SPV | D4: Category | E4: Capacity (MW) | F4: WTG Nos. | G4: PSS No. | H4: 45748 | I4: 45778 | J4: 45809 | K4: 45839 | L4: 45870 | M4: 45901 | N4: 45931 | O4: 45962 | P4: 45992 | Q4: 46023 | R4: 46054 | S4: 46082
A5: 1 | B5: AGEL Merchant (Wind) | C5: AGE24L | D5: Merchant | E5: =SUM(H5:S5) -> 52 | F5: =E5/5.2 -> 10 | G5: PSS-04 | H5: =10*5.2 -> 52
A6: 2 | B6: Hybrid Cement (Wind) | C6: ACL | D6: Group | E6: =SUM(H6:S6) -> 57.2 | F6: =E6/5.2 -> 11 | G6: PSS-04 | I6: 26 | J6: =6*5.2 -> 31.2
A7: 3 | B7: AGEL Merchant (Wind) | C7: AHEJ5L | D7: Merchant | E7: =SUM(H7:S7) -> 62.4 | F7: =E7/5.2 -> 12 | G7: PSS-04 | H7: =10*5.2 -> 52 | J7: =2*5.2 -> 10.4
A8: 4 | B8: AGEL Hybrid Merchant (Wind) | C8: AGE26BL | D8: Merchant | E8: =SUM(H8:S8) -> 156 | F8: =E8/5.2 -> 30 | G8: PSS-10 | J8: =23*5.2 -> 119.6 | K8: =5*5.2 -> 26 | R8: =2*5.2 -> 10.4
A9: 5 | B9: AGEL Merchant (Wind) | C9: AHEJ5L | D9: Merchant | E9: =SUM(H9:S9) -> 67.6 | F9: =E9/5.2 -> 13 | G9: PSS-08 | M9: =6*5.2 -> 31.2 | O9: =6*5.2 -> 31.2 | Q9: =1*5.2 -> 5.2
A10: 6 | B10: AGEL Merchant (Wind) | C10: ARE41L | D10: Merchant | E10: =SUM(H10:S10) -> 130 | F10: =E10/5.2 -> 25 | G10: PSS-08 | L10: =24*5.2 -> 124.8 | O10: =1*5.2 -> 5.2
A11: 7 | B11: Google Hybrid (Wind) | C11: ARE3L | D11: Merchant | E11: =SUM(H11:S11) -> 15.6 | F11: =E11/5.2 -> 3 | G11: PSS-08 | K11: =3*5.2 -> 15.6
A12: 8 | B12: Google Hybrid (Wind) | C12: ARE3L | D12: Merchant | E12: =SUM(H12:S12) -> 26 | F12: =E12/5.2 -> 5 | G12: PSS-08 | K12: =5*5.2 -> 26
A13: 9 | B13: AGEL Hybrid Merchant (Wind) | C13: ASEJ6PL | D13: Merchant | E13: =SUM(H13:S13) -> 62.4 | F13: =E13/5.2 -> 12 | G13: PSS-08 | Q13: =6*5.2 -> 31.2 | R13: =4*5.2 -> 20.8 | S13: =2*5.2 -> 10.4
A14: 10 | B14: SECI H-3 (Wind) | C14: AHEJ5L | D14: PPA | E14: =SUM(H14:S14) -> 202.8 | F14: =E14/5.2 -> 39 | G14: PSS-05 | N14: =15*5.2 -> 78 | O14: =9*5.2 -> 46.8 | P14: =4*5.2+7*5.2 -> 57.2 | S14: =4*5.2 -> 20.8
A15: 11a | B15: AGEL Merchant (Wind) | C15: AGE25CL | D15: Merchant | E15: =SUM(H15:S15) -> 156 | F15: =E15/5.2 -> 30 | G15: PSS-11 | Q15: =15*5.2 -> 78 | R15: =12*5.2 -> 62.4 | S15: =3*5.2 -> 15.6
A16: 12a | B16: AGEL Merchant (Wind) | C16: AGE26AL | D16: Merchant | E16: =SUM(H16:S16) -> 140.4 | F16: =E16/5.2 -> 27 | G16: PSS-12 | R16: =15*5.2 -> 78 | S16: =12*5.2 -> 62.4
B17: Total - MW | E17: =SUM(E5:E16) -> 1128.4 | H17: =SUM(H5:H16) -> 104 | I17: =SUM(I5:I16) -> 26 | J17: =SUM(J5:J16) -> 161.2 | K17: =SUM(K5:K16) -> 67.6 | L17: =SUM(L5:L16) -> 124.8 | M17: =SUM(M5:M16) -> 31.2 | N17: =SUM(N5:N16) -> 78 | O17: =SUM(O5:O16) -> 83.2 | ... S17: =SUM(S5:S16) -> 109.2
H18: =+SUM(H17:J17) -> 291.2 | K18: =+SUM(K17:M17) -> 223.6 | N18: =+SUM(N17:P17) -> 218.4 | Q18: =+SUM(Q17:S17) -> 395.2
B19: Total - WTG | F19: =SUM(F5:F16) -> 217 | H19: =+H17/5.2 -> 20 | I19: =+I17/5.2 -> 5 | J19: =+J17/5.2 -> 31 | K19: =+K17/5.2 -> 13 | L19: =+L17/5.2 -> 24 | M19: =+M17/5.2 -> 6 | N19: =+N17/5.2 -> 15 | O19: =+O17/5.2 -> 16 | ... S19: =+S17/5.2 -> 21
H20: =+SUM(H19:J19) -> 56 | K20: =+SUM(K19:M19) -> 43 | N20: =+SUM(N19:P19) -> 42 | Q20: =+SUM(Q19:S19) -> 76
A22: Additional for internal
A23: 11b | B23: AGEL Merchant (Wind) | C23: AGE25CL | D23: Merchant | E23: =SUM(H23:S23) -> 98.8 | F23: =E23/5.2 -> 19 | H23: =SUM(H24:H25) -> 0 | I23: =SUM(I24:I25) -> 0 | J23: =SUM(J24:J25) -> 0 | K23: =SUM(K24:K25) -> 0 | L23: =SUM(L24:L25) -> 0 | M23: =SUM(M24:M25) -> 0 | N23: =SUM(N24:N25) -> 0 | O23: =SUM(O24:O25) -> 0 | ... S23: =SUM(S24:S25) -> 72.8
E24: =SUM(H24:S24) -> 31.2 | F24: =E24/5.2 -> 6 | G24: PSS-11 | Q24: =2*5.2 -> 10.4 | R24: =3*5.2 -> 15.6 | S24: =1*5.2 -> 5.2
E25: =SUM(H25:S25) -> 67.6 | F25: =E25/5.2 -> 13 | G25: PSS-14 | S25: =13*5.2 -> 67.6
A26: 12b | B26: AGEL Merchant (Wind) | C26: AGE26AL | D26: Merchant | E26: =SUM(H26:S26) -> 312 | F26: =E26/5.2 -> 60 | G26: PSS-14 | Q26: =7*5.2 -> 36.4 | R26: =26*5.2 -> 135.2 | S26: =27*5.2 -> 140.4
A27: 13 | B27: AGEL Merchant | C27: AGE25BL | D27: Merchant | E27: =SUM(H27:S27) -> 10.4 | F27: =E27/5.2 -> 2 | G27: PSS-09 | Q27: =2*5.2 -> 10.4
B28: Total (for Internal) | E28: =SUM(E23:E27) -> 520 | F28: =SUM(F24:F27) -> 81 | H28: =SUM(H24:H27) -> 0 | I28: =SUM(I24:I27) -> 0 | J28: =SUM(J24:J27) -> 0 | K28: =SUM(K24:K27) -> 0 | L28: =SUM(L24:L27) -> 0 | M28: =SUM(M24:M27) -> 0 | N28: =SUM(N24:N27) -> 0 | O28: =SUM(O24:O27) -> 0 | ... S28: =SUM(S24:S27) -> 213.2
B30: Total - MW | E30: =+E28+E17 -> 1648.4 | F30: =+F28+F17 -> 81 | G30: =+G28+G17 -> 0 | H30: =+H28+H17 -> 104 | I30: =+I28+I17 -> 26 | J30: =+J28+J17 -> 161.2 | K30: =+K28+K17 -> 67.6 | L30: =+L28+L17 -> 124.8 | ... S30: =+S28+S17 -> 322.4
I32: Mwac | J32: WTG
H33: Budget Plan | I33: 1128 | J33: 217
H34: Internal Plan | I34: 1549.6 | J34: =I34/5.2 -> 298
H35: Actual YTD Dec-25 | I35: =J35*5.2 -> 733.2 | J35: 141
H36: Balance Budget | I36: =I33-I35 -> 394.8 | J36: =J33-J35 -> 76
H37: Balance Internal | I37: =I34-I35 -> 816.4 | J37: =J34-J35 -> 157

Sheet KH Solar Actual
A2: Phase-III: Khavda Solar Projects Monthly COD Actuals & Forecast (MWac) | Q2: TR Done in Nov-25 but COD in Dec-25 | Y2: 46021 | AB2: In addition to COD | AF2: Physical Progress Status till 27/28-Dec | AK2: Manpower as per DPR
A3: Priority | B3: Project | C3: SPV | D3: Plot No | E3: Category | F3: Category | G3: MMS Type | H3: Module Source | I3: Capacity (MWac) | J3: OL | K3: Capacity (MWdc) | L3: PSS No. | M3: PSS Charging Date | N3: SCOD | O3: 45748 | P3: 45778 | Q3: 45809 | R3: 45839 | S3: 45870 | T3: 45901 | U3: 45931 | V3: 45962 | W3: 45992 | X3: 46023 | Y3: 46054 | Z3: 46082 | AB3: Charging | AC3: Trail Run | AD3: Trail Run Certificate | AF3: Piling | AG3: MMS (Purlin) | AH3: Module | AI3: IDT | AK3: Avaliable as of 27/28-Dec | AL3: Required
A4: A. Khavda Solar Projects
A5: 1 | B5: AGEL Merchant | C5: ARE56L | D5: S-08 | E5: Merchant | F5: Merchant | G5: HSAT | H5: ALMM | I5: 250 | J5: 1.37 | K5: =I5*J5 -> 342.5 | L5: PSS-09 | M5: 45612 | P5: 75 | Q5: 50 | S5: 125 | T5: 0 | AB5: 0 | AC5: 0 | AD5: 0 | AF5: Completed | AG5: Completed | AH5: Completed | AI5: Completed
A6: 2 | B6: AGEL Merchant | C6: ARE56L | D6: A-02 | E6: Merchant | F6: Merchant | G6: HSAT | H6: ALMM | I6: 50 | J6: 1.37 | K6: =I6*J6 -> 68.5 | L6: PSS-04 | M6: 45714 | P6: 50 | Q6: 0 | R6: 0 | S6: 0 | T6: 0 | AB6: 0 | AC6: 0 | AD6: 0 | AF6: Completed | AG6: Completed | AH6: Completed | AI6: Completed
A7: 3 | B7: MLP AP New | C7: ARE57L | D7: A-11 | E7: PPA | F7: PPA | G7: HSAT | H7: China | I7: 187.5 | J7: 1.36 | K7: =I7*J7 -> 255 | L7: PSS-13 | M7: 45708 | N7: 15-Jun-29 (LTA +15D) | O7: 75 | P7: 112.5 | Q7: 0 | R7: 0 | S7: 0 | T7: 0 | AB7: 0 | AC7: 0 | AD7: 0 | AF7: Completed | AG7: Completed | AH7: Completed | AI7: Completed
A8: 4 | B8: MLP AP New | C8: ARE57L | D8: A-12 | E8: PPA | F8: PPA | G8: HSAT | H8: China | I8: 350 | J8: 1.35 | K8: =I8*J8 -> 472.5 | L8: PSS-13 | M8: 45708 | N8: 15-Jun-29 (LTA +15D) | P8: 50 | Q8: 175 | V8: 125 | AF8: Completed | AG8: Completed | AH8: Completed | AI8: Completed | AK8: 0 | AL8: =+AK8 -> 0
A9: 5 | B9: SECI H-3 | C9: AHEJ5L | D9: A-13 | E9: PPA | F9: PPA | G9: FT | H9: China | I9: 570 | J9: 1.4 | K9: =I9*J9 -> 798 | L9: PSS-05 | M9: 45721 | N9: 31-Dec-25 (LTA) | O9: 145 | Q9: 150 | S9: 50 | T9: 75 | U9: 75 | W9: 75 | AF9: Completed | AG9: Completed | AH9: Completed | AI9: Completed | AK9: 7 | AL9: =+AK9 -> 7
A10: 6 | B10: AGEL Merchant | C10: ARE45L | D10: A-14 | E10: Merchant | F10: Merchant | G10: HSAT | H10: ALMM | I10: 250 | J10: 1.37 | K10: =I10*J10 -> 342.5 | L10: PSS-05 | M10: 45721 | O10: 50 | Q10: 125 | T10: 75 | U10: 0 | AF10: Completed | AG10: Completed | AH10: Completed | AI10: Completed
A11: 7 | B11: MLP T3 AP | C11: ARE56L | D11: S-06 | E11: PPA | F11: PPA | G11: HSAT | H11: China | I11: 500 | J11: 1.37 | K11: =I11*J11 -> 685 | L11: PSS-10 | M11: 45741 | N11: 45990 | O11: 100 | Q11: 137.5 | S11: 87.5 | T11: 100 | V11: 75 | AF11: Completed | AG11: Completed | AH11: Completed | AI11: Completed | AK11: 0 | AL11: =+AK11 -> 0
A12: P-01 | B12: Google Hybrid | C12: ARE3L | D12: A-6 | E12: Merchant-Google | F12: Merchant | G12: HSAT | H12: ALMM | I12: 25 | J12: 1.35 | K12: =J12*I12 -> 33.75 | L12: PSS-08 | M12: 45851 | N12: - | R12: 25 | S12: 0 | T12: 0 | U12: 0 | W12: 0 | AF12: Completed | AG12: Completed | AH12: Completed | AI12: Completed
A13: P-02 | B13: AGEL Merchant | C13: ASEJ6PL | D13: A-6 | E13: Merchant-Hybrid | F13: Merchant | G13: HSAT | H13: ALMM | I13: 35 | J13: 1.35 | K13: =J13*I13 -> 47.25 | L13: PSS-08 | M13: 45851 | N13: - | R13: 35 | S13: 0 | T13: 0 | U13: 0 | W13: 0 | AF13: Completed | AG13: Completed | AH13: Completed | AI13: Completed
A14: P-03 | B14: AGEL Hybrid Merchant | C14: AGE25BL | D14: S-8 | E14: Merchant-Hybrid | F14: Merchant | G14: HSAT | H14: ALMM | I14: 100 | J14: 1.35 | K14: =J14*I14 -> 135 | L14: PSS-09 | M14: 45612 | N14: - | T14: 100 | AF14: Completed | AG14: Completed | AH14: Completed | AI14: Completed
A15: P-04 | B15: AGEL Merchant | C15: AHEJ5L | D15: A-15a | E15: Merchant | F15: Merchant | G15: HSAT | H15: ALMM | I15: 150 | J15: 1.35 | K15: =J15*I15 -> 202.5 | L15: PSS-08 | M15: 45851 | N15: - | T15: 50 | X15: 50 | Y15: 50 | AF15: 0.97 | AG15: 0.817 | AH15: 0.62 | AI15: C:92%; E:83% | AK15: 360 | AL15: 240
A16: P-05 | B16: AGEL Hybrid Merchant | C16: AGE26BL | D16: S-5 | E16: Merchant-Hybrid | F16: Merchant | G16: HSAT | H16: ALMM | I16: =SUM(I17:I18) -> 292 | J16: 1.35 | K16: =J16*I16 -> 394.2 | L16: PSS-10 | M16: 45876 | N16: - | O16: =SUM(O17:O18) -> 0 | P16: =SUM(P17:P18) -> 0 | Q16: =SUM(Q17:Q18) -> 0 | R16: =SUM(R17:R18) -> 0 | S16: =SUM(S17:S18) -> 0 | T16: =SUM(T17:T18) -> 50 | U16: =SUM(U17:U18) -> 0 | V16: =SUM(V17:V18) -> 50 | ... AA16: =SUM(AA17:AA18) -> 0 | AD16: =SUM(AD17:AD18) -> 0 | AF16: 0.994 | AG16: 0.896 | AH16: 0.584 | AI16: C:100%; E:83% | AK16: 358 | AL16: 480
A17: P-05a | B17: AGEL Hybrid Merchant | C17: AGE26BL | D17: S-5 | E17: Merchant-Hybrid | F17: Merchant | G17: HSAT | H17: ALMM | I17: 142 | J17: 1.35 | K17: =J17*I17 -> 191.7 | M17: 45876 | N17: - | T17: 50 | V17: 50 | Y17: 42
A18: P-05b | B18: AGEL Merchant | C18: AGE26BL | D18: S-5 | E18: Merchant-Hybrid | F18: Merchant | G18: HSAT | H18: ALMM | I18: 150 | J18: 1.35 | K18: =J18*I18 -> 202.5 | M18: 45876 | N18: - | W18: 50 | X18: 75 | Y18: 25
A19: P-06 | B19: AGEL Merchant | C19: AGE24L | D19: S-5 | E19: Merchant | F19: Merchant | G19: HSAT | H19: ALMM | I19: 150 | J19: 1.35 | K19: =J19*I19 -> 202.5 | L19: PSS-10 | M19: 45876 | N19: - | X19: 62.5 | Y19: 87.5 | AF19: 0.98 | AG19: 0.817 | AH19: 0.46433553 | AI19: C:100%; E:83% | AK19: 520 | AL19: 380
A20: P-07 | B20: AGEL Merchant | C20: AGE24L | D20: A-14 | E20: Merchant | F20: Merchant | G20: HSAT | H20: ALMM | I20: 150 | J20: 1.35 | K20: =J20*I20 -> 202.5 | L20: PSS-05 | M20: 45721 | N20: - | X20: 75 | Y20: 75 | AF20: 0.95 | AG20: 0.487 | AH20: 0.133 | AI20: C:50%; E:50% | AK20: 412 | AL20: 840
A21: P-08 | B21: Cement - Hybrid | C21: ACL | D21: A-1 | E21: Cement - Hybrid | F21: Group | G21: FT | H21: ALMM | I21: 125 | J21: 1.36 | K21: =J21*I21 -> 170 | L21: PSS-04 | M21: 45714 | N21: - | T21: 50 | W21: 75 | AF21: Completed | AG21: Completed | AH21: Completed | AI21: Completed
A22: P-09 | B22: MLP T3 AP | C22: AGE25CL | D22: A-6 | E22: PPA | F22: PPA | G22: HSAT | H22: China | I22: 75 | J22: 1.35 | K22: =J22*I22 -> 101.25 | L22: PSS-08 | M22: 45851 | N22: 45990 | W22: 75 | Z22: 0 | AF22: Completed | AG22: Completed | AH22: Completed | AI22: Completed
A23: P-10 | B23: MLP T1 J&K | C23: AGE26AL | D23: A-16a | E23: PPA | F23: PPA | G23: FT | H23: SEA | I23: 50 | J23: 1.3306 | K23: =J23*I23 -> 66.53 | L23: PSS-06 | M23: 45997 | N23: 46034 | X23: 50 | AF23: Completed | AG23: Completed | AH23: Completed | AI23: Completed | AK23: 129 | AL23: 250
A24: P-11 | B24: MLP T1 CG | C24: AGE26AL | D24: A-16b | E24: PPA | F24: PPA | G24: FT | H24: SEA | I24: 200 | J24: 1.3181 | K24: =J24*I24 -> 263.62 | L24: PSS-06 | M24: 45997 | N24: 46034 | X24: 175 | Y24: 25 | AF24: 0.77 | AG24: 0.417 | AH24: 0.278 | AI24: C:63%; E:63% | AK24: 659 | AL24: 1050
A25: P-12 | B25: MLP T1 TN | C25: AGE26AL | D25: A-16c | E25: PPA | F25: PPA | G25: FT | H25: SEA | I25: 167 | J25: 1.3293413 | K25: =J25*I25 -> 222 | L25: PSS-06 | M25: 45997 | N25: 46034 | X25: 100 | Y25: 67 | AF25: 0.6093 | AG25: 0.019262855 | AI25: C:0%; E:0% | AK25: 331 | AL25: 1020
A26: P-13 | B26: MLP T1 OR | C26: AGE26AL | D26: A-16d | E26: PPA | F26: PPA | G26: FT | H26: SEA | I26: 333 | J26: 1.3243243 | K26: =J26*I26 -> 441 | L26: PSS-06 | M26: 46049 | N26: 46034 | X26: 150 | Y26: 183 | AB26: 0 | AC26: 0 | AD26: 0 | AF26: 0.5239 | AG26: 0.03 | AI26: C:15%; E:11% | AK26: 304 | AL26: 1620
A27: P-14 | B27: MLP T1 TR | C27: AGE26AL | D27: A10a | E27: PPA | F27: PPA | G27: FT | H27: SEA | I27: 50 | J27: 1.36 | K27: =J27*I27 -> 68 | L27: PSS-03 | M27: 45373 | N27: 08-Dec-25 (LTA -23D) | U27: 50 | AB27: 0 | AC27: 0 | AF27: 0.9952 | AG27: 0.962 | AH27: 0.91 | AI27: Completed | AK27: 56 | AL27: 90
A28: P-15 | B28: MLP T3 AP | C28: AGE25CL | D28: A-6 | E28: PPA | F28: PPA | G28: FT | H28: China | I28: 425 | J28: 1.36 | K28: =J28*I28 -> 578 | L28: PSS-08 | M28: 45961 | N28: 45990 | X28: 100 | Y28: 150 | Z28: 175 | AB28: 0 | AC28: 0 | AD28: 0 | AF28: 0.678 | AG28: 0.1813 | AI28: C:59%; E:47% | AK28: 794 | AL28: 1420
B29: Subtotal (A) | I29: =SUM(I5:I28)-I16 -> 4484.5 | K29: =SUM(K5:K28)-K16 -> 6092.1 | O29: =SUM(O5:O28)-O16 -> 370 | P29: =SUM(P5:P28)-P16 -> 287.5 | Q29: =SUM(Q5:Q28)-Q16 -> 637.5 | R29: =SUM(R5:R28)-R16 -> 60 | S29: =SUM(S5:S28)-S16 -> 262.5 | T29: =SUM(T5:T28)-T16 -> 500 | U29: =SUM(U5:U28)-U16 -> 125 | V29: =SUM(V5:V28)-V16 -> 250 | ... Z29: =SUM(Z5:Z28)-Z16 -> 175 | AB29: =SUM(AB5:AB28) -> 0 | AC29: =SUM(AC5:AC28) -> 0 | AD29: =SUM(AD5:AD28) -> 0 | AK29: =SUM(AK4:AK28) -> 3930 | AL29: =SUM(AL5:AL28) -> 7397
A30: D1. Khavda Solar (Copper + Merchant - 50 MW)
A31: P-18a | B31: KCTL | C31: KCTL | D31: A-15a | E31: Group | F31: Group | G31: HSAT | H31: ALMM | I31: 12.5 | J31: 1.35 | K31: =J31*I31 -> 16.875 | L31: PSS-08 | M31: 45961 | N31: - | Y31: 12.5 | AB31: 0 | AC31: 0 | AD31: 0 | AL31: 30
A32: P-18b | B32: MCIPL | C32: MCIPL | D32: A-15a | E32: Group | F32: Group | G32: HSAT | H32: ALMM | I32: 12.5 | J32: 1.35 | K32: =J32*I32 -> 16.875 | L32: PSS-08 | M32: 45961 | N32: - | Y32: 12.5 | AB32: 0 | AC32: 0 | AD32: 0 | AL32: 30
A33: P-19 | B33: AGEL Merchant | C33: ASEJo6PL | D33: A-15a | E33: Merchant | F33: Merchant | G33: HSAT | H33: ALMM | I33: 25 | J33: 1.35 | K33: =J33*I33 -> 33.75 | L33: PSS-08 | M33: 45961 | N33: - | Y33: 25 | AB33: 0 | AC33: 0 | AD33: 0 | AL33: 60
B34: Subtotal (D1) | I34: =SUM(I31:I33) -> 50 | K34: =SUM(K31:K33) -> 67.5 | O34: =SUM(O31:O33) -> 0 | P34: =SUM(P31:P33) -> 0 | Q34: =SUM(Q31:Q33) -> 0 | R34: =SUM(R31:R33) -> 0 | S34: =SUM(S31:S33) -> 0 | T34: =SUM(T31:T33) -> 0 | U34: =SUM(U31:U33) -> 0 | V34: =SUM(V31:V33) -> 0 | ... Z34: =SUM(Z31:Z33) -> 0 | AB34: =SUM(AB31:AB33) -> 0 | AC34: =SUM(AC31:AC33) -> 0 | AD34: =SUM(AD31:AD33) -> 0 | AL34: =SUM(AL31:AL33) -> 120
A35: D2. Khavda Solar (Additional from Internal - 650 MW)
A36: P-16 | B36: AGEL Hybrid Merchant | C36: AHEJ5L | D36: S-4 | E36: Merchant | F36: Merchant | G36: HSAT | H36: ALMM | I36: 300 | J36: 1.35 | K36: =J36*I36 -> 405 | L36: PSS-11 | M36: 45996 | N36: - | AB36: 0 | AC36: 0 | AD36: 0 | AL36: 890
A37: P-17 | B37: =B8 -> MLP AP New | C37: =C8 -> ARE57L | D37: =D8 -> A-12 | E37: PPA | F37: PPA | G37: HSAT | H37: China | I37: 350 | J37: 1.35 | K37: =J37*I37 -> 472.5 | L37: =L8 -> PSS-13 | M37: 45708 | N37: 15-Jun-29 (LTA +15D) | AB37: 0 | AC37: 0 | AD37: 0 | AF37: 0.98608963 | AG37: 0.0187 | AH37: 0 | AI37: C:60%; E:7% | AL37: 870
B38: Subtotal (D2) | I38: =SUM(I36:I37) -> 650 | K38: =SUM(K36:K37) -> 877.5 | O38: =SUM(O36:O37) -> 0 | P38: =SUM(P36:P37) -> 0 | Q38: =SUM(Q36:Q37) -> 0 | R38: =SUM(R36:R37) -> 0 | S38: =SUM(S36:S37) -> 0 | T38: =SUM(T36:T37) -> 0 | U38: =SUM(U36:U37) -> 0 | V38: =SUM(V36:V37) -> 0 | ... Z38: =SUM(Z36:Z37) -> 0 | AB38: =SUM(AB36:AB37) -> 0 | AC38: =SUM(AC36:AC37) -> 0 | AD38: =SUM(AD36:AD37) -> 0 | AK38: =AK36+AK37 -> 0 | AL38: =AL36+AL37 -> 1760
A40: Overall Total (A + D1 + D2) | I40: =+I29+I34+I38 -> 5184.5 | K40: =+K29+K34+K38 -> 7037.1 | O40: =+O29+O34+O38 -> 370 | P40: =+P29+P34+P38 -> 287.5 | Q40: =+Q29+Q34+Q38 -> 637.5 | R40: =+R29+R34+R38 -> 60 | S40: =+S29+S34+S38 -> 262.5 | T40: =+T29+T34+T38 -> 500 | U40: =+U29+U34+U38 -> 125 | V40: =+V29+V34+V38 -> 250 | ... Z40: =+Z29+Z34+Z38 -> 175 | AB40: =+AB29+AB34+AB38 -> 0 | AC40: =+AC29+AC34+AC38 -> 0 | AD40: =+AD29+AD34+AD38 -> 0 | AK40: =+AK29+AK34+AK38 -> 3930 | AL40: =+AL29+AL34+AL38 -> 9277
L46: PSS-03 | O46: =SUMIF($L$5:$L$40,$L46,O$5:O$40) -> 0 | P46: =SUMIF($L$5:$L$40,$L46,P$5:P$40) -> 0 | Q46: =SUMIF($L$5:$L$40,$L46,Q$5:Q$40) -> 0 | R46: =SUMIF($L$5:$L$40,$L46,R$5:R$40) -> 0 | S46: =SUMIF($L$5:$L$40,$L46,S$5:S$40) -> 0 | T46: =SUMIF($L$5:$L$40,$L46,T$5:T$40) -> 0 | U46: =SUMIF($L$5:$L$40,$L46,U$5:U$40) -> 50 | V46: =SUMIF($L$5:$L$40,$L46,V$5:V$40) -> 0 | ... Z46: =SUMIF($L$5:$L$40,$L46,Z$5:Z$40) -> 0
L47: PSS-04 | O47: =SUMIF($L$5:$L$40,$L47,O$5:O$40) -> 0 | P47: =SUMIF($L$5:$L$40,$L47,P$5:P$40) -> 50 | Q47: =SUMIF($L$5:$L$40,$L47,Q$5:Q$40) -> 0 | R47: =SUMIF($L$5:$L$40,$L47,R$5:R$40) -> 0 | S47: =SUMIF($L$5:$L$40,$L47,S$5:S$40) -> 0 | T47: =SUMIF($L$5:$L$40,$L47,T$5:T$40) -> 50 | U47: =SUMIF($L$5:$L$40,$L47,U$5:U$40) -> 0 | V47: =SUMIF($L$5:$L$40,$L47,V$5:V$40) -> 0 | ... Z47: =SUMIF($L$5:$L$40,$L47,Z$5:Z$40) -> 0
L48: PSS-05 | O48: =SUMIF($L$5:$L$40,$L48,O$5:O$40) -> 195 | P48: =SUMIF($L$5:$L$40,$L48,P$5:P$40) -> 0 | Q48: =SUMIF($L$5:$L$40,$L48,Q$5:Q$40) -> 275 | R48: =SUMIF($L$5:$L$40,$L48,R$5:R$40) -> 0 | S48: =SUMIF($L$5:$L$40,$L48,S$5:S$40) -> 50 | T48: =SUMIF($L$5:$L$40,$L48,T$5:T$40) -> 150 | U48: =SUMIF($L$5:$L$40,$L48,U$5:U$40) -> 75 | V48: =SUMIF($L$5:$L$40,$L48,V$5:V$40) -> 0 | ... Z48: =SUMIF($L$5:$L$40,$L48,Z$5:Z$40) -> 0
L49: PSS-06 | O49: =SUMIF($L$5:$L$40,$L49,O$5:O$40) -> 0 | P49: =SUMIF($L$5:$L$40,$L49,P$5:P$40) -> 0 | Q49: =SUMIF($L$5:$L$40,$L49,Q$5:Q$40) -> 0 | R49: =SUMIF($L$5:$L$40,$L49,R$5:R$40) -> 0 | S49: =SUMIF($L$5:$L$40,$L49,S$5:S$40) -> 0 | T49: =SUMIF($L$5:$L$40,$L49,T$5:T$40) -> 0 | U49: =SUMIF($L$5:$L$40,$L49,U$5:U$40) -> 0 | V49: =SUMIF($L$5:$L$40,$L49,V$5:V$40) -> 0 | ... Z49: =SUMIF($L$5:$L$40,$L49,Z$5:Z$40) -> 0
L50: PSS-08 | O50: =SUMIF($L$5:$L$40,$L50,O$5:O$40) -> 0 | P50: =SUMIF($L$5:$L$40,$L50,P$5:P$40) -> 0 | Q50: =SUMIF($L$5:$L$40,$L50,Q$5:Q$40) -> 0 | R50: =SUMIF($L$5:$L$40,$L50,R$5:R$40) -> 60 | S50: =SUMIF($L$5:$L$40,$L50,S$5:S$40) -> 0 | T50: =SUMIF($L$5:$L$40,$L50,T$5:T$40) -> 50 | U50: =SUMIF($L$5:$L$40,$L50,U$5:U$40) -> 0 | V50: =SUMIF($L$5:$L$40,$L50,V$5:V$40) -> 0 | ... Z50: =SUMIF($L$5:$L$40,$L50,Z$5:Z$40) -> 175
L51: PSS-09 | O51: =SUMIF($L$5:$L$40,$L51,O$5:O$40) -> 0 | P51: =SUMIF($L$5:$L$40,$L51,P$5:P$40) -> 75 | Q51: =SUMIF($L$5:$L$40,$L51,Q$5:Q$40) -> 50 | R51: =SUMIF($L$5:$L$40,$L51,R$5:R$40) -> 0 | S51: =SUMIF($L$5:$L$40,$L51,S$5:S$40) -> 125 | T51: =SUMIF($L$5:$L$40,$L51,T$5:T$40) -> 100 | U51: =SUMIF($L$5:$L$40,$L51,U$5:U$40) -> 0 | V51: =SUMIF($L$5:$L$40,$L51,V$5:V$40) -> 0 | ... Z51: =SUMIF($L$5:$L$40,$L51,Z$5:Z$40) -> 0
L52: PSS-10 | O52: =SUMIF($L$5:$L$40,$L52,O$5:O$40) -> 100 | P52: =SUMIF($L$5:$L$40,$L52,P$5:P$40) -> 0 | Q52: =SUMIF($L$5:$L$40,$L52,Q$5:Q$40) -> 137.5 | R52: =SUMIF($L$5:$L$40,$L52,R$5:R$40) -> 0 | S52: =SUMIF($L$5:$L$40,$L52,S$5:S$40) -> 87.5 | T52: =SUMIF($L$5:$L$40,$L52,T$5:T$40) -> 150 | U52: =SUMIF($L$5:$L$40,$L52,U$5:U$40) -> 0 | V52: =SUMIF($L$5:$L$40,$L52,V$5:V$40) -> 125 | ... Z52: =SUMIF($L$5:$L$40,$L52,Z$5:Z$40) -> 0
L53: PSS-11 | O53: =SUMIF($L$5:$L$40,$L53,O$5:O$40) -> 0 | P53: =SUMIF($L$5:$L$40,$L53,P$5:P$40) -> 0 | Q53: =SUMIF($L$5:$L$40,$L53,Q$5:Q$40) -> 0 | R53: =SUMIF($L$5:$L$40,$L53,R$5:R$40) -> 0 | S53: =SUMIF($L$5:$L$40,$L53,S$5:S$40) -> 0 | T53: =SUMIF($L$5:$L$40,$L53,T$5:T$40) -> 0 | U53: =SUMIF($L$5:$L$40,$L53,U$5:U$40) -> 0 | V53: =SUMIF($L$5:$L$40,$L53,V$5:V$40) -> 0 | ... Z53: =SUMIF($L$5:$L$40,$L53,Z$5:Z$40) -> 0
L54: PSS-13 | O54: =SUMIF($L$5:$L$40,$L54,O$5:O$40) -> 75 | P54: =SUMIF($L$5:$L$40,$L54,P$5:P$40) -> 162.5 | Q54: =SUMIF($L$5:$L$40,$L54,Q$5:Q$40) -> 175 | R54: =SUMIF($L$5:$L$40,$L54,R$5:R$40) -> 0 | S54: =SUMIF($L$5:$L$40,$L54,S$5:S$40) -> 0 | T54: =SUMIF($L$5:$L$40,$L54,T$5:T$40) -> 0 | U54: =SUMIF($L$5:$L$40,$L54,U$5:U$40) -> 0 | V54: =SUMIF($L$5:$L$40,$L54,V$5:V$40) -> 125 | ... Z54: =SUMIF($L$5:$L$40,$L54,Z$5:Z$40) -> 0
M55: 2642.5

Sheet  RJ Solar Plan
A1: FY 2025-26 | RJ & AP Solar Projects Monthly Commissioning Plan (MWac) | U1: For Internal Purpose | Z1: Date: 1-Oct-25
A2: Priority | B2: Project | C2: SPV | D2: Location | E2: Category | F2: MMS Type | G2: Capacity (MWac) | H2: OL | I2: Capacity (MWdc) | J2: SCOD | K2: Commissioning as per Business Plan | L2: Capex BOQ Release Date | N2: Till Feb-25 | O2: 45717 | P2: 45748 | Q2: 45778 | R2: 45809 | S2: 45839 | T2: 45870 | U2: 45901 | V2: 45931 | W2: 45962 | X2: 45992 | Y2: 46023 | Z2: 46054 | AA2: 46082 | AC2: Capex NFA Status
A3: 1 | B3: Ambuja Cement Limited | C3: ACL | D3: Essel Park | E3: Group | F3: FT | G3: 300 | H3: 1.42 | I3: =H3*G3 -> 426 | J3: NA | K3: 45838 | R3: 300
A4: 2 | B4: Ultratech | C4: ASEJ6PL | D4: Bap | E4: Merchant | F4: HSAT | G4: 50 | H4: 1.37 | I4: =H4*G4 -> 68.5 | J4: NA | K4: 45838 | R4: 50
A5: 3 | B5: NHPC BOO | C5: ASEB1PL | D5: Baiya | E5: PPA | F5: FT | G5: 600 | H5: 1.36 | I5: =H5*G5 -> 816 | J5: Extension awaited | K5: 46081 | L5: Capex Approved | AC5: Approved
A6: 4 | B6: MLP AP NEW | C6: AGE26BL | D6: Bandha | E6: PPA | F6: HSAT | G6: 534 | H6: 1.37 | I6: =H6*G6 -> 731.58 | J6: 46296 | K6: 45930 | L6: Capex Approved | W6: 250 | X6: 284 | AC6: Approved
A7: 5 | B7: MLP T1 | C7: AGE27L | D7: Bandha | E7: PPA | F7: FT | G7: 500 | H7: 1.39 | I7: =H7*G7 -> 695 | J7: LTA+60 Days | K7: =K5 -> 46081 | L7: 45608 | X7: 200 | Y7: 300
A8: Total | G8: =SUM(G3:G7) -> 1984 | I8: =SUM(I3:I7) -> 2737.08 | N8: =SUM(N3:N7) -> 0 | O8: =SUM(O3:O7) -> 0 | P8: =SUM(P3:P7) -> 0 | Q8: =SUM(Q3:Q7) -> 0 | R8: =SUM(R3:R7) -> 350 | S8: =SUM(S3:S7) -> 0 | T8: =SUM(T3:T7) -> 0 | U8: =SUM(U3:U7) -> 0 | ... AA8: =SUM(AA3:AA7) -> 0 | AC8: =SUM(#REF!) -> #REF!

Sheet  RJ Solar Rephase
A1: FY 2025-26 | RJ & AP Solar Projects Monthly Commissioning Plan (MWac) | U1: For Internal Purpose | Z1: Date: 1-Oct-25
A2: Priority | B2: Project | C2: SPV | D2: Location | E2: Category | F2: MMS Type | G2: Capacity (MWac) | H2: OL | I2: Capacity (MWdc) | J2: SCOD | K2: Commissioning as per Business Plan | L2: Capex BOQ Release Date | N2: Till Feb-25 | O2: 45717 | P2: 45748 | Q2: 45778 | R2: 45809 | S2: 45839 | T2: 45870 | U2: 45901 | V2: 45931 | W2: 45962 | X2: 45992 | Y2: 46023 | Z2: 46054 | AA2: 46082 | AC2: Capex NFA Status
A3: 1 | B3: Ambuja Cement Limited | C3: ACL | D3: Essel Park | E3: Group | F3: FT | G3: 300 | H3: 1.42 | I3: =H3*G3 -> 426 | J3: NA | K3: 45838 | S3: 150 | T3: 150
A4: 2 | B4: Ultratech | C4: ASEJ6PL | D4: Bap | E4: Merchant | F4: HSAT | G4: 50 | H4: 1.37 | I4: =H4*G4 -> 68.5 | J4: NA | K4: 45838 | R4: 50
A5: 3 | B5: NHPC BOO | C5: ASEB1PL | D5: Baiya | E5: PPA | F5: FT | G5: 600 | H5: 1.36 | I5: =H5*G5 -> 816 | J5: Extension awaited | K5: 46081 | L5: Capex Approved | AC5: Approved
A6: 4 | B6: MLP AP NEW | C6: AGE26BL | D6: Bandha | E6: PPA | F6: HSAT | G6: 534 | H6: 1.37 | I6: =H6*G6 -> 731.58 | J6: 46296 | K6: 45930 | L6: Capex Approved | X6: 534 | AC6: Approved
A7: 5 | B7: MLP T1 | C7: AGE27L | D7: Bandha | E7: PPA | F7: FT | G7: 500 | H7: 1.39 | I7: =H7*G7 -> 695 | J7: LTA+60 Days | K7: =K5 -> 46081 | L7: 45608 | Y7: 250 | Z7: 250
A8: Total | G8: =SUM(G3:G7) -> 1984 | I8: =SUM(I3:I7) -> 2737.08 | N8: =SUM(N3:N7) -> 0 | O8: =SUM(O3:O7) -> 0 | P8: =SUM(P3:P7) -> 0 | Q8: =SUM(Q3:Q7) -> 0 | R8: =SUM(R3:R7) -> 50 | S8: =SUM(S3:S7) -> 150 | T8: =SUM(T3:T7) -> 150 | U8: =SUM(U3:U7) -> 0 | ... AA8: =SUM(AA3:AA7) -> 0 | AC8: =SUM(#REF!) -> #REF!

Sheet  RJ Solar - Actual
A1: FY 2025-26 | RJ & AP Solar Projects Monthly Commissioning Plan (MWac) | Z1: Date: 26-Dec-25
A2: Priority | B2: Project | C2: SPV | D2: Location | E2: Category | F2: MMS Type | G2: Capacity (MWac) | H2: OL | I2: Capacity (MWdc) | J2: SCOD | K2: Commissioning as per Business Plan | L2: Capex BOQ Release Date | N2: Till Feb-25 | O2: 45717 | P2: 45748 | Q2: 45778 | R2: 45809 | S2: 45839 | T2: 45870 | U2: 45901 | V2: 45931 | W2: 45962 | X2: 45992 | Y2: 46023 | Z2: 46054 | AA2: 46082
A3: 1 | B3: Ambuja Cement Limited | C3: ACL | D3: Essel Park | E3: Group | F3: FT | G3: 300 | H3: 1.42 | I3: =H3*G3 -> 426 | J3: NA | K3: 45838 | T3: 150 | X3: 150
A4: 2 | B4: Ultratech | C4: ASEJ6PL | D4: Bap | E4: Merchant | F4: HSAT | G4: 50 | H4: 1.37 | I4: =H4*G4 -> 68.5 | J4: NA | K4: 45838 | R4: 50
A5: 3 | B5: NHPC BOO | C5: ASEB1PL | D5: Baiya | E5: PPA | F5: FT | G5: 600 | H5: 1.36 | I5: =H5*G5 -> 816 | J5: Extension awaited | K5: 46081 | L5: Capex Approved | AA5: 300
A6: 4 | B6: MLP AP NEW | C6: AGE26BL | D6: Bandha | E6: PPA | F6: HSAT | G6: 534 | H6: 1.37 | I6: =H6*G6 -> 731.58 | J6: 46296 | K6: 45930 | L6: Capex Approved
A7: 5 | B7: MLP T1 | C7: AGE25BL | D7: Bandha | E7: PPA | F7: FT | G7: 500 | H7: 1.39 | I7: =H7*G7 -> 695 | J7: LTA+60 Days | K7: =K5 -> 46081 | L7: 45608 | AA7: 250 | AB7: 1034 | AC7: =AB7-AA7-AA5 -> 484
A8: Total | G8: =SUM(G3:G7) -> 1984 | I8: =SUM(I3:I7) -> 2737.08 | N8: =SUM(N3:N7) -> 0 | O8: =SUM(O3:O7) -> 0 | P8: =SUM(P3:P7) -> 0 | Q8: =SUM(Q3:Q7) -> 0 | R8: =SUM(R3:R7) -> 50 | S8: =SUM(S3:S7) -> 0 | T8: =SUM(T3:T7) -> 150 | U8: =SUM(U3:U7) -> 0 | ... AA8: =SUM(AA3:AA7) -> 550

Sheet KH Wind Plan
A2: FY 2024-26 | Khavda Wind Projects Monthly Commissioning Plan (MWac) | R2: Date: 31-Mar-25
A3: Sl. | B3: Project | C3: SPV | D3: Category | E3: Capacity (MW) | F3: WTG Nos. | G3: PSS No. | H3: 45748 | I3: 45778 | J3: 45809 | K3: 45839 | L3: 45870 | M3: 45901 | N3: 45931 | O3: 45962 | P3: 45992 | Q3: 46023 | R3: 46054 | S3: 46082
A4: 1 | B4: AGEL Merchant (Wind) | C4: AGE24L | D4: Merchant | E4: =SUM(H4:S4) -> 52 | F4: =E4/5.2 -> 10 | G4: PSS-04 | H4: 52
A5: 2 | B5: Hybrid Cement (Wind) | C5: ACL | D5: Group | E5: =SUM(H5:S5) -> 57.2 | F5: =E5/5.2 -> 11 | G5: PSS-04 | H5: 26 | I5: 31.2
A6: 3 | B6: AGEL Merchant (Wind) | C6: AHEJ5L | D6: Merchant | E6: =SUM(H6:S6) -> 62.4 | F6: =E6/5.2 -> 12 | G6: PSS-04 | H6: 52 | I6: 10.4
A7: 4 | B7: AGEL Hybrid Merchant (Wind) | C7: AGE26BL | D7: Merchant | E7: =SUM(H7:S7) -> 156 | F7: =E7/5.2 -> 30 | G7: PSS-10 | H7: 52 | I7: 104
A8: 5 | B8: AGEL Merchant (Wind) | C8: AHEJ5L | D8: Merchant | E8: =SUM(H8:S8) -> 67.6 | F8: =E8/5.2 -> 13 | G8: PSS-08 | J8: 67.6
A9: 6 | B9: AGEL Merchant (Wind) | C9: ARE41L | D9: Merchant | E9: =SUM(H9:S9) -> 130 | F9: =E9/5.2 -> 25 | G9: PSS-08 | I9: 36.4 | J9: 93.6
A10: 7 | B10: Google Hybrid (Wind) | C10: ARE3L | D10: Merchant | E10: =SUM(H10:S10) -> 15.6 | F10: =E10/5.2 -> 3 | G10: PSS-08 | J10: 15.6
A11: 8 | B11: Google Hybrid (Wind) | C11: ARE3L | D11: Merchant | E11: =SUM(H11:S11) -> 26 | F11: =E11/5.2 -> 5 | G11: PSS-08 | H11: 0 | J11: 26
A12: 9 | B12: AGEL Hybrid Merchant (Wind) | C12: ASEJ6PL | D12: Merchant | E12: =SUM(H12:S12) -> 62.4 | F12: =E12/5.2 -> 12 | G12: PSS-08 | J12: 41.6 | K12: 20.8
A13: 10 | B13: SECI H-3 (Wind) | C13: AHEJ5L | D13: PPA | E13: =SUM(H13:S13) -> 202.8 | F13: =E13/5.2 -> 39 | G13: PSS-05 | K13: 72.8 | L13: 26 | M13: 26 | N13: 52 | O13: 26
A14: 11a | B14: AGEL Merchant (Wind) | C14: AGE25CL | D14: Merchant | E14: =SUM(H14:S14) -> 156 | F14: =E14/5.2 -> 30 | G14: PSS-11 | O14: 104 | P14: 52
A15: 12a | B15: AGEL Merchant (Wind) | C15: AGE26AL | D15: Merchant | E15: =SUM(H15:S15) -> 140.4 | F15: =E15/5.2 -> 27 | G15: PSS-12 | P15: 78 | Q15: 62.4
B16: Total | E16: =SUM(E4:E15) -> 1128.4 | F16: =SUM(F4:F15) -> 217 | H16: =SUM(H4:H15) -> 182 | I16: =SUM(I4:I15) -> 182 | J16: =SUM(J4:J15) -> 244.4 | K16: =SUM(K4:K15) -> 93.6 | L16: =SUM(L4:L15) -> 26 | M16: =SUM(M4:M15) -> 26 | N16: =SUM(N4:N15) -> 52 | O16: =SUM(O4:O15) -> 130 | ... S16: =SUM(S4:S15) -> 0
A19: 11b | B19: AGEL Merchant (Wind) | C19: AGE25CL | D19: Merchant | E19: =SUM(H19:S19) -> 98.8 | F19: =E19/5.2 -> 19 | H19: =SUM(H20:H21) -> 0 | I19: =SUM(I20:I21) -> 0 | J19: =SUM(J20:J21) -> 0 | K19: =SUM(K20:K21) -> 0 | L19: =SUM(L20:L21) -> 0 | M19: =SUM(M20:M21) -> 0 | N19: =SUM(N20:N21) -> 0 | O19: =SUM(O20:O21) -> 0 | ... S19: =SUM(S20:S21) -> 0
G20: PSS-11 | Q20: =6*5.2 -> 31.2
G21: PSS-14 | Q21: =13*5.2 -> 67.6
A22: 12b | B22: AGEL Merchant (Wind) | C22: AGE26AL | D22: Merchant | E22: =SUM(H22:S22) -> 312 | F22: =E22/5.2 -> 60 | G22: PSS-12 | Q22: =8*5.2 -> 41.6 | R22: =30*5.2 -> 156 | S22: =22*5.2 -> 114.4
A23: 13 | B23: AGEL Merchant | C23: AGE25BL | D23: Merchant | E23: =SUM(H23:S23) -> 10.4 | F23: =E23/5.2 -> 2 | G23: PSS-09 | P23: =2*5.2 -> 10.4
B24: Total (for Internal) | E24: =SUM(E19:E23) -> 421.2 | F24: =SUM(F19:F23) -> 81 | H24: =SUM(H20:H23) -> 0 | I24: =SUM(I20:I23) -> 0 | J24: =SUM(J20:J23) -> 0 | K24: =SUM(K20:K23) -> 0 | L24: =SUM(L20:L23) -> 0 | M24: =SUM(M20:M23) -> 0 | N24: =SUM(N20:N23) -> 0 | O24: =SUM(O20:O23) -> 0 | ... S24: =SUM(S20:S23) -> 114.4
B26: Total | E26: =+E24+E16 -> 1549.6 | F26: =+F24+F16 -> 298 | G26: =+G24+G16 -> 0 | H26: =+H24+H16 -> 182 | I26: =+I24+I16 -> 182 | J26: =+J24+J16 -> 244.4 | K26: =+K24+K16 -> 93.6 | L26: =+L24+L16 -> 26 | ... S26: =+S24+S16 -> 114.4

Sheet KH Wind Rephase
A2: FY 2024-26 | Khavda Wind Projects Monthly Commissioning Plan (MWac) | J2: Chairman Budget Purpose Revised | R2: Date: 30-Jun-25
A3: Sl. | B3: Project | C3: SPV | D3: Category | E3: Capacity (MW) | F3: WTG Nos. | G3: PSS No. | H3: 45748 | I3: 45778 | J3: 45809 | K3: 45839 | L3: 45870 | M3: 45901 | N3: 45931 | O3: 45962 | P3: 45992 | Q3: 46023 | R3: 46054 | S3: 46082
A4: 1 | B4: AGEL Merchant (Wind) | C4: AGE24L | D4: Merchant | E4: 52 | F4: =E4/5.2 -> 10 | G4: PSS-04 | H4: =10*5.2 -> 52
A5: 2 | B5: Hybrid Cement (Wind) | C5: ACL | D5: Group | E5: 57.2 | F5: =E5/5.2 -> 11 | G5: PSS-04 | I5: =5*5.2 -> 26 | J5: =6*5.2 -> 31.2
A6: 3 | B6: AGEL Merchant (Wind) | C6: AHEJ5L | D6: Merchant | E6: 62.4 | F6: =E6/5.2 -> 12 | G6: PSS-04 | H6: =10*5.2 -> 52 | J6: =2*5.2 -> 10.4
A7: 4 | B7: AGEL Hybrid Merchant (Wind) | C7: AGE26BL | D7: Merchant | E7: 156 | F7: =E7/5.2 -> 30 | G7: PSS-10 | J7: =23*5.2 -> 119.6 | K7: =5*5.2 -> 26 | L7: =2*5.2 -> 10.4
A8: 5 | B8: AGEL Merchant (Wind) | C8: AHEJ5L | D8: Merchant | E8: 67.6 | F8: =E8/5.2 -> 13 | G8: PSS-08 | M8: =10*5.2 -> 52 | N8: =3*5.2 -> 15.6
A9: 6 | B9: AGEL Merchant (Wind) | C9: ARE41L | D9: Merchant | E9: 130 | F9: =E9/5.2 -> 25 | G9: PSS-08 | K9: =10*5.2 -> 52 | L9: =5*5.2 -> 26 | M9: =5*5.2 -> 26 | N9: =5*5.2 -> 26
A10: 7 | B10: Google Hybrid (Wind) | C10: ARE3L | D10: Merchant | E10: 15.6 | F10: =E10/5.2 -> 3 | G10: PSS-08 | L10: =3*5.2 -> 15.6
A11: 8 | B11: Google Hybrid (Wind) | C11: ARE3L | D11: Merchant | E11: 26 | F11: =E11/5.2 -> 5 | G11: PSS-08 | H11: =3*5.2*0 -> 0 | L11: =5*5.2 -> 26
A12: 9 | B12: AGEL Hybrid Merchant (Wind) | C12: ASEJ6PL | D12: Merchant | E12: 62.4 | F12: =E12/5.2 -> 12 | G12: PSS-08 | N12: =12*5.2 -> 62.4
A13: 10 | B13: SECI H-3 (Wind) | C13: AHEJ5L | D13: PPA | E13: 202.8 | F13: =E13/5.2 -> 39 | G13: PSS-05 | O13: =20*5.2 -> 104 | P13: =19*5.2 -> 98.8
A14: 11a | B14: AGEL Merchant (Wind) | C14: AGE25CL | D14: Merchant | E14: 156 | F14: =E14/5.2 -> 30 | G14: PSS-11 | Q14: =20*5.2 -> 104 | R14: =10*5.2 -> 52
A15: 12a | B15: AGEL Merchant (Wind) | C15: AGE26AL | D15: Merchant | E15: 140.4 | F15: =E15/5.2 -> 27 | G15: PSS-12 | R15: =15*5.2 -> 78 | S15: =12*5.2 -> 62.4
B16: Total | E16: =SUM(E4:E15) -> 1128.4 | F16: =SUM(F4:F15) -> 217 | H16: =SUM(H4:H15) -> 104 | I16: =SUM(I4:I15) -> 26 | J16: =SUM(J4:J15) -> 161.2 | K16: =SUM(K4:K15) -> 78 | L16: =SUM(L4:L15) -> 78 | M16: =SUM(M4:M15) -> 78 | N16: =SUM(N4:N15) -> 104 | O16: =SUM(O4:O15) -> 104 | ... S16: =SUM(S4:S15) -> 62.4
A19: 11b | B19: AGEL Merchant (Wind) | C19: AGE25CL | D19: Merchant | E19: =SUM(H19:S19) -> 98.8 | F19: =E19/5.2 -> 19 | H19: =SUM(H20:H21) -> 0 | I19: =SUM(I20:I21) -> 0 | J19: =SUM(J20:J21) -> 0 | K19: =SUM(K20:K21) -> 0 | L19: =SUM(L20:L21) -> 0 | M19: =SUM(M20:M21) -> 0 | N19: =SUM(N20:N21) -> 0 | O19: =SUM(O20:O21) -> 0 | ... S19: =SUM(S20:S21) -> 0
G20: PSS-11 | Q20: =6*5.2 -> 31.2
G21: PSS-14 | Q21: =13*5.2 -> 67.6
A22: 12b | B22: AGEL Merchant (Wind) | C22: AGE26AL | D22: Merchant | E22: =SUM(H22:S22) -> 312 | F22: =E22/5.2 -> 60 | G22: PSS-12 | Q22: =8*5.2 -> 41.6 | R22: =30*5.2 -> 156 | S22: =22*5.2 -> 114.4
A23: 13 | B23: AGEL Merchant | C23: AGE25BL | D23: Merchant | E23: =SUM(H23:S23) -> 10.4 | F23: =E23/5.2 -> 2 | G23: PSS-09 | P23: =2*5.2 -> 10.4
B24: Total (for Internal) | E24: =SUM(E19:E23) -> 421.2 | F24: =SUM(F19:F23) -> 81 | H24: =SUM(H20:H23) -> 0 | I24: =SUM(I20:I23) -> 0 | J24: =SUM(J20:J23) -> 0 | K24: =SUM(K20:K23) -> 0 | L24: =SUM(L20:L23) -> 0 | M24: =SUM(M20:M23) -> 0 | N24: =SUM(N20:N23) -> 0 | O24: =SUM(O20:O23) -> 0 | ... S24: =SUM(S20:S23) -> 114.4
B26: Total | E26: =+E24+E16 -> 1549.6 | F26: =+F24+F16 -> 298 | G26: =+G24+G16 -> 0 | H26: =+H24+H16 -> 104 | I26: =+I24+I16 -> 26 | J26: =+J24+J16 -> 161.2 | K26: =+K24+K16 -> 78 | L26: =+L24+L16 -> 78 | ... S26: =+S24+S16 -> 176.8

Sheet KH Wind Internal
A2: FY 2025-26 | Khavda Wind Projects Monthly Commissioning Plan (MWac) (Phase-02 Carry forward) | O2: For Internal Purpose | W2: Date : 08-Dec-25
A3: Sl. | B3: Project | C3: SPV | D3: Category | E3: Total Capacity (MW) | F3: Total WTG Nos. | G3: PSS No. | H3: PSS Charging Date | I3: Till Mar-25 | J3: 45748 | K3: 45778 | L3: 45809 | M3: 45839 | N3: 45870 | O3: 45901 | P3: 45931 | Q3: 45962 | R3: 45992 | S3: 46023 | T3: 46054 | U3: 46082 | W3: FY 25-26 Total (Plan) | Y3: FY 25-26 Commissioned till Nov-25 | AA3: FY 24-25 Commissioned | AC3: Total Commissioned till Nov-25
W4: WTG | X4: MW | Y4: WTG | Z4: MW | AA4: WTG | AB4: MW | AC4: WTG | AD4: MW
A5: 1 | B5: Hybrid Port (Wind) | C5: APSEZ | D5: Group | E5: 20.8 | F5: =E5/5.2 -> 4 | G5: PSS-3 | H5: Charged | I5: 20.8 | W5: =+X5/5.2 -> 0 | X5: =+SUM(J5:U5) -> 0 | Y5: =+Z5/5.2 -> 0 | Z5: =+SUM(J5:Q5) -> 0 | AA5: =+AB5/5.2 -> 4 | AB5: 20.8 | AC5: =+AD5/5.2 -> 4 | AD5: =+AB5+Z5 -> 20.8 | AF5: =E5-SUM(I5:U5) -> 0
A6: 2 | B6: AGEL Merchant (Wind) | C6: ARE41L | D6: Merchant | E6: 260 | F6: =E6/5.2 -> 50 | G6: PSS-3 | H6: Charged | I6: 260 | W6: =+X6/5.2 -> 0 | X6: =+SUM(J6:U6) -> 0 | Y6: =+Z6/5.2 -> 0 | Z6: =+SUM(J6:Q6) -> 0 | AA6: =+AB6/5.2 -> 50 | AB6: 260 | AC6: =+AD6/5.2 -> 50 | AD6: =+AB6+Z6 -> 260 | AF6: =E6-SUM(I6:U6) -> 0
A7: 3 | B7: AGEL Hybrid Merchant (Wind) | C7: ARE48L AGE25BL | D7: Merchant | E7: =23*5.2 -> 119.6 | F7: =E7/5.2 -> 23 | G7: PSS-09 | H7: Charged | I7: =23*5.2 -> 119.6 | W7: =+X7/5.2 -> 0 | X7: =+SUM(J7:U7) -> 0 | Y7: =+Z7/5.2 -> 0 | Z7: =+SUM(J7:Q7) -> 0 | AA7: =+AB7/5.2 -> 23 | AB7: =23*5.2 -> 119.6 | AC7: =+AD7/5.2 -> 23 | AD7: =+AB7+Z7 -> 119.6 | AF7: =E7-SUM(I7:U7) -> 0 | AG7: =884+4345 -> 5229
A8: 4 | B8: AGEL Merchant (Wind) | C8: ARE41L | D8: Merchant | E8: =24*5.2 -> 124.8 | F8: =E8/5.2 -> 24 | G8: PSS-13 | H8: Charged | I8: =24*5.2 -> 124.8 | W8: =+X8/5.2 -> 0 | X8: =+SUM(J8:U8) -> 0 | Y8: =+Z8/5.2 -> 0 | Z8: =+SUM(J8:Q8) -> 0 | AA8: =+AB8/5.2 -> 24 | AB8: =24*5.2 -> 124.8 | AC8: =+AD8/5.2 -> 24 | AD8: =+AB8+Z8 -> 124.8 | AF8: =E8-SUM(I8:U8) -> 0
A9: 5 | B9: AGEL Merchant (Wind) | C9: AGE24L | D9: Merchant | E9: =20*5.2 -> 104 | F9: =E9/5.2 -> 20 | G9: PSS-04 | H9: Charged | I9: =10*5.2 -> 52 | J9: =10*5.2 -> 52 | W9: =+X9/5.2 -> 10 | X9: =+SUM(J9:U9) -> 52 | Y9: =+Z9/5.2 -> 10 | Z9: =+SUM(J9:Q9) -> 52 | AA9: =+AB9/5.2 -> 10 | AB9: =10*5.2 -> 52 | AC9: =+AD9/5.2 -> 20 | AD9: =+AB9+Z9 -> 104 | AF9: =E9-SUM(I9:U9) -> 0 | AG9: 4
A10: 6 | B10: Hybrid Cement (Wind) | C10: ACL | D10: Group | E10: =30*5.2 -> 156 | F10: =E10/5.2 -> 30 | G10: PSS-04 | H10: Charged | I10: =19*5.2 -> 98.8 | K10: =5*5.2 -> 26 | L10: =6*5.2 -> 31.2 | W10: =+X10/5.2 -> 11 | X10: =+SUM(J10:U10) -> 57.2 | Y10: =+Z10/5.2 -> 11 | Z10: =+SUM(J10:Q10) -> 57.2 | AA10: =+AB10/5.2 -> 19 | AB10: =19*5.2 -> 98.8 | AC10: =+AD10/5.2 -> 30 | AD10: =+AB10+Z10 -> 156 | AF10: =E10-SUM(I10:U10) -> 0
A11: 7 | B11: Hybrid Port (Wind) | C11: APSEZ | D11: Group | E11: =10*5.2 -> 52 | F11: =E11/5.2 -> 10 | G11: PSS-04 | H11: Charged | I11: =10*5.2 -> 52 | W11: =+X11/5.2 -> 0 | X11: =+SUM(J11:U11) -> 0 | Y11: =+Z11/5.2 -> 0 | Z11: =+SUM(J11:Q11) -> 0 | AA11: =+AB11/5.2 -> 10 | AB11: =10*5.2 -> 52 | AC11: =+AD11/5.2 -> 10 | AD11: =+AB11+Z11 -> 52 | AF11: =E11-SUM(I11:U11) -> 0
A12: 8 | B12: AGEL Merchant (Wind) | C12: AHEJ5L | D12: Merchant | E12: =12*5.2 -> 62.4 | F12: =E12/5.2 -> 12 | G12: PSS-04 | H12: Charged | J12: =10*5.2 -> 52 | L12: =2*5.2 -> 10.4 | W12: =+X12/5.2 -> 12 | X12: =+SUM(J12:U12) -> 62.4 | Y12: =+Z12/5.2 -> 12 | Z12: =+SUM(J12:Q12) -> 62.4 | AA12: =+AB12/5.2 -> 0 | AC12: =+AD12/5.2 -> 12 | AD12: =+AB12+Z12 -> 62.4 | AF12: =E12-SUM(I12:U12) -> 0 | AG12: 2.4
A13: 9 | B13: AESL PPA (C&I) - Wind - RSWM | C13: ARE41L | D13: Merchant | E13: =10*5.2 -> 52 | F13: =E13/5.2 -> 10 | G13: PSS-04 | H13: Charged | I13: =10*5.2 -> 52 | W13: =+X13/5.2 -> 0 | X13: =+SUM(J13:U13) -> 0 | Y13: =+Z13/5.2 -> 0 | Z13: =+SUM(J13:Q13) -> 0 | AA13: =+AB13/5.2 -> 10 | AB13: =10*5.2 -> 52 | AC13: =+AD13/5.2 -> 10 | AD13: =+AB13+Z13 -> 52 | AF13: =E13-SUM(I13:U13) -> 0
A14: 10 | B14: AGEL Hybrid Merchant (Wind) | C14: AGE26BL | D14: Merchant | E14: =30*5.2 -> 156 | F14: =E14/5.2 -> 30 | G14: PSS-10 | H14: Charged | L14: =23*5.2 -> 119.6 | M14: =5*5.2 -> 26 | U14: =2*5.2 -> 10.4 | W14: =+X14/5.2 -> 30 | X14: =+SUM(J14:U14) -> 156 | Y14: =+Z14/5.2 -> 28 | Z14: =+SUM(J14:Q14) -> 145.6 | AA14: =+AB14/5.2 -> 0 | AC14: =+AD14/5.2 -> 28 | AD14: =+AB14+Z14 -> 145.6 | AF14: =E14-SUM(I14:U14) -> 0
A15: 11 | B15: AGEL Merchant (Wind) | C15: AHEJ5L | D15: Merchant | E15: =13*5.2 -> 67.6 | F15: =E15/5.2 -> 13 | G15: PSS-08 | H15: Charged | O15: =6*5.2 -> 31.2 | Q15: =6*5.2 -> 31.2 | S15: =1*5.2 -> 5.2 | W15: =+X15/5.2 -> 13 | X15: =+SUM(J15:U15) -> 67.6 | Y15: =+Z15/5.2 -> 12 | Z15: =+SUM(J15:Q15) -> 62.4 | AA15: =+AB15/5.2 -> 0 | AC15: =+AD15/5.2 -> 12 | AD15: =+AB15+Z15 -> 62.4 | AF15: =E15-SUM(I15:U15) -> 0 | AI15: SPV | AJ15: PSS | AK15: WTGs | AL15: MW
A16: 12 | B16: AGEL Merchant (Wind) | C16: ARE41L | D16: Merchant | E16: =25*5.2 -> 130 | F16: =E16/5.2 -> 25 | G16: PSS-08 | H16: Charged | N16: =24*5.2 -> 124.8 | Q16: =1*5.2 -> 5.2 | W16: =+X16/5.2 -> 25 | X16: =+SUM(J16:U16) -> 130 | Y16: =+Z16/5.2 -> 25 | Z16: =+SUM(J16:Q16) -> 130 | AA16: =+AB16/5.2 -> 0 | AC16: =+AD16/5.2 -> 25 | AD16: =+AB16+Z16 -> 130 | AF16: =E16-SUM(I16:U16) -> 0 | AI16: AHEJ5L | AJ16: PSS-08 | AK16: 7 | AL16: =AK16*5.2 -> 36.4
A17: 13 | B17: Google Hybrid (Wind) | C17: ARE3L | D17: Merchant | E17: =3*5.2 -> 15.6 | F17: =E17/5.2 -> 3 | G17: PSS-08 | H17: Charged | M17: =3*5.2 -> 15.6 | W17: =+X17/5.2 -> 3 | X17: =+SUM(J17:U17) -> 15.6 | Y17: =+Z17/5.2 -> 3 | Z17: =+SUM(J17:Q17) -> 15.6 | AA17: =+AB17/5.2 -> 0 | AC17: =+AD17/5.2 -> 3 | AD17: =+AB17+Z17 -> 15.6 | AF17: =E17-SUM(I17:U17) -> 0 | AI17: ARE41L | AJ17: PSS-08 | AK17: 1 | AL17: =AK17*5.2 -> 5.2
A18: Monthwise FY 24-25 Projects (A) - Total (MW) | E18: =SUM(E5:E17) -> 1320.8 | I18: =SUM(I5:I17) -> 780 | J18: =SUM(J5:J17) -> 104 | K18: =SUM(K5:K17) -> 26 | L18: =SUM(L5:L17) -> 161.2 | M18: =SUM(M5:M17) -> 41.6 | N18: =SUM(N5:N17) -> 124.8 | O18: =SUM(O5:O17) -> 31.2 | P18: =SUM(P5:P17) -> 0 | ... U18: =SUM(U5:U17) -> 10.4 | W18: =+X18/5.2 -> 104 | X18: =+SUM(J18:U18) -> 540.8 | Y18: =+Z18/5.2 -> 101 | Z18: =+SUM(J18:Q18) -> 525.2 | AA18: =+AB18/5.2 -> 150 | AB18: =SUM(AB5:AB17) -> 780 | AC18: =+AD18/5.2 -> 251 | AD18: =+AB18+Z18 -> 1305.2 | AI18: ASEJ6PL | AJ18: PSS-08 | AK18: 10 | AL18: =AK18*5.2 -> 52
A19: Total (No of WTG's) | F19: =SUM(F5:F17) -> 254 | I19: =I18/5.2 -> 150 | J19: =J18/5.2 -> 20 | K19: =K18/5.2 -> 5 | L19: =L18/5.2 -> 31 | M19: =M18/5.2 -> 8 | N19: =N18/5.2 -> 24 | O19: =O18/5.2 -> 6 | P19: =P18/5.2 -> 0 | ... U19: =U18/5.2 -> 2 | AI19: AHEJ5L (PPA) | AJ19: PSS-05 | AK19: 18 | AL19: =AK19*5.2 -> 93.6
AI20: Total | AK20: =SUM(AK16:AK19) -> 36 | AL20: =SUM(AL16:AL19) -> 187.2
H21: Category | I21: Till Dec-24 | M21: 45839 | N21: 45870 | O21: 45901 | P21: 45931 | Q21: 45962 | R21: 45992 | S21: 46023 | T21: 46054 | U21: 46082
H22: Merchant | I22: =SUMIF($D$5:$D$14,$H22,I$5:I$14) -> 608.4 | M22: =SUMIF($D$5:$D$17,$H22,M$5:M$17) -> 41.6 | N22: =SUMIF($D$5:$D$14,$H22,N$5:N$14) -> 0 | O22: =SUMIF($D$5:$D$14,$H22,O$5:O$14) -> 0 | P22: =SUMIF($D$5:$D$14,$H22,P$5:P$14) -> 0 | Q22: =SUMIF($D$5:$D$14,$H22,Q$5:Q$14) -> 0 | R22: =SUMIF($D$5:$D$14,$H22,R$5:R$14) -> 0 | S22: =SUMIF($D$5:$D$14,$H22,S$5:S$14) -> 0 | T22: =SUMIF($D$5:$D$14,$H22,T$5:T$14) -> 0 | U22: =SUMIF($D$5:$D$14,$H22,U$5:U$14) -> 10.4
H23: PPA | I23: =SUMIF($D$5:$D$14,$H23,I$5:I$14) -> 0 | M23: =SUMIF($D$5:$D$14,$H23,M$5:M$14) -> 0 | N23: =SUMIF($D$5:$D$14,$H23,N$5:N$14) -> 0 | O23: =SUMIF($D$5:$D$14,$H23,O$5:O$14) -> 0 | P23: =SUMIF($D$5:$D$14,$H23,P$5:P$14) -> 0 | Q23: =SUMIF($D$5:$D$14,$H23,Q$5:Q$14) -> 0 | R23: =SUMIF($D$5:$D$14,$H23,R$5:R$14) -> 0 | S23: =SUMIF($D$5:$D$14,$H23,S$5:S$14) -> 0 | T23: =SUMIF($D$5:$D$14,$H23,T$5:T$14) -> 0 | U23: =SUMIF($D$5:$D$14,$H23,U$5:U$14) -> 0
H24: Group | I24: =SUMIF($D$5:$D$14,$H24,I$5:I$14) -> 171.6 | M24: =SUMIF($D$5:$D$14,$H24,M$5:M$14) -> 0 | N24: =SUMIF($D$5:$D$14,$H24,N$5:N$14) -> 0 | O24: =SUMIF($D$5:$D$14,$H24,O$5:O$14) -> 0 | P24: =SUMIF($D$5:$D$14,$H24,P$5:P$14) -> 0 | Q24: =SUMIF($D$5:$D$14,$H24,Q$5:Q$14) -> 0 | R24: =SUMIF($D$5:$D$14,$H24,R$5:R$14) -> 0 | S24: =SUMIF($D$5:$D$14,$H24,S$5:S$14) -> 0 | T24: =SUMIF($D$5:$D$14,$H24,T$5:T$14) -> 0 | U24: =SUMIF($D$5:$D$14,$H24,U$5:U$14) -> 0
H25: EPC | I25: =SUMIF($D$5:$D$14,$H25,I$5:I$14) -> 0 | M25: =SUMIF($D$5:$D$14,$H25,M$5:M$14) -> 0 | N25: =SUMIF($D$5:$D$14,$H25,N$5:N$14) -> 0 | O25: =SUMIF($D$5:$D$14,$H25,O$5:O$14) -> 0 | P25: =SUMIF($D$5:$D$14,$H25,P$5:P$14) -> 0 | Q25: =SUMIF($D$5:$D$14,$H25,Q$5:Q$14) -> 0 | R25: =SUMIF($D$5:$D$14,$H25,R$5:R$14) -> 0 | S25: =SUMIF($D$5:$D$14,$H25,S$5:S$14) -> 0 | T25: =SUMIF($D$5:$D$14,$H25,T$5:T$14) -> 0 | U25: =SUMIF($D$5:$D$14,$H25,U$5:U$14) -> 0
H26: Total | I26: =SUM(I22:I25) -> 780 | M26: =SUM(M22:M25) -> 41.6 | N26: =SUM(N22:N25) -> 0 | O26: =SUM(O22:O25) -> 0 | P26: =SUM(P22:P25) -> 0 | Q26: =SUM(Q22:Q25) -> 0 | R26: =SUM(R22:R25) -> 0 | S26: =SUM(S22:S25) -> 0 | T26: =SUM(T22:T25) -> 0 | U26: =SUM(U22:U25) -> 10.4
I27: =I18/5.2-54 -> 96
A28: FY 2025-26 | Khavda Wind Projects Monthly Commissioning Plan (MWac) (Phase-03)
A29: Sl. | B29: Project | C29: SPV | D29: Category | E29: Total Capacity (MW) | F29: Total WTG Nos. | G29: PSS No. | H29: PSS Charging Date | I29: Till Mar-25 | J29: 45748 | K29: 45778 | L29: 45809 | M29: 45839 | N29: 45870 | O29: 45901 | P29: 45931 | Q29: 45962 | R29: 45992 | S29: 46023 | T29: 46054 | U29: 46082 | W29: FY 25-26 Total (Plan) | Y29: FY 25-26 Commissioned till Nov-25 | AA29: FY 24-25 Commissioned | AC29: Total Commissioned till Nov-25
W30: WTG | X30: MW | Y30: WTG | Z30: MW | AA30: WTG | AB30: MW | AC30: WTG | AD30: MW
A31: 1 | B31: Google Hybrid (Wind) | C31: ARE3L | D31: Merchant | E31: =5*5.2 -> 26 | F31: =E31/5.2 -> 5 | G31: PSS-08 | H31: =H16 -> Charged | M31: =5*5.2 -> 26 | R31: nnd--2 | W31: =+X31/5.2 -> 5 | X31: =+SUM(J31:U31) -> 26 | Y31: =+Z31/5.2 -> 5 | Z31: =+SUM(J31:Q31) -> 26 | AA31: NA | AB31: NA | AC31: =+AD31/5.2 -> 5 | AD31: =+Z31 -> 26 | AE31: =SUM(I31:AD31)/5.2 -> 22.884615 | AF31: =AE31-F31 -> 17.884615
A32: 2 | B32: AGEL Hybrid Merchant (Wind) | C32: ASEJ6PL | D32: Merchant | E32: =12*5.2 -> 62.4 | F32: =E32/5.2 -> 12 | G32: PSS-08 | H32: =H31 -> Charged | R32: =4*5.2 -> 20.8 | S32: =3*5.2 -> 15.6 | T32: =5*5.2 -> 26 | W32: =+X32/5.2 -> 12 | X32: =+SUM(J32:U32) -> 62.4 | Y32: =+Z32/5.2 -> 0 | Z32: =+SUM(J32:Q32) -> 0 | AA32: NA | AB32: NA | AC32: =+AD32/5.2 -> 0 | AD32: =+Z32 -> 0 | AE32: =SUM(I32:AD32)/5.2 -> 26.307692 | AF32: =AE32-F32 -> 14.307692
A33: 3 | B33: AGEL Merchant (Wind) | C33: AGE25BL | D33: Merchant | E33: =2*5.2 -> 10.4 | F33: 2 | G33: PSS-09 | H33: Charged | R33: =1*5.2 -> 5.2 | S33: =1*5.2 -> 5.2 | W33: =+X33/5.2 -> 2 | X33: =+SUM(J33:U33) -> 10.4 | Y33: =+Z33/5.2 -> 0 | Z33: =+SUM(J33:Q33) -> 0 | AA33: NA | AB33: NA | AC33: =+AD33/5.2 -> 0 | AD33: =+Z33 -> 0 | AE33: =SUM(I33:AD33)/5.2 -> 4.3846154 | AF33: =AE33-F33 -> 2.3846154
A34: 4 | B34: SECI H-3 (Wind) | C34: AHEJ5L | D34: PPA | E34: =39*5.2 -> 202.8 | F34: =E34/5.2 -> 39 | G34: PSS-05 | H34: Charged | P34: =15*5.2 -> 78 | Q34: =16*5.2 -> 83.2 | R34: =4*5.2 -> 20.8 | U34: =4*5.2 -> 20.8 | W34: =+X34/5.2 -> 39 | X34: =+SUM(J34:U34) -> 202.8 | Y34: =+Z34/5.2 -> 31 | Z34: =+SUM(J34:Q34) -> 161.2 | AA34: NA | AB34: NA | AC34: =+AD34/5.2 -> 31 | AD34: =+Z34 -> 161.2 | AE34: =SUM(I34:AD34)/5.2 -> 159.42308 | AF34: =AE34-F34 -> 120.42308
A35: 5 | B35: AGEL Merchant (Wind) | C35: AGE25CL | D35: Merchant | E35: =36*5.2 -> 187.2 | F35: =E35/5.2 -> 36 | G35: PSS-11 | H35: ='[1]FY 24-26 Khavda Solar '!M31 -> 45900 | R35: =20*5.2 -> 104 | S35: =15*5.2 -> 78 | T35: =1*5.2 -> 5.2 | W35: =+X35/5.2 -> 36 | X35: =+SUM(J35:U35) -> 187.2 | Y35: =+Z35/5.2 -> 0 | Z35: =+SUM(J35:Q35) -> 0 | AA35: NA | AB35: NA | AC35: =+AD35/5.2 -> 0 | AD35: =+Z35 -> 0 | AE35: =SUM(I35:AD35)/5.2 -> 78.923077 | AF35: =AE35-F35 -> 42.923077
A36: 6 | B36: AGEL Merchant (Wind) | C36: AGE26AL | D36: Merchant | E36: =27*5.2 -> 140.4 | F36: =E36/5.2 -> 27 | G36: PSS-12 | H36: 45900 | S36: =19*5.2 -> 98.8 | T36: =8*5.2 -> 41.6 | W36: =+X36/5.2 -> 27 | X36: =+SUM(J36:U36) -> 140.4 | Y36: =+Z36/5.2 -> 0 | Z36: =+SUM(J36:Q36) -> 0 | AA36: NA | AB36: NA | AC36: =+AD36/5.2 -> 0 | AD36: =+Z36 -> 0 | AE36: =SUM(I36:AD36)/5.2 -> 59.192308 | AF36: =AE36-F36 -> 32.192308
A37: 8 | B37: AGEL Merchant (Wind) | C37: AGE25CL | D37: Merchant | E37: =13*5.2 -> 67.6 | F37: =E37/5.2 -> 13 | G37: PSS-14 | H37: 45991 | T37: =5*5.2 -> 26 | U37: =8*5.2 -> 41.6 | W37: =+X37/5.2 -> 13 | X37: =+SUM(J37:U37) -> 67.6 | Y37: =+Z37/5.2 -> 0 | Z37: =+SUM(J37:Q37) -> 0 | AA37: NA | AB37: NA | AC37: =+AD37/5.2 -> 0 | AD37: =+Z37 -> 0 | AE37: =SUM(I37:AD37)/5.2 -> 28.5 | AF37: =AE37-F37 -> 15.5
A38: 9 | B38: AGEL Merchant (Wind) | C38: AGE26AL | D38: Merchant | E38: =60*5.2 -> 312 | F38: =E38/5.2 -> 60 | G38: PSS-14 | H38: 45991 | S38: =4*5.2 -> 20.8 | T38: =24*5.2 -> 124.8 | U38: =32*5.2 -> 166.4 | W38: =+X38/5.2 -> 60 | X38: =+SUM(J38:U38) -> 312 | Y38: =+Z38/5.2 -> 0 | Z38: =+SUM(J38:Q38) -> 0 | AA38: NA | AB38: NA | AC38: =+AD38/5.2 -> 0 | AD38: =+Z38 -> 0 | AE38: =SUM(I38:AD38)/5.2 -> 131.53846 | AF38: =AE38-F38 -> 71.538462
A39: Monthwise FY 25-26 Projects (B) - Total (MW) | E39: =SUM(E25:E38) -> 1008.8 | I39: =SUM(I31:I38) -> 0 | J39: =SUM(J31:J38) -> 0 | K39: =SUM(K31:K38) -> 0 | L39: =SUM(L31:L38) -> 0 | M39: =SUM(M31:M38) -> 26 | N39: =SUM(N31:N38) -> 0 | O39: =SUM(O31:O38) -> 0 | P39: =SUM(P31:P38) -> 78 | ... U39: =SUM(U31:U38) -> 228.8 | W39: =+X39/5.2 -> 194 | X39: =+SUM(J39:U39) -> 1008.8 | Y39: =+Z39/5.2 -> 36 | Z39: =+SUM(J39:Q39) -> 187.2 | AA39: NA | AB39: NA | AC39: =+AD39/5.2 -> 36 | AD39: =+Z39 -> 187.2
A40: Monthwise FY 25-26 Projects (B) - Total (WTGs) | F40: =SUM(F25:F38) -> 194 | I40: =I39/5.2 -> 0 | J40: =J39/5.2 -> 0 | K40: =K39/5.2 -> 0 | L40: =L39/5.2 -> 0 | M40: =M39/5.2 -> 5 | N40: =N39/5.2 -> 0 | O40: =O39/5.2 -> 0 | P40: =P39/5.2 -> 15 | ... U40: =U39/5.2 -> 44
A42: Monthwise FY 24-26 Projects (A+B) - Total (MW) | E42: =SUM(E39,E18) -> 2329.6 | I42: =SUM(I39,I18) -> 780 | J42: =SUM(J39,J18) -> 104 | K42: =SUM(K39,K18) -> 26 | L42: =SUM(L39,L18) -> 161.2 | M42: =SUM(M39,M18) -> 67.6 | N42: =SUM(N39,N18) -> 124.8 | O42: =SUM(O39,O18) -> 31.2 | P42: =SUM(P39,P18) -> 78 | ... U42: =SUM(U39,U18) -> 239.2 | W42: =+X42/5.2 -> 298 | X42: =SUM(X39,X18) -> 1549.6 | Y42: =+Z42/5.2 -> 137 | Z42: =SUM(Z39,Z18) -> 712.4 | AA42: =+AB42/5.2 -> 150 | AB42: =SUM(AA39,AB18) -> 780 | AC42: =+AD42/5.2 -> 287 | AD42: =SUM(AD39,AD18) -> 1492.4
J43: =SUM(J42:L42) -> 291.2 | M43: =SUM(M42:O42) -> 223.6 | P43: =SUM(P42:R42) -> 348.4 | S43: =SUM(S42:U42) -> 686.4 | W43: =SUM(X40,X19) -> 0
A44: Monthwise FY 24-26 Projects (A+B) - Total (WTGs) | F44: =SUM(F40,F19) -> 448 | I44: =SUM(I40,I19) -> 150 | J44: =SUM(J40,J19) -> 20 | K44: =SUM(K40,K19) -> 5 | L44: =SUM(L40,L19) -> 31 | M44: =SUM(M40,M19) -> 13 | N44: =SUM(N40,N19) -> 24 | O44: =SUM(O40,O19) -> 6 | P44: =SUM(P40,P19) -> 15 | ... U44: =SUM(U40,U19) -> 46
H45: =H43+H19 -> 0 | J45: =SUM(J44:L44) -> 56 | M45: =SUM(M44:O44) -> 43 | P45: =SUM(P44:R44) -> 67 | S45: =SUM(S44:U44) -> 132
B46: Note : WTG Commissioning of PSS-11 & 12 is linked with PSS charging.
H47: PSS Charging Date | I47: Till Mar-25 | J47: 45748 | K47: 45778 | L47: 45809 | M47: 45839 | N47: 45870 | O47: 45901 | P47: 45931 | Q47: 45962 | R47: 45992 | S47: 46023 | T47: 46054 | U47: 46082 | W47: FY 25-26 Total (Plan) | Y47: FY 25-26 Commissioned till Nov-25 | AA47: FY 24-25 Commissioned | AC47: Total Commissioned till Nov-25
W48: WTG | X48: MW | Y48: WTG | Z48: MW | AA48: WTG | AB48: MW | AC48: WTG | AD48: MW
B49: Overall Status | C49: WTG | D49: MW | G49: PPA | H49: PPA | I49: =SUMIF($D$5:$D$38,$H49,I$5:U$38) -> 0 | J49: =SUMIF($D$5:$D$38,$H49,J$5:AE$38) -> 0 | K49: =SUMIF($D$5:$D$38,$H49,K$5:AF$38) -> 0 | L49: =SUMIF($D$5:$D$38,$H49,L$5:AG$38) -> 0 | M49: =SUMIF($D$5:$D$38,$H49,M$5:AH$38) -> 0 | N49: =SUMIF($D$5:$D$38,$H49,N$5:AI$38) -> 0 | O49: =SUMIF($D$5:$D$38,$H49,O$5:AJ$38) -> 0 | P49: =SUMIF($D$5:$D$38,$H49,P$5:AK$38) -> 78 | Q49: =SUMIF($D$5:$D$38,$H49,Q$5:AL$38) -> 83.2 | ... U49: =SUMIF($D$5:$D$38,$H49,U$5:AP$38) -> 20.8 | W49: =+X49/5.2 -> 39 | X49: =+SUM(J49:U49) -> 202.8 | Y49: =+Z49/5.2 -> 31 | Z49: =+SUM(J49:Q49) -> 161.2 | AA49: =+AB49/5.2 -> 0 | AB49: =SUMIF($D$5:$D$38,$H49,AB$5:AP$38) -> 0 | AC49: =+AD49/5.2 -> 31 | AD49: =+AB49+Z49 -> 161.2
B50: Total Plan | C50: =+W52+AA52 -> 448 | D50: =+X52+AB52 -> 2329.6 | G50: Merchant | H50: Merchant | I50: =SUMIF($D$5:$D$38,$H50,I$5:U$38) -> 608.4 | J50: =SUMIF($D$5:$D$38,$H50,J$5:AE$38) -> 104 | K50: =SUMIF($D$5:$D$38,$H50,K$5:AF$38) -> 0 | L50: =SUMIF($D$5:$D$38,$H50,L$5:AG$38) -> 130 | M50: =SUMIF($D$5:$D$38,$H50,M$5:AH$38) -> 67.6 | N50: =SUMIF($D$5:$D$38,$H50,N$5:AI$38) -> 124.8 | O50: =SUMIF($D$5:$D$38,$H50,O$5:AJ$38) -> 31.2 | P50: =SUMIF($D$5:$D$38,$H50,P$5:AK$38) -> 0 | Q50: =SUMIF($D$5:$D$38,$H50,Q$5:AL$38) -> 36.4 | ... U50: =SUMIF($D$5:$D$38,$H50,U$5:AP$38) -> 218.4 | W50: =+X50/5.2 -> 248 | X50: =+SUM(J50:U50) -> 1289.6 | Y50: =+Z50/5.2 -> 95 | Z50: =+SUM(J50:Q50) -> 494 | AA50: =+AB50/5.2 -> 117 | AB50: =SUMIF($D$5:$D$38,$H50,AB$5:AP$38) -> 608.4 | AC50: =+AD50/5.2 -> 212 | AD50: =+AB50+Z50 -> 1102.4
B51: Total Actual | C51: =+Y52+AA52 -> 287 | D51: =+Z52+AB52 -> 1492.4 | G51: Group | H51: Group | I51: =SUMIF($D$5:$D$38,$H51,I$5:U$38) -> 171.6 | J51: =SUMIF($D$5:$D$38,$H51,J$5:AE$38) -> 0 | K51: =SUMIF($D$5:$D$38,$H51,K$5:AF$38) -> 26 | L51: =SUMIF($D$5:$D$38,$H51,L$5:AG$38) -> 31.2 | M51: =SUMIF($D$5:$D$38,$H51,M$5:AH$38) -> 0 | N51: =SUMIF($D$5:$D$38,$H51,N$5:AI$38) -> 0 | O51: =SUMIF($D$5:$D$38,$H51,O$5:AJ$38) -> 0 | P51: =SUMIF($D$5:$D$38,$H51,P$5:AK$38) -> 0 | Q51: =SUMIF($D$5:$D$38,$H51,Q$5:AL$38) -> 0 | ... U51: =SUMIF($D$5:$D$38,$H51,U$5:AP$38) -> 0 | W51: =+X51/5.2 -> 11 | X51: =+SUM(J51:U51) -> 57.2 | Y51: =+Z51/5.2 -> 11 | Z51: =+SUM(J51:Q51) -> 57.2 | AA51: =+AB51/5.2 -> 33 | AB51: =SUMIF($D$5:$D$38,$H51,AB$5:AP$38) -> 171.6 | AC51: =+AD51/5.2 -> 44 | AD51: =+AB51+Z51 -> 228.8
H52: Total | I52: =SUM(I49:I51) -> 780 | J52: =SUM(J49:J51) -> 104 | K52: =SUM(K49:K51) -> 26 | L52: =SUM(L49:L51) -> 161.2 | M52: =SUM(M49:M51) -> 67.6 | N52: =SUM(N49:N51) -> 124.8 | O52: =SUM(O49:O51) -> 31.2 | P52: =SUM(P49:P51) -> 78 | ... U52: =SUM(U49:U51) -> 239.2 | W52: =+X52/5.2 -> 298 | X52: =+SUM(J52:U52) -> 1549.6 | Y52: =+Z52/5.2 -> 137 | Z52: =+SUM(J52:Q52) -> 712.4 | AA52: =+AB52/5.2 -> 150 | AB52: =SUM(AB49:AB51) -> 780 | AC52: =+AD52/5.2 -> 287 | AD52: =+AB52+Z52 -> 1492.4
H54: FY 2024-26 | Khavda Wind Projects Monthly Commissioning Plan (MWac)
H55: Category | I55: Till Dec-24 | J55: 45748 | K55: 45778 | S55: 46023 | T55: 46054 | U55: 46082
H56: Merchant | I56: =I22+I50 -> 1216.8 | J56: =J22+J50 -> 104 | K56: =K22+K50 -> 0 | S56: =S22+S50 -> 223.6 | T56: =T22+T50 -> 223.6 | U56: =U22+U50 -> 228.8
H57: PPA | I57: =I23+I49 -> 0 | J57: =J23+J49 -> 0 | K57: =K23+K49 -> 0 | S57: =S23+S49 -> 0 | T57: =T23+T49 -> 0 | U57: =U23+U49 -> 20.8
H58: Group | I58: =I24+I51 -> 343.2 | J58: =J24+J51 -> 0 | K58: =K24+K51 -> 26 | S58: =S24+S51 -> 0 | T58: =T24+T51 -> 0 | U58: =U24+U51 -> 0
H59: EPC | I59: =I25+#REF! -> #REF! | J59: =J25+#REF! -> #REF! | K59: =K25+#REF! -> #REF! | S59: =S25+#REF! -> #REF! | T59: =T25+#REF! -> #REF! | U59: =U25+#REF! -> #REF!
H60: Total | I60: =SUM(I56:I59) -> #REF! | J60: =SUM(J56:J59) -> #REF! | K60: =SUM(K56:K59) -> #REF! | S60: =SUM(S56:S59) -> #REF! | T60: =SUM(T56:T59) -> #REF! | U60: =SUM(U56:U59) -> #REF!
I62: =I60/5.2 -> #REF! | J62: =J60/5.2 -> #REF! | K62: =K60/5.2 -> #REF! | S62: =S60/5.2 -> #REF! | T62: =T60/5.2 -> #REF! | U62: =U60/5.2 -> #REF!
J63: =SUM(I62:J62) -> #REF! | T63: =SUM(K62:T62) -> #REF!
I64: =I62 -> #REF! | J64: =J62+4 -> #REF! | K64: =K62 -> #REF! | S64: =S62-9 -> #REF! | T64: =T62-45 -> #REF! | U64: =U62 -> #REF!
J65: =SUM(I64:J64) -> #REF! | T65: =SUM(K64:T64) -> #REF!
J67: =J39/5.2 -> 0 | K67: =K39/5.2 -> 0 | S67: =S39/5.2 -> 42 | T67: =T39/5.2 -> 43 | U67: =U39/5.2 -> 44
J68: =J18+J39 -> 104 | K68: =K18+K39 -> 26 | S68: =S18+S39 -> 223.6 | T68: =T18+T39 -> 223.6 | U68: =U18+U39 -> 239.2

Sheet Wind Mundra
A1: FY 2025-26 | Wind Projects (O/S Khavda Monthly Commissioning Plan (MWac) | R1: Date: 1-Oct-25
A2: Priority | B2: Project | C2: SPV | D2: Location | E2: Category | F2: Category | G2: Capacity (MW) | H2: 45748 | I2: 45778 | J2: 45809 | K2: 45839 | L2: 45870 | M2: 45901 | N2: 45931 | O2: 45962 | P2: 45992 | Q2: 46023 | R2: 46054 | S2: 46082
A3: P-01 | B3: AGEL Merchant (Wind) | C3: AGE32L | D3: Mandvi | E3: Merchant-Wind | F3: Merchant | G3: =79*3.3 -> 260.7
A4: P-02 | B4: AGEL Merchant (Wind) | C4: AWEK3L | D4: Mundra North | E4: Merchant-Wind | F4: Merchant | G4: =98*3.3 -> 323.4 | S4: =60*3.3 -> 198
A6: Total | G6: =SUM(G3:G5) -> 584.1 | H6: =SUM(H3:H5) -> 0 | I6: =SUM(I3:I5) -> 0 | J6: =SUM(J3:J5) -> 0 | K6: =SUM(K3:K5) -> 0 | L6: =SUM(L3:L5) -> 0 | M6: =SUM(M3:M5) -> 0 | N6: =SUM(N3:N5) -> 0 | ... S6: =SUM(S3:S5) -> 198
H8: 45748 | I8: 45778 | J8: 45809 | K8: 45839 | L8: 45870 | M8: 45901 | N8: 45931 | O8: 45962 | P8: 45992 | Q8: 46023 | R8: 46054 | S8: 46082
H9: =SUMIF($F$3:$F$5,#REF!,H$3:H$5) -> 0 | I9: =SUMIF($F$3:$F$5,#REF!,I$3:I$5) -> 0 | J9: =SUMIF($F$3:$F$5,#REF!,J$3:J$5) -> 0 | K9: =SUMIF($F$3:$F$5,#REF!,K$3:K$5) -> 0 | L9: =SUMIF($F$3:$F$5,#REF!,L$3:L$5) -> 0 | M9: =SUMIF($F$3:$F$5,#REF!,M$3:M$5) -> 0 | N9: =SUMIF($F$3:$F$5,#REF!,N$3:N$5) -> 0 | O9: =SUMIF($F$3:$F$5,#REF!,O$3:O$5) -> 0 | ... S9: =SUMIF($F$3:$F$5,#REF!,S$3:S$5) -> 0
H10: =SUMIF($F$3:$F$5,#REF!,H$3:H$5) -> 0 | I10: =SUMIF($F$3:$F$5,#REF!,I$3:I$5) -> 0 | J10: =SUMIF($F$3:$F$5,#REF!,J$3:J$5) -> 0 | K10: =SUMIF($F$3:$F$5,#REF!,K$3:K$5) -> 0 | L10: =SUMIF($F$3:$F$5,#REF!,L$3:L$5) -> 0 | M10: =SUMIF($F$3:$F$5,#REF!,M$3:M$5) -> 0 | N10: =SUMIF($F$3:$F$5,#REF!,N$3:N$5) -> 0 | O10: =SUMIF($F$3:$F$5,#REF!,O$3:O$5) -> 0 | ... S10: =SUMIF($F$3:$F$5,#REF!,S$3:S$5) -> 0
H11: =SUMIF($F$3:$F$5,#REF!,H$3:H$5) -> 0 | I11: =SUMIF($F$3:$F$5,#REF!,I$3:I$5) -> 0 | J11: =SUMIF($F$3:$F$5,#REF!,J$3:J$5) -> 0 | K11: =SUMIF($F$3:$F$5,#REF!,K$3:K$5) -> 0 | L11: =SUMIF($F$3:$F$5,#REF!,L$3:L$5) -> 0 | M11: =SUMIF($F$3:$F$5,#REF!,M$3:M$5) -> 0 | N11: =SUMIF($F$3:$F$5,#REF!,N$3:N$5) -> 0 | O11: =SUMIF($F$3:$F$5,#REF!,O$3:O$5) -> 0 | ... S11: =SUMIF($F$3:$F$5,#REF!,S$3:S$5) -> 0
H12: =SUMIF($F$3:$F$5,#REF!,H$3:H$5) -> 0 | I12: =SUMIF($F$3:$F$5,#REF!,I$3:I$5) -> 0 | J12: =SUMIF($F$3:$F$5,#REF!,J$3:J$5) -> 0 | K12: =SUMIF($F$3:$F$5,#REF!,K$3:K$5) -> 0 | L12: =SUMIF($F$3:$F$5,#REF!,L$3:L$5) -> 0 | M12: =SUMIF($F$3:$F$5,#REF!,M$3:M$5) -> 0 | N12: =SUMIF($F$3:$F$5,#REF!,N$3:N$5) -> 0 | O12: =SUMIF($F$3:$F$5,#REF!,O$3:O$5) -> 0 | ... S12: =SUMIF($F$3:$F$5,#REF!,S$3:S$5) -> 0
H13: =SUM(H9:H12) -> 0 | I13: =SUM(I9:I12) -> 0 | J13: =SUM(J9:J12) -> 0 | K13: =SUM(K9:K12) -> 0 | L13: =SUM(L9:L12) -> 0 | M13: =SUM(M9:M12) -> 0 | N13: =SUM(N9:N12) -> 0 | O13: =SUM(O9:O12) -> 0 | ... S13: =SUM(S9:S12) -> 0
